Workbook
Name \0: #REF!
Name \a: #N/A
Name \b: #N/A
Name \c: #N/A
Name \d: #N/A
Name \e: #N/A
Name \f: #N/A
Name \g: #N/A
Name \h: #N/A
Name \i: #N/A
Name \j: #N/A
Name \k: #N/A
Name \l: #N/A
Name \m: #N/A
Name \n: #N/A
Name \o: #N/A
Name \p: #N/A
Name \q: #N/A
Name \s: #N/A
Name \u: '[1]2010-2015'!#REF!
Name \v: #N/A
Name \x: #N/A
Name \z: #N/A
Name ___mds_first_cell___: #N/A
Name ___mds_view_data___: #N/A
Name __DAT2: #N/A
Name __shared_1_0_0: #REF!-#REF!
Name __shared_1_0_1: #REF!*#REF!
Name __shared_1_0_10: #REF!*#REF!
Name __shared_1_0_11: #REF!*#REF!
Name __shared_1_0_12: #REF!*#REF!
Name __shared_1_0_13: #REF!*#REF!
Name __shared_1_0_14: (((#REF!+#REF!)*(1+#REF!)*#REF!)-#REF!)
Name __shared_1_0_15: #REF!+#REF!+#REF!
Name __shared_1_0_16: #REF!/(1-#REF!)
Name __shared_1_0_17: (#REF!/(1-(#REF!+#REF!+#REF!)))
Name __shared_1_0_18: #REF!/(1-#REF!)
Name __shared_1_0_19: (((#REF!+#REF!)*(1+#REF!)*#REF!)-#REF!)
Name __shared_1_0_2: #REF!/(1-#REF!)
Name __shared_1_0_20: #REF!+#REF!+#REF!
Name __shared_1_0_21: IF(#REF!>#REF!,"REVISAR","OK")
Name __shared_1_0_22: (#REF!/(1-(#REF!+#REF!+#REF!)))
Name __shared_1_0_23: #REF!/(1-#REF!)
Name __shared_1_0_24: #REF!*#REF!
Name __shared_1_0_25: (((#REF!+#REF!)*(1+#REF!))*#REF!)-#REF!
Name __shared_1_0_26: #REF!+#REF!+#REF!
Name __shared_1_0_27: #REF!-#REF!-#REF!-#REF!-#REF!
Name __shared_1_0_28: #REF!*#REF!
Name __shared_1_0_29: (#REF!-#REF!)/#REF!
Name __shared_1_0_3: #REF!*#REF!
Name __shared_1_0_30: #REF!-#REF!
Name __shared_1_0_31: (#REF!/(1-(#REF!+#REF!+#REF!)))
Name __shared_1_0_32: #REF!*#REF!
Name __shared_1_0_33: #REF!/(1-#REF!)
Name __shared_1_0_34: (#REF!/(1-(#REF!+#REF!+#REF!)))
Name __shared_1_0_35: #REF!/(1-#REF!)
Name __shared_1_0_36: #REF!*#REF!
Name __shared_1_0_37: #REF!*#REF!
Name __shared_1_0_38: #REF!*#REF!
Name __shared_1_0_39: #REF!*#REF!

Sheet LISTA PREÇO 2022-Vigen 01.02.22
A4: LISTA DE PREÇO: Nº 052021 - Vigência: 01/08/2021
A5: LISTA DE PREÇO FABRICA E PREÇO MÁXIMO CONSUMIDOR | J5: Preço Lista | M5: Politica 1% s/ PV Base | P5: Politica 7% s/ B22 | S5: Politica 13% s/ B22 | V5: Politica 6% s/ B22 | Y5: Politica 12% s/ B22 | AB5: Politica 18% s/ B22 | AF5: Politica NA | AI5: Politica NA | AL5: Politica NA | AO5: Politica NA | AR5: Politica NA | AU5: ICMS 0% | AW5: ICMS 12% | AY5: ICMS 17% | BA5: ICMS 17,5% | BC5: ICMS 18% | BE5: ICMS 20% | BG5: ICMS 17% (ALC) | BI5: ICMS 17,5% (ALC) | BK5: ICMS 18% (ALC)
A6: Empresa | B6: Canal | C6: EAN | D6: Código CIGAM | E6: Código SAP | F6: Descrição | G6: NCM | H6: Status | I6: UN/CX | J6: PV BASE | L6: Preço Médio | M6: B22 | N6: % B21 | P6: DPN | Q6: % DPN | S6: PRIME | T6: % PRIME | V6: COMBATE | W6: % COMBATE | Y6: REGIONAL | Z6: % REGIONAL | AB6: PROFISSIONAL | AC6: % REGIONAL | AE6: MG | AF6: % REGIONAL | AH6: PAGUE MENOS | AI6: % PM | AK6: RD | AL6: % RD | AN6: DPSP | AO6: % DPSP | AQ6: CONDE | AR6: % CONDE | AT6: PF 18% (SAP) | AU6: PF | AV6: PMC | AW6: PF | AX6: PMC | AY6: PF | AZ6: PMC | BA6: PF | BB6: PMC | BC6: PF | BD6: PMC | BE6: PF | BF6: PMC | BG6: PF | BH6: PMC | BI6: PF | BJ6: PMC | BK6: PF | BL6: PMC | BM6: Lista PIS/COFINS | BN6: Categoria de Grupo CMED
A7: Natulab | B7: Medicamentos | C7: 7899470804828 | D7: 43890 | E7: 15000145 | F7: AD-VITAM SOL GOT X 20ML | G7: 30045040 | H7: ATIVO | I7: 50 | J7: 4.23 | L7: 4.15 | M7: 4.23 | N7: =IFERROR(100%-(J7/M7),"") -> 0 | P7: 4.55 | Q7: =IFERROR(100%-(M7/P7),0) -> 0.07032967 | S7: 4.89 | T7: =IFERROR(100%-(M7/S7),0) -> 0.13496933 | V7: 4.2875564 | W7: =IFERROR(100%-(M7/V7),0) -> 0.01342406 | Y7: 4.5798898 | Z7: =IFERROR(100%-(M7/Y7),0) -> 0.076396992 | AB7: 4.9150037 | AC7: =IFERROR(100%-(M7/AB7),0) -> 0.13936992 | AE7: 4.0507614 | AF7: =IFERROR(100%-(M7/AE7),0) -> -0.04424812 | AH7: 0 | AI7: =IFERROR(100%-(M7/AH7),0) -> 0 | AK7: 0 | AL7: =IFERROR(100%-(M7/AK7),0) -> 0 | AN7: 0 | AO7: =IFERROR(100%-(M7/AN7),0) -> 0 | AR7: =IFERROR(100%-(P7/AQ7),0) -> 0 | AT7: 12.14 | AU7: 9.68 | AV7: 12.98 | AW7: 11.19 | AX7: 14.94 | AY7: 11.97 | AZ7: 15.95 | BA7: 12.05 | BB7: 16.05 | BC7: 12.14 | BD7: 16.17 | BE7: 12.49 | BF7: 16.63 | BG7: 10.42 | BH7: 14.41 | BI7: 10.49 | BJ7: 14.5 | BK7: 10.55 | BL7: 14.59 | BM7: Negativa | BN7: Grupo 2
A8: Natulab | B8: Medicamentos | C8: 7898133136535 | D8: 23646 | E8: 15000153 | F8: Afolic Comprimido 5mg 1bl X 20com X 200ct - Farma | G8: 30045090 | H8: ATIVO | I8: 200 | J8: 1.47 | L8: 1.54 | M8: 1.47 | N8: =IFERROR(100%-(J8/M8),0) -> 0 | P8: 1.58 | Q8: =IFERROR(100%-(M8/P8),0) -> 0.069620253 | S8: 1.7 | T8: =IFERROR(100%-(M8/S8),0) -> 0.13529412 | V8: 1.4904449 | W8: =IFERROR(100%-(M8/V8),0) -> 0.013717297 | Y8: 1.5920661 | Z8: =IFERROR(100%-(M8/Y8),0) -> 0.076671512 | AB8: 1.7085588 | AC8: =IFERROR(100%-(M8/AB8),0) -> 0.13962573 | AE8: 1.3401015 | AF8: =IFERROR(100%-(M8/AE8),0) -> -0.096931818 | AH8: 1.4 | AI8: =IFERROR(100%-(M8/AH8),0) -> -0.05 | AK8: 4.3575 | AL8: =IFERROR(100%-(M8/AK8),0) -> 0.6626506 | AN8: 0 | AO8: =IFERROR(100%-(M8/AN8),0) -> 0 | AR8: =IFERROR(100%-(P8/AQ8),0) -> 0 | AT8: 8.83 | AU8: 7.04 | AV8: 9.44 | AW8: 8.14 | AX8: 10.87 | AY8: 8.7 | AZ8: 11.59 | BA8: 8.76 | BB8: 11.67 | BC8: 8.83 | BD8: 11.76 | BE8: 9.09 | BF8: 12.1 | BG8: 7.58 | BH8: 10.48 | BI8: 7.63 | BJ8: 10.55 | BK8: 7.67 | BL8: 10.6 | BM8: Negativa | BN8: Grupo 3
A9: Natulab | B9: Medicamentos | C9: 7898133139741 | D9: 34232 | E9: 15000133 | F9: Aftliv 25ml 1ct X 100fr - Farma | G9: 30042029 | H9: ATIVO | I9: 200 | J9: 7.12 | L9: 6.98 | M9: 7.12 | N9: =IFERROR(100%-(J9/M9),0) -> 0 | P9: 7.66 | Q9: =IFERROR(100%-(M9/P9),0) -> 0.070496084 | S9: 8.23 | T9: =IFERROR(100%-(M9/S9),0) -> 0.13487242 | V9: 7.2156458 | W9: =IFERROR(100%-(M9/V9),0) -> 0.013255337 | Y9: 7.7076217 | Z9: =IFERROR(100%-(M9/Y9),0) -> 0.076239039 | AB9: 8.271594 | AC9: =IFERROR(100%-(M9/AB9),0) -> 0.13922274 | AE9: 6.5076142 | AF9: =IFERROR(100%-(M9/AE9),0) -> -0.094102964 | AH9: 6.78 | AI9: =IFERROR(100%-(M9/AH9),0) -> -0.050147493 | AK9: 9.9596 | AL9: =IFERROR(100%-(M9/AK9),0) -> 0.28511185 | AN9: 0 | AO9: =IFERROR(100%-(M9/AN9),0) -> 0 | AR9: =IFERROR(100%-(P9/AQ9),0) -> 0 | AT9: 35.57 | AU9: 28.38 | AV9: 38.07 | AW9: 32.8 | AX9: 43.81 | AY9: 35.07 | AZ9: 46.74 | BA9: 35.32 | BB9: 47.06 | BC9: 35.57 | BD9: 47.39 | BE9: 36.6 | BF9: 48.72 | BG9: 30.54 | BH9: 42.22 | BI9: 30.72 | BJ9: 42.47 | BK9: 30.91 | BL9: 42.73 | BM9: Negativa | BN9: Grupo 1
A10: Natulab | B10: Medicamentos | C10: 7899470801414 | D10: 23719 | E10: 15000155 | F10: Alcachofra Natulab 300mg 2bl X 15cap X 50ct - Farma | G10: 30044990 | H10: ATIVO | I10: 50 | J10: 7.85 | L10: 7.69 | M10: 7.85 | N10: =IFERROR(100%-(J10/M10),0) -> 0 | P10: 8.44 | Q10: =IFERROR(100%-(M10/P10),0) -> 0.069905213 | S10: 9.07 | T10: =IFERROR(100%-(M10/S10),0) -> 0.13450937 | V10: 7.9490393 | W10: =IFERROR(100%-(M10/V10),0) -> 0.012459283 | Y10: 8.4910193 | Z10: =IFERROR(100%-(M10/Y10),0) -> 0.075493797 | AB10: 9.1123134 | AC10: =IFERROR(100%-(M10/AB10),0) -> 0.13852831 | AE10: 7.1634518 | AF10: =IFERROR(100%-(M10/AE10),0) -> -0.09584042 | AH10: 0 | AI10: =IFERROR(100%-(M10/AH10),0) -> 0 | AK10: 0 | AL10: =IFERROR(100%-(M10/AK10),0) -> 0 | AN10: 0 | AO10: =IFERROR(100%-(M10/AN10),0) -> 0 | AR10: =IFERROR(100%-(P10/AQ10),0) -> 0 | AT10: 28.88 | AU10: 23.04 | AV10: 30.9 | AW10: 26.63 | AX10: 35.57 | AY10: 28.47 | AZ10: 37.94 | BA10: 28.67 | BB10: 38.2 | BC10: 28.88 | BD10: 38.48 | BE10: 29.72 | BF10: 39.56 | BG10: 24.79 | BH10: 34.27 | BI10: 24.94 | BJ10: 34.48 | BK10: 25.09 | BL10: 34.69 | BM10: Negativa | BN10: Grupo 2
A11: Natulab | B11: Medicamentos | C11: 7898133134456 | D11: 28582 | E11: 15000120 | F11: Alumimax 100ml Fn 1ct X 50fr - Farma | G11: 30049099 | H11: ATIVO | I11: 50 | J11: 3.04 | L11: 2.98 | M11: 3.04 | N11: =IFERROR(100%-(J11/M11),0) -> 0 | P11: 3.26 | Q11: =IFERROR(100%-(M11/P11),0) -> 0.067484663 | S11: 3.51 | T11: =IFERROR(100%-(M11/S11),0) -> 0.13390313 | V11: 3.0755212 | W11: =IFERROR(100%-(M11/V11),0) -> 0.011549642 | Y11: 3.2852158 | Z11: =IFERROR(100%-(M11/Y11),0) -> 0.074642218 | AB11: 3.5255974 | AC11: =IFERROR(100%-(M11/AB11),0) -> 0.13773479 | AE11: 2.8105797 | AF11: =IFERROR(100%-(M11/AE11),0) -> -0.081627376 | AH11: 0 | AI11: =IFERROR(100%-(M11/AH11),0) -> 0 | AK11: 0 | AL11: =IFERROR(100%-(M11/AK11),0) -> 0 | AN11: 0 | AO11: =IFERROR(100%-(M11/AN11),0) -> 0 | AR11: =IFERROR(100%-(P11/AQ11),0) -> 0 | AT11: 16.84 | AU11: 13.43 | AV11: 18.01 | AW11: 15.52 | AX11: 20.73 | AY11: 16.6 | AZ11: 22.12 | BA11: 16.72 | BB11: 22.28 | BC11: 16.84 | BD11: 22.44 | BE11: 17.33 | BF11: 23.07 | BG11: 14.46 | BH11: 19.99 | BI11: 14.54 | BJ11: 20.1 | BK11: 14.63 | BL11: 20.23 | BM11: Negativa | BN11: Grupo 1
A12: Natulab | B12: Medicamentos | C12: 7898133134630 | D12: 28578 | E12: 15000119 | F12: Alumimax 150ml Fn 1ct X 60fr - Farma | G12: 30049099 | H12: ATIVO | I12: 60 | J12: 4.02 | L12: 3.94 | M12: 4.02 | N12: =IFERROR(100%-(J12/M12),0) -> 0 | P12: 4.32 | Q12: =IFERROR(100%-(M12/P12),0) -> 0.069444444 | S12: 4.64 | T12: =IFERROR(100%-(M12/S12),0) -> 0.13362069 | V12: 4.0691511 | W12: =IFERROR(100%-(M12/V12),0) -> 0.012078953 | Y12: 4.3465932 | Z12: =IFERROR(100%-(M12/Y12),0) -> 0.075137743 | AB12: 4.6646366 | AC12: =IFERROR(100%-(M12/AB12),0) -> 0.13819653 | AE12: 3.7082554 | AF12: =IFERROR(100%-(M12/AE12),0) -> -0.084067723 | AH12: 0 | AI12: =IFERROR(100%-(M12/AH12),0) -> 0 | AK12: 0 | AL12: =IFERROR(100%-(M12/AK12),0) -> 0 | AN12: 0 | AO12: =IFERROR(100%-(M12/AN12),0) -> 0 | AR12: =IFERROR(100%-(P12/AQ12),0) -> 0 | AT12: 20.91 | AU12: 16.68 | AV12: 22.37 | AW12: 19.28 | AX12: 25.75 | AY12: 20.62 | AZ12: 27.48 | BA12: 20.76 | BB12: 27.66 | BC12: 20.91 | BD12: 27.86 | BE12: 21.52 | BF12: 28.64 | BG12: 17.95 | BH12: 24.82 | BI12: 18.06 | BJ12: 24.97 | BK12: 18.17 | BL12: 25.12 | BM12: Negativa | BN12: Grupo 1
A13: Natulab | B13: Medicamentos | C13: 7898133136634 | D13: 23792 | E13: 15000068 | F13: Arlivry 100ml Cereja 1ct X 50fr - Farma | G13: 30049099 | H13: ATIVO | I13: 50 | J13: 3.61 | L13: 3.54 | M13: 3.61 | N13: =IFERROR(100%-(J13/M13),0) -> 0 | P13: 3.88 | Q13: =IFERROR(100%-(M13/P13),0) -> 0.069587629 | S13: 4.17 | T13: =IFERROR(100%-(M13/S13),0) -> 0.13429257 | V13: 3.6535568 | W13: =IFERROR(100%-(M13/V13),0) -> 0.011921765 | Y13: 3.902663 | Z13: =IFERROR(100%-(M13/Y13),0) -> 0.074990588 | AB13: 4.1882237 | AC13: =IFERROR(100%-(M13/AB13),0) -> 0.13805941 | AE13: 3.43 | AF13: =IFERROR(100%-(M13/AE13),0) -> -0.052478134 | AH13: 3.3 | AI13: =IFERROR(100%-(M13/AH13),0) -> -0.093939394 | AK13: 13.133 | AL13: =IFERROR(100%-(M13/AK13),0) -> 0.72511993 | AN13: 11.826675 | AO13: =IFERROR(100%-(M13/AN13),0) -> 0.69475783 | AR13: =IFERROR(100%-(P13/AQ13),0) -> 0 | AT13: 19.93 | AU13: 15.9 | AV13: 21.32 | AW13: 18.37 | AX13: 24.53 | AY13: 19.65 | AZ13: 26.19 | BA13: 19.79 | BB13: 26.37 | BC13: 19.93 | BD13: 26.55 | BE13: 20.51 | BF13: 27.3 | BG13: 17.11 | BH13: 23.65 | BI13: 17.21 | BJ13: 23.79 | BK13: 17.32 | BL13: 23.94 | BM13: Negativa | BN13: Grupo 2
A14: Natulab | B14: Medicamentos | C14: 7898133136757 | D14: 23794 | E14: 15000069 | F14: Arlivry 100ml Mel 1ct X 50fr - Farma | G14: 30049099 | H14: ATIVO | I14: 50 | J14: 3.61 | L14: 3.54 | M14: 3.61 | N14: =IFERROR(100%-(J14/M14),0) -> 0 | P14: 3.88 | Q14: =IFERROR(100%-(M14/P14),0) -> 0.069587629 | S14: 4.17 | T14: =IFERROR(100%-(M14/S14),0) -> 0.13429257 | V14: 3.6535568 | W14: =IFERROR(100%-(M14/V14),0) -> 0.011921765 | Y14: 3.902663 | Z14: =IFERROR(100%-(M14/Y14),0) -> 0.074990588 | AB14: 4.1882237 | AC14: =IFERROR(100%-(M14/AB14),0) -> 0.13805941 | AE14: 3.43 | AF14: =IFERROR(100%-(M14/AE14),0) -> -0.052478134 | AH14: 3.3 | AI14: =IFERROR(100%-(M14/AH14),0) -> -0.093939394 | AK14: 13.144 | AL14: =IFERROR(100%-(M14/AK14),0) -> 0.72534997 | AN14: 11.826675 | AO14: =IFERROR(100%-(M14/AN14),0) -> 0.69475783 | AR14: =IFERROR(100%-(P14/AQ14),0) -> 0 | AT14: 25.03 | AU14: 19.97 | AV14: 26.78 | AW14: 23.08 | AX14: 30.83 | AY14: 24.68 | AZ14: 32.89 | BA14: 24.85 | BB14: 33.11 | BC14: 25.03 | BD14: 33.35 | BE14: 25.76 | BF14: 34.29 | BG14: 21.49 | BH14: 29.71 | BI14: 21.62 | BJ14: 29.89 | BK14: 21.75 | BL14: 30.07 | BM14: Negativa | BN14: Grupo 2
A15: Natulab | B15: Medicamentos | C15: 7899470802725 | D15: 23670 | E15: 15000154 | F15: Arpynflan 450mg 2bl X 15cap X 100ct - Farma | G15: 30049099 | H15: ATIVO | I15: 100 | J15: 21.2 | L15: 20.79 | M15: 21.2 | N15: =IFERROR(100%-(J15/M15),0) -> 0 | P15: 22.8 | Q15: =IFERROR(100%-(M15/P15),0) -> 0.070175439 | S15: 24.51 | T15: =IFERROR(100%-(M15/S15),0) -> 0.13504692 | V15: 21.480765 | W15: =IFERROR(100%-(M15/V15),0) -> 0.013070535 | Y15: 22.945363 | Z15: =IFERROR(100%-(M15/Y15),0) -> 0.076066033 | AB15: 24.624292 | AC15: =IFERROR(100%-(M15/AB15),0) -> 0.13906153 | AE15: 19.543147 | AF15: =IFERROR(100%-(M15/AE15),0) -> -0.084779221 | AH15: 0 | AI15: =IFERROR(100%-(M15/AH15),0) -> 0 | AK15: 0 | AL15: =IFERROR(100%-(M15/AK15),0) -> 0 | AN15: 0 | AO15: =IFERROR(100%-(M15/AN15),0) -> 0 | AR15: =IFERROR(100%-(P15/AQ15),0) -> 0 | AT15: 82.28 | AU15: 65.66 | AV15: 88.08 | AW15: 75.87 | AX15: 101.34 | AY15: 81.13 | AZ15: 108.14 | BA15: 81.7 | BB15: 108.87 | BC15: 82.28 | BD15: 109.62 | BE15: 84.66 | BF15: 112.69 | BG15: 70.63 | BH15: 97.64 | BI15: 71.06 | BJ15: 98.24 | BK15: 71.49 | BL15: 98.83 | BM15: Negativa | BN15: Grupo 2
A16: Natulab | B16: Medicamentos | C16: 7899470805726 | D16: 27414 | E16: 15000220 | F16: Baby D - Pomada Para Assadura 45g 1bg X 100ct - Farma | G16: 30049099 | H16: ATIVO | I16: 100 | J16: 3.79 | L16: 3.71 | M16: 3.79 | N16: =IFERROR(100%-(J16/M16),0) -> 0 | P16: 4.07 | Q16: =IFERROR(100%-(M16/P16),0) -> 0.068796069 | S16: 4.38 | T16: =IFERROR(100%-(M16/S16),0) -> 0.1347032 | V16: 3.8362347 | W16: =IFERROR(100%-(M16/V16),0) -> 0.012052101 | Y16: 4.0977961 | Z16: =IFERROR(100%-(M16/Y16),0) -> 0.075112605 | AB16: 4.3976349 | AC16: =IFERROR(100%-(M16/AB16),0) -> 0.13817311 | AE16: 3.6243655 | AF16: =IFERROR(100%-(M16/AE16),0) -> -0.04570028 | AH16: 0 | AI16: =IFERROR(100%-(M16/AH16),0) -> 0 | AK16: 0 | AL16: =IFERROR(100%-(M16/AK16),0) -> 0 | AN16: 0 | AO16: =IFERROR(100%-(M16/AN16),0) -> 0 | AR16: =IFERROR(100%-(P16/AQ16),0) -> 0 | AT16: 20.49 | AU16: 16.35 | AV16: 21.93 | AW16: 18.89 | AX16: 25.23 | AY16: 20.2 | AZ16: 26.92 | BA16: 20.34 | BB16: 27.1 | BC16: 20.49 | BD16: 27.3 | BE16: 21.08 | BF16: 28.06 | BG16: 17.59 | BH16: 24.32 | BI16: 17.7 | BJ16: 24.47 | BK16: 17.8 | BL16: 24.61 | BM16: Negativa | BN16: Grupo 1
A17: Natulab | B17: Medicamentos | C17: 7899470805955 | D17: 30023 | E17: 15000130 | F17: Bronqtrat 100ml 1ct X 50fr - Farma Novo | G17: 30049039 | H17: ATIVO | I17: 50 | J17: 2.69 | M17: 0 | N17: =IFERROR(100%-(J17/M17),0) -> 0 | P17: 0 | Q17: =IFERROR(100%-(M17/P17),0) -> 0 | S17: 0 | T17: =IFERROR(100%-(M17/S17),0) -> 0 | V17: 0 | W17: =IFERROR(100%-(M17/V17),0) -> 0 | Y17: 0 | Z17: =IFERROR(100%-(M17/Y17),0) -> 0 | AB17: 0 | AC17: =IFERROR(100%-(M17/AB17),0) -> 0 | AE17: 0 | AF17: =IFERROR(100%-(M17/AE17),0) -> 0 | AH17: 0 | AI17: =IFERROR(100%-(M17/AH17),0) -> 0 | AK17: 0 | AL17: =IFERROR(100%-(M17/AK17),0) -> 0 | AN17: 0 | AO17: =IFERROR(100%-(M17/AN17),0) -> 0 | AR17: =IFERROR(100%-(P17/AQ17),0) -> 0 | AT17: 26.65 | AU17: 21.26 | AV17: 28.52 | AW17: 24.57 | AX17: 32.82 | AY17: 26.28 | AZ17: 35.02 | BA17: 26.46 | BB17: 35.26 | BC17: 26.65 | BD17: 35.51 | BE17: 27.42 | BF17: 36.5 | BG17: 22.88 | BH17: 31.63 | BI17: 23.02 | BJ17: 31.82 | BK17: 23.16 | BL17: 32.02 | BM17: Negativa | BN17: Grupo 2
A18: Natulab | B18: Medicamentos | C18: 7898133135941 | D18: 23805 | E18: 15000071 | F18: Bronqtrat Infantil 100ml 1ct X 50fr - Farma | G18: 30049039 | H18: ATIVO | I18: 50 | J18: 2.81 | L18: 2.76 | M18: 2.81 | N18: =IFERROR(100%-(J18/M18),0) -> 0 | P18: 3.03 | Q18: =IFERROR(100%-(M18/P18),0) -> 0.072607261 | S18: 3.25 | T18: =IFERROR(100%-(M18/S18),0) -> 0.13538462 | V18: 2.8862583 | W18: =IFERROR(100%-(M18/V18),0) -> 0.026421172 | Y18: 3.0830487 | Z18: =IFERROR(100%-(M18/Y18),0) -> 0.088564502 | AB18: 3.3086376 | AC18: =IFERROR(100%-(M18/AB18),0) -> 0.15070783 | AE18: 2.5685279 | AF18: =IFERROR(100%-(M18/AE18),0) -> -0.094011858 | AH18: 0 | AI18: =IFERROR(100%-(M18/AH18),0) -> 0 | AK18: 0 | AL18: =IFERROR(100%-(M18/AK18),0) -> 0 | AN18: 0 | AO18: =IFERROR(100%-(M18/AN18),0) -> 0 | AR18: =IFERROR(100%-(P18/AQ18),0) -> 0 | AT18: 27.79 | AU18: 22.17 | AV18: 29.74 | AW18: 25.62 | AX18: 34.22 | AY18: 27.4 | AZ18: 36.52 | BA18: 27.59 | BB18: 36.76 | BC18: 27.79 | BD18: 37.03 | BE18: 28.6 | BF18: 38.07 | BG18: 23.86 | BH18: 32.99 | BI18: 24 | BJ18: 33.18 | BK18: 24.15 | BL18: 33.39 | BM18: Negativa | BN18: Grupo 2
A19: Natulab | B19: Medicamentos | C19: 7899470802565 | D19: 28440 | E19: 15000117 | F19: Buscoplex Composto Gotas 20ml 1ct X 200fr - Farma | G19: 30044990 | H19: ATIVO | I19: 200 | J19: 5.6 | L19: 5.45 | M19: 5.6 | N19: =IFERROR(100%-(J19/M19),0) -> 0 | P19: 6.02 | Q19: =IFERROR(100%-(M19/P19),0) -> 0.069767442 | S19: 6.47 | T19: =IFERROR(100%-(M19/S19),0) -> 0.13446677 | V19: 5.6702128 | W19: =IFERROR(100%-(M19/V19),0) -> 0.012382739 | Y19: 6.0568182 | Z19: =IFERROR(100%-(M19/Y19),0) -> 0.075422139 | AB19: 6.5 | AC19: =IFERROR(100%-(M19/AB19),0) -> 0.13846154 | AE19: 5.33 | AF19: =IFERROR(100%-(M19/AE19),0) -> -0.05065666 | AH19: 5.29 | AI19: =IFERROR(100%-(M19/AH19),0) -> -0.058601134 | AK19: 8.1765 | AL19: =IFERROR(100%-(M19/AK19),0) -> 0.31511038 | AN19: 0 | AO19: =IFERROR(100%-(M19/AN19),0) -> 0 | AR19: =IFERROR(100%-(P19/AQ19),0) -> 0 | AT19: 10.84 | AU19: 8.65 | AV19: 11.6 | AW19: 9.99 | AX19: 13.34 | AY19: 10.69 | AZ19: 14.24 | BA19: 10.76 | BB19: 14.33 | BC19: 10.84 | BD19: 14.44 | BE19: 11.15 | BF19: 14.84 | BG19: 9.31 | BH19: 12.87 | BI19: 9.36 | BJ19: 12.94 | BK19: 9.42 | BL19: 13.02 | BM19: Negativa | BN19: Grupo 2
A20: Natulab | B20: Medicamentos | C20: 7899470805849 | D20: 33549 | E20: 15000131 | F20: Butalab C/ Cp Med 100ml 1ct X 50fr - Farma | G20: 30039099 | H20: ATIVO | I20: 50 | J20: 1.77 | L20: 1.74 | M20: 1.77 | N20: =IFERROR(100%-(J20/M20),0) -> 0 | P20: 1.91 | Q20: =IFERROR(100%-(M20/P20),0) -> 0.073298429 | S20: 2.05 | T20: =IFERROR(100%-(M20/S20),0) -> 0.13658537 | V20: 1.7978723 | W20: =IFERROR(100%-(M20/V20),0) -> 0.015502959 | Y20: 1.9204545 | Z20: =IFERROR(100%-(M20/Y20),0) -> 0.078343195 | AB20: 2.0609756 | AC20: =IFERROR(100%-(M20/AB20),0) -> 0.14118343 | AE20: 1.5126904 | AF20: =IFERROR(100%-(M20/AE20),0) -> -0.17010067 | AH20: 0 | AI20: =IFERROR(100%-(M20/AH20),0) -> 0 | AK20: 0 | AL20: =IFERROR(100%-(M20/AK20),0) -> 0 | AN20: 0 | AO20: =IFERROR(100%-(M20/AN20),0) -> 0 | AR20: =IFERROR(100%-(P20/AQ20),0) -> 0 | AT20: 5.48 | AU20: 4.49 | AV20: 6.2 | AW20: 5.1 | AX20: 7.05 | AY20: 5.41 | AZ20: 7.47 | BA20: 5.44 | BB20: 7.52 | BC20: 5.48 | BD20: 7.58 | BE20: 5.62 | BF20: 7.77 | BG20: 5.41 | BH20: 7.48 | BI20: 5.45 | BJ20: 7.53 | BK20: 5.48 | BL20: 7.58 | BM20: Positiva | BN20: Grupo 3
A21: Natulab | B21: Medicamentos | C21: 7899470804200 | D21: 44983 | E21: 15000211 | F21: Cardomarin 127mg 2bl X 10com X 100ct - Farma | G21: 30049099 | H21: ATIVO | I21: 100 | J21: 11.98 | L21: 11.75 | M21: 11.98 | N21: =IFERROR(100%-(J21/M21),0) -> 0 | P21: 12.88 | Q21: =IFERROR(100%-(M21/P21),0) -> 0.069875776 | S21: 13.85 | T21: =IFERROR(100%-(M21/S21),0) -> 0.13501805 | V21: 12.13648 | W21: =IFERROR(100%-(M21/V21),0) -> 0.012893334 | Y21: 12.963967 | Z21: =IFERROR(100%-(M21/Y21),0) -> 0.075900143 | AB21: 13.91255 | AC21: =IFERROR(100%-(M21/AB21),0) -> 0.13890695 | AE21: 10.93401 | AF21: =IFERROR(100%-(M21/AE21),0) -> -0.095663881 | AH21: 0 | AI21: =IFERROR(100%-(M21/AH21),0) -> 0 | AK21: 0 | AL21: =IFERROR(100%-(M21/AK21),0) -> 0 | AN21: 0 | AO21: =IFERROR(100%-(M21/AN21),0) -> 0 | AR21: =IFERROR(100%-(P21/AQ21),0) -> 0 | AT21: 50.38 | AU21: 40.2 | AV21: 53.92 | AW21: 46.45 | AX21: 62.04 | AY21: 49.68 | AZ21: 66.22 | BA21: 50.02 | BB21: 66.65 | BC21: 50.38 | BD21: 67.12 | BE21: 51.84 | BF21: 69 | BG21: 43.25 | BH21: 59.79 | BI21: 43.51 | BJ21: 60.15 | BK21: 43.78 | BL21: 60.52 | BM21: Negativa | BN21: Grupo 1
A22: Natulab | B22: Medicamentos | C22: 7899470803647 | D22: 23815 | E22: 15000074 | F22: Cardomarin 18.05mg 100ml 1ct X 50fr - Farma | G22: 30049099 | H22: ATIVO | I22: 50 | J22: 15.39 | L22: 0 | M22: 15.39 | N22: =IFERROR(100%-(J22/M22),0) -> 0 | P22: 16.55 | Q22: =IFERROR(100%-(M22/P22),0) -> 0.070090634 | S22: 17.8 | T22: =IFERROR(100%-(M22/S22),0) -> 0.13539326 | V22: 15.585106 | W22: =IFERROR(100%-(M22/V22),0) -> 0.012518771 | Y22: 16.647727 | Z22: =IFERROR(100%-(M22/Y22),0) -> 0.075549488 | AB22: 17.865854 | AC22: =IFERROR(100%-(M22/AB22),0) -> 0.1385802 | AE22: 14.65 | AF22: =IFERROR(100%-(M22/AE22),0) -> -0.050511945 | AH22: 0 | AI22: =IFERROR(100%-(M22/AH22),0) -> 0 | AK22: 0 | AL22: =IFERROR(100%-(M22/AK22),0) -> 0 | AN22: 0 | AO22: =IFERROR(100%-(M22/AN22),0) -> 0 | AR22: =IFERROR(100%-(P22/AQ22),0) -> 0 | AT22: 50.25 | AU22: 40.1 | AV22: 53.79 | AW22: 46.33 | AX22: 61.88 | AY22: 49.55 | AZ22: 66.04 | BA22: 49.89 | BB22: 66.48 | BC22: 50.25 | BD22: 66.95 | BE22: 51.71 | BF22: 68.83 | BG22: 43.14 | BH22: 59.64 | BI22: 43.4 | BJ22: 60 | BK22: 43.66 | BL22: 60.36 | BM22: Negativa | BN22: Grupo 1
A23: Natulab | B23: Medicamentos | C23: 7899470804149 | D23: 45087 | E23: 15000213 | F23: Cardomarin Cap Dura 254Mg X 20 | G23: 30049099 | H23: ATIVO | I23: 50 | J23: 16.96 | L23: 16.63 | M23: 16.96 | N23: =IFERROR(100%-(J23/M23),0) -> 0 | P23: 18.24 | Q23: =IFERROR(100%-(M23/P23),0) -> 0.070175439 | S23: 19.61 | T23: =IFERROR(100%-(M23/S23),0) -> 0.13513514 | V23: 17.182463 | W23: =IFERROR(100%-(M23/V23),0) -> 0.012947092 | Y23: 18.353994 | Z23: =IFERROR(100%-(M23/Y23),0) -> 0.075950469 | AB23: 19.69697 | AC23: =IFERROR(100%-(M23/AB23),0) -> 0.13895385 | AE23: 16.233503 | AF23: =IFERROR(100%-(M23/AE23),0) -> -0.044752971 | AH23: 16.15 | AI23: =IFERROR(100%-(M23/AH23),0) -> -0.050154799 | AK23: 29.4546 | AL23: =IFERROR(100%-(M23/AK23),0) -> 0.4241986 | AN23: 0 | AO23: =IFERROR(100%-(M23/AN23),0) -> 0 | AR23: =IFERROR(100%-(P23/AQ23),0) -> 0 | AT23: 70.13 | AU23: 55.96 | AV23: 75.06 | AW23: 64.67 | AX23: 86.38 | AY23: 69.15 | AZ23: 92.17 | BA23: 69.64 | BB23: 92.8 | BC23: 70.13 | BD23: 93.44 | BE23: 72.16 | BF23: 96.05 | BG23: 60.2 | BH23: 83.22 | BI23: 60.57 | BJ23: 83.73 | BK23: 60.94 | BL23: 84.25 | BM23: Negativa | BN23: Grupo 1
A24: Natulab | B24: Medicamentos | C24: 7898133137549 | D24: 23780 | E24: 15000158 | F24: Comple B Comprimidos 1fr X 50com X 100ct - Farma | G24: 30045090 | H24: ATIVO | I24: 100 | J24: 4.23 | L24: 3.79 | M24: 4.23 | N24: =IFERROR(100%-(J24/M24),0) -> 0 | P24: 4.55 | Q24: =IFERROR(100%-(M24/P24),0) -> 0.07032967 | S24: 4.89 | T24: =IFERROR(100%-(M24/S24),0) -> 0.13496933 | V24: 3.915375 | W24: =IFERROR(100%-(M24/V24),0) -> -0.08035628 | Y24: 4.1823324 | Z24: =IFERROR(100%-(M24/Y24),0) -> -0.011397369 | AB24: 4.4883567 | AC24: =IFERROR(100%-(M24/AB24),0) -> 0.057561543 | AE24: 3.5284264 | AF24: =IFERROR(100%-(M24/AE24),0) -> -0.1988347 | AH24: 3.68 | AI24: =IFERROR(100%-(M24/AH24),0) -> -0.14945652 | AK24: 5.08 | AL24: =IFERROR(100%-(M24/AK24),0) -> 0.16732283 | AN24: 0 | AO24: =IFERROR(100%-(M24/AN24),0) -> 0 | AR24: =IFERROR(100%-(P24/AQ24),0) -> 0 | AT24: 25.56 | AU24: 20.39 | AV24: 27.35 | AW24: 23.57 | AX24: 31.48 | AY24: 25.2 | AZ24: 33.59 | BA24: 25.38 | BB24: 33.82 | BC24: 25.56 | BD24: 34.05 | BE24: 26.3 | BF24: 35.01 | BG24: 21.94 | BH24: 30.33 | BI24: 22.08 | BJ24: 30.52 | BK24: 22.21 | BL24: 30.7 | BM24: Negativa | BN24: Grupo 2
A25: Natulab | B25: Medicamentos | C25: 7899470802282 | D25: 23783 | E25: 15000159 | F25: Epaphyto Cap Dura 300mg x 30 | G25: 30044990 | H25: ATIVO | I25: 100 | J25: 9.53 | L25: 9.35 | M25: 9.53 | N25: =IFERROR(100%-(J25/M25),0) -> 0 | P25: 10.25 | Q25: =IFERROR(100%-(M25/P25),0) -> 0.070243902 | S25: 11.02 | T25: =IFERROR(100%-(M25/S25),0) -> 0.13520871 | V25: 9.6604341 | W25: =IFERROR(100%-(M25/V25),0) -> 0.013501891 | Y25: 10.3191 | Z25: =IFERROR(100%-(M25/Y25),0) -> 0.076469855 | AB25: 11.074156 | AC25: =IFERROR(100%-(M25/AB25),0) -> 0.13943782 | AE25: 9.1269036 | AF25: =IFERROR(100%-(M25/AE25),0) -> -0.04416574 | AH25: 0 | AI25: =IFERROR(100%-(M25/AH25),0) -> 0 | AK25: 0 | AL25: =IFERROR(100%-(M25/AK25),0) -> 0 | AN25: 0 | AO25: =IFERROR(100%-(M25/AN25),0) -> 0 | AR25: =IFERROR(100%-(P25/AQ25),0) -> 0 | AT25: 38.29 | AU25: 30.55 | AV25: 40.98 | AW25: 35.31 | AX25: 47.16 | AY25: 37.75 | AZ25: 50.31 | BA25: 38.02 | BB25: 50.66 | BC25: 38.29 | BD25: 51.01 | BE25: 39.4 | BF25: 52.44 | BG25: 32.87 | BH25: 45.44 | BI25: 33.07 | BJ25: 45.72 | BK25: 33.27 | BL25: 45.99 | BM25: Negativa | BN25: Grupo 2
A26: Natulab | B26: Medicamentos | C26: 7899470803067 | D26: 24129 | E26: 15000114 | F26: Epaphyto Sol Or 14mg X 150ml | G26: 30044990 | H26: ATIVO | I26: 60 | J26: 10.85 | L26: 10.649524 | M26: 10.85 | N26: =IFERROR(100%-(J26/M26),0) -> 0 | P26: 11.66 | Q26: =IFERROR(100%-(M26/P26),0) -> 0.069468268 | S26: 12.54 | T26: =IFERROR(100%-(M26/S26),0) -> 0.13476874 | V26: 10.989362 | W26: =IFERROR(100%-(M26/V26),0) -> 0.01268151 | Y26: 11.738636 | Z26: =IFERROR(100%-(M26/Y26),0) -> 0.075701839 | AB26: 12.597561 | AC26: =IFERROR(100%-(M26/AB26),0) -> 0.13872217 | AE26: 10.33 | AF26: =IFERROR(100%-(M26/AE26),0) -> -0.050338819 | AH26: 0 | AI26: =IFERROR(100%-(M26/AH26),0) -> 0 | AK26: 0 | AL26: =IFERROR(100%-(M26/AK26),0) -> 0 | AN26: 0 | AO26: =IFERROR(100%-(M26/AN26),0) -> 0 | AR26: =IFERROR(100%-(P26/AQ26),0) -> 0 | AT26: 43.4 | AU26: 34.63 | AV26: 46.45 | AW26: 40.02 | AX26: 53.45 | AY26: 42.79 | AZ26: 57.03 | BA26: 43.09 | BB26: 57.42 | BC26: 43.4 | BD26: 57.82 | BE26: 44.66 | BF26: 59.44 | BG26: 37.26 | BH26: 51.51 | BI26: 37.48 | BJ26: 51.81 | BK26: 37.71 | BL26: 52.13 | BM26: Negativa | BN26: Grupo 2
A27: Natulab | B27: Medicamentos | C27: 7899470802299 | D27: 23830 | E27: 15000160 | F27: Espinheira Santa Natulab 380mg 3bl X 15cap X 50ct - Farma | G27: 30049099 | H27: ATIVO | I27: 50 | J27: 11.03 | L27: 10.82 | M27: 11.03 | N27: =IFERROR(100%-(J27/M27),0) -> 0 | P27: 11.86 | Q27: =IFERROR(100%-(M27/P27),0) -> 0.069983137 | S27: 12.76 | T27: =IFERROR(100%-(M27/S27),0) -> 0.13557994 | V27: 11.178337 | W27: =IFERROR(100%-(M27/V27),0) -> 0.013270003 | Y27: 11.940496 | Z27: =IFERROR(100%-(M27/Y27),0) -> 0.076252769 | AB27: 12.814191 | AC27: =IFERROR(100%-(M27/AB27),0) -> 0.13923553 | AE27: 10.073604 | AF27: =IFERROR(100%-(M27/AE27),0) -> -0.094940791 | AH27: 0 | AI27: =IFERROR(100%-(M27/AH27),0) -> 0 | AK27: 0 | AL27: =IFERROR(100%-(M27/AK27),0) -> 0 | AN27: 0 | AO27: =IFERROR(100%-(M27/AN27),0) -> 0 | AR27: =IFERROR(100%-(P27/AQ27),0) -> 0 | AT27: 52.01 | AU27: 41.5 | AV27: 55.67 | AW27: 47.96 | AX27: 64.06 | AY27: 51.28 | AZ27: 68.35 | BA27: 51.64 | BB27: 68.81 | BC27: 52.01 | BD27: 69.29 | BE27: 53.52 | BF27: 71.24 | BG27: 44.65 | BH27: 61.73 | BI27: 44.92 | BJ27: 62.1 | BK27: 45.19 | BL27: 62.47 | BM27: Negativa | BN27: Grupo 2
A28: Natulab | B28: Medicamentos | C28: 7898133131110 | D28: 23825 | E28: 15000273 | F28: EXPECTOFLUI XPE 13.33MG/ML X 120ML | G28: 30049039 | H28: ATIVO | I28: 30 | J28: 3.62 | L28: 3.55 | M28: 3.62 | N28: =IFERROR(100%-(J28/M28),0) -> 0 | P28: 3.89 | Q28: =IFERROR(100%-(M28/P28),0) -> 0.06940874 | S28: 4.18 | T28: =IFERROR(100%-(M28/S28),0) -> 0.13397129 | V28: 3.6643026 | W28: =IFERROR(100%-(M28/V28),0) -> 0.012090323 | Y28: 3.9141414 | Z28: =IFERROR(100%-(M28/Y28),0) -> 0.075148387 | AB28: 4.200542 | AC28: =IFERROR(100%-(M28/AB28),0) -> 0.13820645 | AE28: 3.3045685 | AF28: =IFERROR(100%-(M28/AE28),0) -> -0.095453149 | AH28: 0 | AI28: =IFERROR(100%-(M28/AH28),0) -> 0 | AK28: 0 | AL28: =IFERROR(100%-(M28/AK28),0) -> 0 | AN28: 0 | AO28: =IFERROR(100%-(M28/AN28),0) -> 0 | AR28: =IFERROR(100%-(P28/AQ28),0) -> 0 | AT28: 15.13 | AU28: 12.07 | AV28: 16.19 | AW28: 13.95 | AX28: 18.63 | AY28: 14.92 | AZ28: 19.88 | BA28: 15.02 | BB28: 20.01 | BC28: 15.13 | BD28: 20.16 | BE28: 15.57 | BF28: 20.72 | BG28: 12.99 | BH28: 17.96 | BI28: 13.07 | BJ28: 18.07 | BK28: 13.15 | BL28: 18.18 | BM28: Negativa | BN28: Grupo 2
A29: Natulab | B29: Medicamentos | C29: 7898133131400 | D29: 23828 | E29: 15000079 | F29: Helmilab S/Acucar 30m 1ct X 200fr - Farma | G29: 30049099 | H29: ATIVO | I29: 200 | J29: 1.48 | L29: 1.45 | M29: 1.48 | N29: =IFERROR(100%-(J29/M29),0) -> 0 | P29: 1.59 | Q29: =IFERROR(100%-(M29/P29),0) -> 0.06918239 | S29: 1.71 | T29: =IFERROR(100%-(M29/S29),0) -> 0.13450292 | V29: 1.5 | W29: =IFERROR(100%-(M29/V29),0) -> 0.013333333 | Y29: 1.6022727 | Z29: =IFERROR(100%-(M29/Y29),0) -> 0.076312057 | AB29: 1.7195122 | AC29: =IFERROR(100%-(M29/AB29),0) -> 0.13929078 | AE29: 1.41 | AF29: =IFERROR(100%-(M29/AE29),0) -> -0.04964539 | AH29: 1.4 | AI29: =IFERROR(100%-(M29/AH29),0) -> -0.057142857 | AK29: 0 | AL29: =IFERROR(100%-(M29/AK29),0) -> 0 | AN29: 0 | AO29: =IFERROR(100%-(M29/AN29),0) -> 0 | AR29: =IFERROR(100%-(P29/AQ29),0) -> 0 | AT29: 6.92 | AU29: 5.52 | AV29: 7.4 | AW29: 6.38 | AX29: 8.52 | AY29: 6.82 | AZ29: 9.09 | BA29: 6.87 | BB29: 9.15 | BC29: 6.92 | BD29: 9.22 | BE29: 7.12 | BF29: 9.48 | BG29: 5.94 | BH29: 8.21 | BI29: 5.98 | BJ29: 8.27 | BK29: 6.01 | BL29: 8.31 | BM29: Negativa | BN29: Grupo 2
... A42: Natulab | B42: Medicamentos | C42: 7898133134760 | D42: 23857 | E42: 15000086 | F42: Ibuprotrat Infantil C/Seringa 100ml 1ct X 50fr - Farma | G42: 30049029 | H42: ATIVO | I42: 50 | J42: 4.34 | L42: 4.2622 | M42: 4.34 | N42: =IFERROR(100%-(J42/M42),0) -> 0 | P42: 4.66 | Q42: =IFERROR(100%-(M42/P42),0) -> 0.068669528 | S42: 5.01 | T42: =IFERROR(100%-(M42/S42),0) -> 0.13373253 | V42: 4.393617 | W42: =IFERROR(100%-(M42/V42),0) -> 0.01220339 | Y42: 4.6931818 | Z42: =IFERROR(100%-(M42/Y42),0) -> 0.075254237 | AB42: 5.0365854 | AC42: =IFERROR(100%-(M42/AB42),0) -> 0.13830508 | AE42: 4.13 | AF42: =IFERROR(100%-(M42/AE42),0) -> -0.050847458 | AH42: 0 | AI42: =IFERROR(100%-(M42/AH42),0) -> 0 | AK42: 0 | AL42: =IFERROR(100%-(M42/AK42),0) -> 0 | AN42: 0 | AO42: =IFERROR(100%-(M42/AN42),0) -> 0 | AR42: =IFERROR(100%-(P42/AQ42),0) -> 0 | AT42: 23.93 | AU42: 19.09 | AV42: 25.6 | AW42: 22.06 | AX42: 29.46 | AY42: 23.59 | AZ42: 31.44 | BA42: 23.76 | BB42: 31.66 | BC42: 23.93 | BD42: 31.88 | BE42: 24.62 | BF42: 32.77 | BG42: 20.54 | BH42: 28.4 | BI42: 20.67 | BJ42: 28.58 | BK42: 20.79 | BL42: 28.74 | BM42: Negativa | BN42: Grupo 2
A43: Natulab | B43: Medicamentos | C43: 7898133130281 | D43: 23863 | E43: 15000087 | F43: Iodenax 100ml 1ct X 50fr - Farma | G43: 30049099 | H43: ATIVO | I43: 50 | J43: 3.54 | M43: 3.54 | N43: =IFERROR(100%-(J43/M43),0) -> 0 | P43: 3.81 | Q43: =IFERROR(100%-(M43/P43),0) -> 0.070866142 | S43: 4.1 | T43: =IFERROR(100%-(M43/S43),0) -> 0.13658537 | V43: 3.5890823 | W43: =IFERROR(100%-(M43/V43),0) -> 0.013675449 | Y43: 3.8337925 | Z43: =IFERROR(100%-(M43/Y43),0) -> 0.076632335 | AB43: 4.1143139 | AC43: =IFERROR(100%-(M43/AB43),0) -> 0.13958922 | AE43: 3.2299492 | AF43: =IFERROR(100%-(M43/AE43),0) -> -0.095992456 | AH43: 0 | AI43: =IFERROR(100%-(M43/AH43),0) -> 0 | AK43: 0 | AL43: =IFERROR(100%-(M43/AK43),0) -> 0 | AN43: 0 | AO43: =IFERROR(100%-(M43/AN43),0) -> 0 | AR43: =IFERROR(100%-(P43/AQ43),0) -> 0 | AT43: 21.63 | AU43: 17.26 | AV43: 23.15 | AW43: 19.94 | AX43: 26.63 | AY43: 21.33 | AZ43: 28.43 | BA43: 21.47 | BB43: 28.61 | BC43: 21.63 | BD43: 28.82 | BE43: 22.26 | BF43: 29.63 | BG43: 18.57 | BH43: 25.67 | BI43: 18.68 | BJ43: 25.82 | BK43: 18.8 | BL43: 25.99 | BM43: Negativa | BN43: Grupo 1
A44: Natulab | B44: Medicamentos | C44: 7898133134753 | D44: 23868 | E44: 15000277 | F44: KALONAT 20% X 10ML | G44: 30049029 | H44: ATIVO | I44: 100 | J44: 5.09 | M44: 0 | N44: =IFERROR(100%-(J44/M44),0) -> 0 | P44: 0 | Q44: =IFERROR(100%-(M44/P44),0) -> 0 | S44: 0 | T44: =IFERROR(100%-(M44/S44),0) -> 0 | V44: 0 | W44: =IFERROR(100%-(M44/V44),0) -> 0 | Y44: 0 | Z44: =IFERROR(100%-(M44/Y44),0) -> 0 | AB44: 0 | AC44: =IFERROR(100%-(M44/AB44),0) -> 0 | AE44: 4.6477157 | AF44: =IFERROR(100%-(M44/AE44),0) -> 1 | AH44: 4.85 | AI44: =IFERROR(100%-(M44/AH44),0) -> 1 | AK44: 9.8115 | AL44: =IFERROR(100%-(M44/AK44),0) -> 1 | AN44: 0 | AO44: =IFERROR(100%-(M44/AN44),0) -> 0 | AR44: =IFERROR(100%-(P44/AQ44),0) -> 0 | AT44: 31.65 | AU44: 25.25 | AV44: 33.87 | AW44: 29.18 | AX44: 38.97 | AY44: 31.21 | AZ44: 41.6 | BA44: 31.42 | BB44: 41.87 | BC44: 31.65 | BD44: 42.17 | BE44: 32.57 | BF44: 43.35 | BG44: 27.17 | BH44: 37.56 | BI44: 27.34 | BJ44: 37.8 | BK44: 27.5 | BL44: 38.02 | BM44: Negativa | BN44: Grupo 1
A45: Natulab | B45: Medicamentos | C45: 7898133136092 | D45: 28605 | E45: 15000122 | F45: Kollangel 150ml Hortela Fn 1ct X 60fr - Farma | G45: 30039099 | H45: ATIVO | I45: 60 | J45: 4.93 | L45: 4.84 | M45: 4.93 | N45: =IFERROR(100%-(J45/M45),0) -> 0 | P45: 5.3 | Q45: =IFERROR(100%-(M45/P45),0) -> 0.069811321 | S45: 5.7 | T45: =IFERROR(100%-(M45/S45),0) -> 0.13508772 | V45: 4.9967763 | W45: =IFERROR(100%-(M45/V45),0) -> 0.013363871 | Y45: 5.3374656 | Z45: =IFERROR(100%-(M45/Y45),0) -> 0.076340645 | AB45: 5.7280118 | AC45: =IFERROR(100%-(M45/AB45),0) -> 0.13931742 | AE45: 4.7208122 | AF45: =IFERROR(100%-(M45/AE45),0) -> -0.044311828 | AH45: 0 | AI45: =IFERROR(100%-(M45/AH45),0) -> 0 | AK45: 0 | AL45: =IFERROR(100%-(M45/AK45),0) -> 0 | AN45: 0 | AO45: =IFERROR(100%-(M45/AN45),0) -> 0 | AR45: =IFERROR(100%-(P45/AQ45),0) -> 0 | AT45: 24.4 | AU45: 19.47 | AV45: 26.11 | AW45: 22.5 | AX45: 30.05 | AY45: 24.06 | AZ45: 32.07 | BA45: 24.23 | BB45: 32.28 | BC45: 24.4 | BD45: 32.51 | BE45: 25.11 | BF45: 33.42 | BG45: 20.95 | BH45: 28.96 | BI45: 21.07 | BJ45: 29.13 | BK45: 21.2 | BL45: 29.31 | BM45: Negativa | BN45: Grupo 1
A46: Natulab | B46: Medicamentos | C46: 7898133136085 | D46: 28607 | E46: 15000123 | F46: Kollangel 150ml Morango Fn 1ct X 60fr - Farma | G46: 30039099 | H46: ATIVO | I46: 60 | J46: 4.93 | L46: 4.84 | M46: 4.93 | N46: =IFERROR(100%-(J46/M46),0) -> 0 | P46: 5.3 | Q46: =IFERROR(100%-(M46/P46),0) -> 0.069811321 | S46: 5.7 | T46: =IFERROR(100%-(M46/S46),0) -> 0.13508772 | V46: 4.9967763 | W46: =IFERROR(100%-(M46/V46),0) -> 0.013363871 | Y46: 5.3374656 | Z46: =IFERROR(100%-(M46/Y46),0) -> 0.076340645 | AB46: 5.7280118 | AC46: =IFERROR(100%-(M46/AB46),0) -> 0.13931742 | AE46: 4.7208122 | AF46: =IFERROR(100%-(M46/AE46),0) -> -0.044311828 | AH46: 0 | AI46: =IFERROR(100%-(M46/AH46),0) -> 0 | AK46: 0 | AL46: =IFERROR(100%-(M46/AK46),0) -> 0 | AN46: 0 | AO46: =IFERROR(100%-(M46/AN46),0) -> 0 | AR46: =IFERROR(100%-(P46/AQ46),0) -> 0 | AT46: 25.57 | AU46: 20.4 | AV46: 27.36 | AW46: 23.58 | AX46: 31.49 | AY46: 25.21 | AZ46: 33.6 | BA46: 25.39 | BB46: 33.83 | BC46: 25.57 | BD46: 34.07 | BE46: 26.31 | BF46: 35.02 | BG46: 21.95 | BH46: 30.35 | BI46: 22.08 | BJ46: 30.52 | BK46: 22.22 | BL46: 30.72 | BM46: Negativa | BN46: Grupo 1
A47: Natulab | B47: Medicamentos | C47: 7898133134661 | D47: 28603 | E47: 15000121 | F47: Kollangel 150ml Papaia Fn 1ct X 60fr - Farma | G47: 30039099 | H47: ATIVO | I47: 60 | J47: 4.93 | M47: 4.93 | N47: =IFERROR(100%-(J47/M47),0) -> 0 | P47: 5.3 | Q47: =IFERROR(100%-(M47/P47),0) -> 0.069811321 | S47: 5.7 | T47: =IFERROR(100%-(M47/S47),0) -> 0.13508772 | V47: 4.9967763 | W47: =IFERROR(100%-(M47/V47),0) -> 0.013363871 | Y47: 5.3374656 | Z47: =IFERROR(100%-(M47/Y47),0) -> 0.076340645 | AB47: 5.7280118 | AC47: =IFERROR(100%-(M47/AB47),0) -> 0.13931742 | AE47: 4.7208122 | AF47: =IFERROR(100%-(M47/AE47),0) -> -0.044311828 | AH47: 0 | AI47: =IFERROR(100%-(M47/AH47),0) -> 0 | AK47: 0 | AL47: =IFERROR(100%-(M47/AK47),0) -> 0 | AN47: 0 | AO47: =IFERROR(100%-(M47/AN47),0) -> 0 | AR47: =IFERROR(100%-(P47/AQ47),0) -> 0 | AT47: 25.57 | AU47: 20.4 | AV47: 27.36 | AW47: 23.58 | AX47: 31.49 | AY47: 25.21 | AZ47: 33.6 | BA47: 25.39 | BB47: 33.83 | BC47: 25.57 | BD47: 34.07 | BE47: 26.31 | BF47: 35.02 | BG47: 21.95 | BH47: 30.35 | BI47: 22.08 | BJ47: 30.52 | BK47: 22.22 | BL47: 30.72 | BM47: Negativa | BN47: Grupo 1
A48: Natulab | B48: Medicamentos | C48: 7898133139420 | D48: 23876 | E48: 15000090 | F48: L-Enema 130ml 1ct X 50fr - Farma | G48: 30049099 | H48: ATIVO | I48: 50 | J48: 7.65 | L48: 7.5 | M48: 7.65 | N48: =IFERROR(100%-(J48/M48),0) -> 0 | P48: 8.22 | Q48: =IFERROR(100%-(M48/P48),0) -> 0.069343066 | S48: 8.84 | T48: =IFERROR(100%-(M48/S48),0) -> 0.13461538 | V48: 7.7479476 | W48: =IFERROR(100%-(M48/V48),0) -> 0.012641743 | Y48: 8.2762167 | Z48: =IFERROR(100%-(M48/Y48),0) -> 0.07566461 | AB48: 8.8817935 | AC48: =IFERROR(100%-(M48/AB48),0) -> 0.13868748 | AE48: 6.9847716 | AF48: =IFERROR(100%-(M48/AE48),0) -> -0.095239826 | AH48: 7.28 | AI48: =IFERROR(100%-(M48/AH48),0) -> -0.050824176 | AK48: 8.88 | AL48: =IFERROR(100%-(M48/AK48),0) -> 0.13851351 | AN48: 8.3916 | AO48: =IFERROR(100%-(M48/AN48),0) -> 0.088374088 | AR48: =IFERROR(100%-(P48/AQ48),0) -> 0 | AT48: 11.7 | AU48: 9.33 | AV48: 12.51 | AW48: 10.78 | AX48: 14.4 | AY48: 11.53 | AZ48: 15.36 | BA48: 11.61 | BB48: 15.47 | BC48: 11.7 | BD48: 15.59 | BE48: 12.04 | BF48: 16.03 | BG48: 10.04 | BH48: 13.88 | BI48: 10.11 | BJ48: 13.98 | BK48: 10.17 | BL48: 14.06 | BM48: Negativa | BN48: Grupo 1
A49: Natulab | B49: Medicamentos | C49: 7898133134715 | D49: 23879 | E49: 15000091 | F49: Limonada Purgativa 200ml 1 X 60fr - Farma | G49: 30039099 | H49: ATIVO | I49: 60 | J49: 4.36 | L49: 4.27 | M49: 4.36 | N49: =IFERROR(100%-(J49/M49),0) -> 0 | P49: 4.69 | Q49: =IFERROR(100%-(M49/P49),0) -> 0.070362473 | S49: 5.04 | T49: =IFERROR(100%-(M49/S49),0) -> 0.13492063 | V49: 4.4165055 | W49: =IFERROR(100%-(M49/V49),0) -> 0.012794161 | Y49: 4.7176309 | Z49: =IFERROR(100%-(M49/Y49),0) -> 0.075807299 | AB49: 5.0628234 | AC49: =IFERROR(100%-(M49/AB49),0) -> 0.13882044 | AE49: 3.9761421 | AF49: =IFERROR(100%-(M49/AE49),0) -> -0.096540278 | AH49: 0 | AI49: =IFERROR(100%-(M49/AH49),0) -> 0 | AK49: 0 | AL49: =IFERROR(100%-(M49/AK49),0) -> 0 | AN49: 0 | AO49: =IFERROR(100%-(M49/AN49),0) -> 0 | AR49: =IFERROR(100%-(P49/AQ49),0) -> 0 | AT49: 29.33 | AU49: 23.4 | AV49: 31.39 | AW49: 27.04 | AX49: 36.12 | AY49: 28.92 | AZ49: 38.54 | BA49: 29.12 | BB49: 38.8 | BC49: 29.33 | BD49: 39.08 | BE49: 30.18 | BF49: 40.17 | BG49: 25.18 | BH49: 34.81 | BI49: 25.33 | BJ49: 35.02 | BK49: 25.49 | BL49: 35.24 | BM49: Negativa | BN49: Grupo 1
A50: Natulab | B50: Medicamentos | C50: 7898133137969 | D50: 35686 | E50: 15000135 | F50: Lufbem Gotas 15ml 1ct X 100 - Farma | G50: 30049099 | H50: ATIVO | I50: 100 | J50: 1.78 | L50: 1.75 | M50: 1.78 | N50: =IFERROR(100%-(J50/M50),0) -> 0 | P50: 1.92 | Q50: =IFERROR(100%-(M50/P50),0) -> 0.072916667 | S50: 2.06 | T50: =IFERROR(100%-(M50/S50),0) -> 0.13592233 | V50: 1.8052869 | W50: =IFERROR(100%-(M50/V50),0) -> 0.014007143 | Y50: 1.9283747 | Z50: =IFERROR(100%-(M50/Y50),0) -> 0.076942857 | AB50: 2.0694752 | AC50: =IFERROR(100%-(M50/AB50),0) -> 0.13987857 | AE50: 1.7 | AF50: =IFERROR(100%-(M50/AE50),0) -> -0.047058824 | AH50: 1.45 | AI50: =IFERROR(100%-(M50/AH50),0) -> -0.22758621 | AK50: 5.2775 | AL50: =IFERROR(100%-(M50/AK50),0) -> 0.66271909 | AN50: 0 | AO50: =IFERROR(100%-(M50/AN50),0) -> 0 | AR50: =IFERROR(100%-(P50/AQ50),0) -> 0 | AT50: 21.11 | AU50: 16.84 | AV50: 22.59 | AW50: 19.46 | AX50: 25.99 | AY50: 20.81 | AZ50: 27.73 | BA50: 20.96 | BB50: 27.93 | BC50: 21.11 | BD50: 28.13 | BE50: 21.72 | BF50: 28.91 | BG50: 18.12 | BH50: 25.05 | BI50: 18.23 | BJ50: 25.2 | BK50: 18.34 | BL50: 25.35 | BM50: Negativa | BN50: Grupo 1
A51: Natulab | B51: Medicamentos | C51: 7899470802275 | D51: 23883 | E51: 15000093 | F51: Magmax Hortela 100ml 1 X 100fr - Farma | G51: 30049099 | H51: ATIVO | I51: 100 | J51: 3.07 | L51: 3.01 | M51: 3.07 | N51: =IFERROR(100%-(J51/M51),0) -> 0 | P51: 3.3 | Q51: =IFERROR(100%-(M51/P51),0) -> 0.06969697 | S51: 3.54 | T51: =IFERROR(100%-(M51/S51),0) -> 0.13276836 | V51: 3.1055233 | W51: =IFERROR(100%-(M51/V51),0) -> 0.011438754 | Y51: 3.3172635 | Z51: =IFERROR(100%-(M51/Y51),0) -> 0.074538408 | AB51: 3.5599901 | AC51: =IFERROR(100%-(M51/AB51),0) -> 0.13763806 | AE51: 2.9340102 | AF51: =IFERROR(100%-(M51/AE51),0) -> -0.046349481 | AH51: 2.92 | AI51: =IFERROR(100%-(M51/AH51),0) -> -0.051369863 | AK51: 0 | AL51: =IFERROR(100%-(M51/AK51),0) -> 0 | AN51: 0 | AO51: =IFERROR(100%-(M51/AN51),0) -> 0 | AR51: =IFERROR(100%-(P51/AQ51),0) -> 0 | AT51: 15.38 | AU51: 12.27 | AV51: 16.46 | AW51: 14.18 | AX51: 18.94 | AY51: 15.16 | AZ51: 20.2 | BA51: 15.27 | BB51: 20.34 | BC51: 15.38 | BD51: 20.49 | BE51: 15.83 | BF51: 21.07 | BG51: 13.2 | BH51: 18.25 | BI51: 13.28 | BJ51: 18.36 | BK51: 13.36 | BL51: 18.47 | BM51: Negativa | BN51: Grupo 1
A52: Natulab | B52: Medicamentos | C52: 7899470802268 | D52: 23881 | E52: 15000092 | F52: Magmax Tradicional 100ml 1 X 100fr - Farma | G52: 30049099 | H52: ATIVO | I52: 100 | J52: 3.07 | L52: 3.01 | M52: 3.07 | N52: =IFERROR(100%-(J52/M52),0) -> 0 | P52: 3.3 | Q52: =IFERROR(100%-(M52/P52),0) -> 0.06969697 | S52: 3.54 | T52: =IFERROR(100%-(M52/S52),0) -> 0.13276836 | V52: 3.1055233 | W52: =IFERROR(100%-(M52/V52),0) -> 0.011438754 | Y52: 3.3172635 | Z52: =IFERROR(100%-(M52/Y52),0) -> 0.074538408 | AB52: 3.5599901 | AC52: =IFERROR(100%-(M52/AB52),0) -> 0.13763806 | AE52: 2.9340102 | AF52: =IFERROR(100%-(M52/AE52),0) -> -0.046349481 | AH52: 2.92 | AI52: =IFERROR(100%-(M52/AH52),0) -> -0.051369863 | AK52: 4.944 | AL52: =IFERROR(100%-(M52/AK52),0) -> 0.37904531 | AN52: 3.212055 | AO52: =IFERROR(100%-(M52/AN52),0) -> 0.044225581 | AR52: =IFERROR(100%-(P52/AQ52),0) -> 0 | AT52: 15.45 | AU52: 12.32 | AV52: 16.52 | AW52: 14.24 | AX52: 19.02 | AY52: 15.23 | AZ52: 20.3 | BA52: 15.34 | BB52: 20.44 | BC52: 15.45 | BD52: 20.58 | BE52: 15.9 | BF52: 21.16 | BG52: 13.26 | BH52: 18.33 | BI52: 13.34 | BJ52: 18.44 | BK52: 13.43 | BL52: 18.57 | BM52: Negativa | BN52: Grupo 1
A53: Natulab | B53: Medicamentos | C53: 7899470807225 | D53: 38804 | E53: 15000194 | F53: Masferol Comprimidos 109mg 2bl X 20com X 200ct - Farma | G53: 30039099 | H53: ATIVO | I53: 200 | J53: 3.25 | L53: 3.18 | M53: 3.25 | N53: =IFERROR(100%-(J53/M53),0) -> 0 | P53: 3.49 | Q53: =IFERROR(100%-(M53/P53),0) -> 0.068767908 | S53: 3.75 | T53: =IFERROR(100%-(M53/S53),0) -> 0.13333333 | V53: 3.2884419 | W53: =IFERROR(100%-(M53/V53),0) -> 0.011689994 | Y53: 3.5126538 | Z53: =IFERROR(100%-(M53/Y53),0) -> 0.074773611 | AB53: 3.7696773 | AC53: =IFERROR(100%-(M53/AB53),0) -> 0.13785723 | AE53: 3.035533 | AF53: =IFERROR(100%-(M53/AE53),0) -> -0.070652174 | AH53: 3.09 | AI53: =IFERROR(100%-(M53/AH53),0) -> -0.051779935 | AK53: 4.1752 | AL53: =IFERROR(100%-(M53/AK53),0) -> 0.22159418 | AN53: 0 | AO53: =IFERROR(100%-(M53/AN53),0) -> 0 | AR53: =IFERROR(100%-(P53/AQ53),0) -> 0 | AT53: 12.28 | AU53: 9.8 | AV53: 13.14 | AW53: 11.32 | AX53: 15.12 | AY53: 12.11 | AZ53: 16.14 | BA53: 12.19 | BB53: 16.24 | BC53: 12.28 | BD53: 16.36 | BE53: 12.64 | BF53: 16.82 | BG53: 10.54 | BH53: 14.57 | BI53: 10.61 | BJ53: 14.67 | BK53: 10.67 | BL53: 14.75 | BM53: Negativa | BN53: Grupo 1
A54: Natulab | B54: Medicamentos | C54: 7898133134999 | D54: 41484 | E54: 15000143 | F54: MASFEROL SOL OR 25MG/ML X 100ML | G54: 30039099 | H54: ATIVO | I54: 50 | J54: 2.19 | L54: 2.15 | M54: 2.19 | N54: =IFERROR(100%-(J54/M54),0) -> 0 | P54: 2.36 | Q54: =IFERROR(100%-(M54/P54),0) -> 0.072033898 | S54: 2.54 | T54: =IFERROR(100%-(M54/S54),0) -> 0.13779528 | V54: 2.2238384 | W54: =IFERROR(100%-(M54/V54),0) -> 0.015216206 | Y54: 2.3754637 | Z54: =IFERROR(100%-(M54/Y54),0) -> 0.078074746 | AB54: 2.5492781 | AC54: =IFERROR(100%-(M54/AB54),0) -> 0.14093329 | AE54: 2.0040609 | AF54: =IFERROR(100%-(M54/AE54),0) -> -0.092781155 | AH54: 2.09 | AI54: =IFERROR(100%-(M54/AH54),0) -> -0.04784689 | AK54: 2.7792 | AL54: =IFERROR(100%-(M54/AK54),0) -> 0.21200345 | AN54: 0 | AO54: =IFERROR(100%-(M54/AN54),0) -> 0 | AR54: =IFERROR(100%-(P54/AQ54),0) -> 0 | AT54: 11.58 | AU54: 9.24 | AV54: 12.39 | AW54: 10.67 | AX54: 14.25 | AY54: 11.41 | AZ54: 15.2 | BA54: 11.49 | BB54: 15.31 | BC54: 11.58 | BD54: 15.43 | BE54: 11.92 | BF54: 15.87 | BG54: 9.94 | BH54: 13.74 | BI54: 10 | BJ54: 13.82 | BK54: 10.06 | BL54: 13.91 | BM54: Negativa | BN54: Grupo 2
A55: Natulab | B55: Medicamentos | C55: 7898133131028 | D55: 23912 | E55: 15000096 | F55: Maxalgina 100ml 1ct X 50fr - Farma | G55: 30049069 | H55: ATIVO | I55: 50 | J55: 2.85 | L55: 2.8 | M55: 2.85 | N55: =IFERROR(100%-(J55/M55),0) -> 0 | P55: 3.07 | Q55: =IFERROR(100%-(M55/P55),0) -> 0.071661238 | S55: 3.3 | T55: =IFERROR(100%-(M55/S55),0) -> 0.13636364 | V55: 2.8906082 | W55: =IFERROR(100%-(M55/V55),0) -> 0.014048327 | Y55: 3.0876951 | Z55: =IFERROR(100%-(M55/Y55),0) -> 0.076981413 | AB55: 3.313624 | AC55: =IFERROR(100%-(M55/AB55),0) -> 0.1399145 | AE55: 2.7309645 | AF55: =IFERROR(100%-(M55/AE55),0) -> -0.043587361 | AH55: 0 | AI55: =IFERROR(100%-(M55/AH55),0) -> 0 | AK55: 0 | AL55: =IFERROR(100%-(M55/AK55),0) -> 0 | AN55: 2.7479844 | AO55: =IFERROR(100%-(M55/AN55),0) -> -0.037123792 | AR55: =IFERROR(100%-(P55/AQ55),0) -> 0 | AT55: 17.84 | AU55: 14.23 | AV55: 19.08 | AW55: 16.45 | AX55: 21.97 | AY55: 17.59 | AZ55: 23.44 | BA55: 17.71 | BB55: 23.6 | BC55: 17.84 | BD55: 23.77 | BE55: 18.36 | BF55: 24.44 | BG55: 15.32 | BH55: 21.18 | BI55: 15.41 | BJ55: 21.3 | BK55: 15.5 | BL55: 21.43 | BM55: Negativa | BN55: Grupo 2
A56: Natulab | B56: Medicamentos | C56: 7898133130403 | D56: 23892 | E56: 15000094 | F56: Maxalgina 10ml 1ct X 240fr - Farma | G56: 30049069 | H56: ATIVO | I56: 240 | J56: 1.14 | L56: 1.02 | M56: 1.14 | N56: =IFERROR(100%-(J56/M56),0) -> 0 | P56: 1.22 | Q56: =IFERROR(100%-(M56/P56),0) -> 0.06557377 | S56: 1.32 | T56: =IFERROR(100%-(M56/S56),0) -> 0.13636364 | V56: 1.053084 | W56: =IFERROR(100%-(M56/V56),0) -> -0.082534694 | Y56: 1.1248852 | Z56: =IFERROR(100%-(M56/Y56),0) -> -0.013436735 | AB56: 1.2071939 | AC56: =IFERROR(100%-(M56/AB56),0) -> 0.055661224 | AE56: 0.99492386 | AF56: =IFERROR(100%-(M56/AE56),0) -> -0.14581633 | AH56: 0.99 | AI56: =IFERROR(100%-(M56/AH56),0) -> -0.15151515 | AK56: 0 | AL56: =IFERROR(100%-(M56/AK56),0) -> 0 | AN56: 1.02376 | AO56: =IFERROR(100%-(M56/AN56),0) -> -0.11354224 | AR56: =IFERROR(100%-(P56/AQ56),0) -> 0 | AT56: 7.64 | AU56: 6.09 | AV56: 8.17 | AW56: 7.04 | AX56: 9.4 | AY56: 7.53 | AZ56: 10.03 | BA56: 7.58 | BB56: 10.1 | BC56: 7.64 | BD56: 10.18 | BE56: 7.86 | BF56: 10.46 | BG56: 6.56 | BH56: 9.07 | BI56: 6.6 | BJ56: 9.12 | BK56: 6.64 | BL56: 9.18 | BM56: Negativa | BN56: Grupo 2
A57: Natulab | B57: Medicamentos | C57: 7898133131011 | D57: 23906 | E57: 15000095 | F57: Maxalgina 20ml 1ct X 200fr - Farma | G57: 30049069 | H57: ATIVO | I57: 200 | J57: 1.76 | L57: 1.6 | M57: 1.76 | N57: =IFERROR(100%-(J57/M57),0) -> 0 | P57: 1.89 | Q57: =IFERROR(100%-(M57/P57),0) -> 0.068783069 | S57: 2.03 | T57: =IFERROR(100%-(M57/S57),0) -> 0.13300493 | V57: 1.5903718 | W57: =IFERROR(100%-(M57/V57),0) -> -0.10665946 | Y57: 1.6988062 | Z57: =IFERROR(100%-(M57/Y57),0) -> -0.036021622 | AB57: 1.8231091 | AC57: =IFERROR(100%-(M57/AB57),0) -> 0.034616216 | AE57: 1.5025381 | AF57: =IFERROR(100%-(M57/AE57),0) -> -0.17135135 | AH57: 1.49 | AI57: =IFERROR(100%-(M57/AH57),0) -> -0.18120805 | AK57: 1.651 | AL57: =IFERROR(100%-(M57/AK57),0) -> -0.066020594 | AN57: 1.600209 | AO57: =IFERROR(100%-(M57/AN57),0) -> -0.099856331 | AR57: =IFERROR(100%-(P57/AQ57),0) -> 0 | AT57: 12.69 | AU57: 10.12 | AV57: 13.57 | AW57: 11.7 | AX57: 15.62 | AY57: 12.51 | AZ57: 16.67 | BA57: 12.6 | BB57: 16.79 | BC57: 12.69 | BD57: 16.91 | BE57: 13.06 | BF57: 17.38 | BG57: 10.89 | BH57: 15.06 | BI57: 10.96 | BJ57: 15.15 | BK57: 11.03 | BL57: 15.25 | BM57: Negativa | BN57: Grupo 2
A58: Natulab | B58: Medicamentos | C58: 7899470804576 | D58: 34071 | E58: 15000191 | F58: Maxalgina 500mg 3bl X 10com X 100ct - Farma | G58: 30049069 | H58: ATIVO | I58: 100 | J58: 4.23 | L58: 4.15 | M58: 4.23 | N58: =IFERROR(100%-(J58/M58),0) -> 0 | P58: 4.55 | Q58: =IFERROR(100%-(M58/P58),0) -> 0.07032967 | S58: 4.89 | T58: =IFERROR(100%-(M58/S58),0) -> 0.13496933 | V58: 4.2875564 | W58: =IFERROR(100%-(M58/V58),0) -> 0.01342406 | Y58: 4.5798898 | Z58: =IFERROR(100%-(M58/Y58),0) -> 0.076396992 | AB58: 4.9150037 | AC58: =IFERROR(100%-(M58/AB58),0) -> 0.13936992 | AE58: 4.0507614 | AF58: =IFERROR(100%-(M58/AE58),0) -> -0.04424812 | AH58: 0 | AI58: =IFERROR(100%-(M58/AH58),0) -> 0 | AK58: 0 | AL58: =IFERROR(100%-(M58/AK58),0) -> 0 | AN58: 4.01191 | AO58: =IFERROR(100%-(M58/AN58),0) -> -0.054360641 | AR58: =IFERROR(100%-(P58/AQ58),0) -> 0 | AT58: 15.49 | AU58: 12.36 | AV58: 16.58 | AW58: 14.28 | AX58: 19.07 | AY58: 15.27 | AZ58: 20.35 | BA58: 15.38 | BB58: 20.49 | BC58: 15.49 | BD58: 20.64 | BE58: 15.94 | BF58: 21.22 | BG58: 13.3 | BH58: 18.39 | BI58: 13.38 | BJ58: 18.5 | BK58: 13.46 | BL58: 18.61 | BM58: Negativa | BN58: Grupo 2
A59: Natulab | B59: Medicamentos | C59: 7898133138751 | D59: 23916 | E59: 15000097 | F59: Maxalgina C/Seringa 100ml 1ct X 50fr - Farma | G59: 30049069 | H59: ATIVO | I59: 50 | J59: 3.6 | L59: 0 | M59: 3.6 | N59: =IFERROR(100%-(J59/M59),0) -> 0 | P59: 3.87 | Q59: =IFERROR(100%-(M59/P59),0) -> 0.069767442 | S59: 4.16 | T59: =IFERROR(100%-(M59/S59),0) -> 0.13461538 | V59: 3.6428111 | W59: =IFERROR(100%-(M59/V59),0) -> 0.011752212 | Y59: 3.8911846 | Z59: =IFERROR(100%-(M59/Y59),0) -> 0.074831858 | AB59: 4.1759054 | AC59: =IFERROR(100%-(M59/AB59),0) -> 0.1379115 | AE59: 3.4416244 | AF59: =IFERROR(100%-(M59/AE59),0) -> -0.046017699 | AH59: 0 | AI59: =IFERROR(100%-(M59/AH59),0) -> 0 | AK59: 0 | AL59: =IFERROR(100%-(M59/AK59),0) -> 0 | AN59: 3.5443737 | AO59: =IFERROR(100%-(M59/AN59),0) -> -0.015694254 | AR59: =IFERROR(100%-(P59/AQ59),0) -> 0 | AT59: 18.66 | AU59: 14.89 | AV59: 19.97 | AW59: 17.2 | AX59: 22.97 | AY59: 18.4 | AZ59: 24.52 | BA59: 18.53 | BB59: 24.69 | BC59: 18.66 | BD59: 24.86 | BE59: 19.2 | BF59: 25.56 | BG59: 16.02 | BH59: 22.15 | BI59: 16.12 | BJ59: 22.29 | BK59: 16.21 | BL59: 22.41 | BM59: Negativa | BN59: Grupo 2
... A74: Natulab | B74: Medicamentos | C74: 7899470806020 | D74: 36393 | E74: 15000193 | F74: Pausefemme 150mg 3bl X 10com X 50ct - Farma | G74: 30049099 | H74: ATIVO | I74: 50 | J74: 27.41 | L74: 21 | M74: 27.41 | N74: =IFERROR(100%-(J74/M74),0) -> 0 | P74: 29.47 | Q74: =IFERROR(100%-(M74/P74),0) -> 0.069901595 | S74: 31.69 | T74: =IFERROR(100%-(M74/S74),0) -> 0.13505838 | V74: 27.1875 | W74: =IFERROR(100%-(M74/V74),0) -> -0.008183908 | Y74: 29.659091 | Z74: =IFERROR(100%-(M74/Y74),0) -> 0.075831418 | AB74: 22.160631 | AC74: =IFERROR(100%-(M74/AB74),0) -> -0.23687815 | AE74: 18.263959 | AF74: =IFERROR(100%-(M74/AE74),0) -> -0.50076987 | AH74: 0 | AI74: =IFERROR(100%-(M74/AH74),0) -> 0 | AK74: 0 | AL74: =IFERROR(100%-(M74/AK74),0) -> 0 | AN74: 0 | AO74: =IFERROR(100%-(M74/AN74),0) -> 0 | AR74: =IFERROR(100%-(P74/AQ74),0) -> 0 | AT74: 81.32 | AU74: 64.89 | AV74: 87.04 | AW74: 74.99 | AX74: 100.17 | AY74: 80.19 | AZ74: 106.88 | BA74: 80.75 | BB74: 107.6 | BC74: 81.32 | BD74: 108.34 | BE74: 83.67 | BF74: 111.37 | BG74: 69.81 | BH74: 96.51 | BI74: 70.23 | BJ74: 97.09 | BK74: 70.66 | BL74: 97.68 | BM74: Negativa | BN74: Grupo 2
A75: Natulab | B75: Medicamentos | C75: 7899470803104 | D75: 24038 | E75: 15000176 | F75: Plantolaxy 5g 10env X 50ct - Farma | G75: 30049099 | H75: ATIVO | I75: 50 | J75: 11.99 | M75: 0 | N75: =IFERROR(100%-(J75/M75),0) -> 0 | P75: 0 | Q75: =IFERROR(100%-(M75/P75),0) -> 0 | S75: 0 | T75: =IFERROR(100%-(M75/S75),0) -> 0 | V75: 0 | W75: =IFERROR(100%-(M75/V75),0) -> 0 | Y75: 0 | Z75: =IFERROR(100%-(M75/Y75),0) -> 0 | AB75: 0 | AC75: =IFERROR(100%-(M75/AB75),0) -> 0 | AE75: 0 | AF75: =IFERROR(100%-(M75/AE75),0) -> 0 | AH75: 0 | AI75: =IFERROR(100%-(M75/AH75),0) -> 0 | AK75: 0 | AL75: =IFERROR(100%-(M75/AK75),0) -> 0 | AN75: 0 | AO75: =IFERROR(100%-(M75/AN75),0) -> 0 | AR75: =IFERROR(100%-(P75/AQ75),0) -> 0 | AT75: 42.22 | AU75: 33.69 | AV75: 45.19 | AW75: 38.93 | AX75: 52 | AY75: 41.63 | AZ75: 55.49 | BA75: 41.92 | BB75: 55.86 | BC75: 42.22 | BD75: 56.25 | BE75: 43.44 | BF75: 57.82 | BG75: 36.24 | BH75: 50.1 | BI75: 36.46 | BJ75: 50.4 | BK75: 36.69 | BL75: 50.72 | BM75: Negativa | BN75: Grupo 2
A76: Natulab | B76: Medicamentos | C76: 7898133131066 | D76: 23974 | E76: 15000102 | F76: Polaradex 100ml 1ct X 50fr - Farma | G76: 30049069 | H76: ATIVO | I76: 50 | J76: 2.53 | L76: 2.4852762 | M76: 2.53 | N76: =IFERROR(100%-(J76/M76),0) -> 0 | P76: 2.72 | Q76: =IFERROR(100%-(M76/P76),0) -> 0.069852941 | S76: 2.93 | T76: =IFERROR(100%-(M76/S76),0) -> 0.13651877 | V76: 2.5638298 | W76: =IFERROR(100%-(M76/V76),0) -> 0.013195021 | Y76: 2.7386364 | Z76: =IFERROR(100%-(M76/Y76),0) -> 0.076182573 | AB76: 2.9390244 | AC76: =IFERROR(100%-(M76/AB76),0) -> 0.13917012 | AE76: 2.41 | AF76: =IFERROR(100%-(M76/AE76),0) -> -0.049792531 | AH76: 2.38 | AI76: =IFERROR(100%-(M76/AH76),0) -> -0.06302521 | AK76: 0 | AL76: =IFERROR(100%-(M76/AK76),0) -> 0 | AN76: 0 | AO76: =IFERROR(100%-(M76/AN76),0) -> 0 | AR76: =IFERROR(100%-(P76/AQ76),0) -> 0 | AT76: 12.23 | AU76: 9.76 | AV76: 13.09 | AW76: 11.27 | AX76: 15.05 | AY76: 12.06 | AZ76: 16.07 | BA76: 12.14 | BB76: 16.17 | BC76: 12.23 | BD76: 16.29 | BE76: 12.58 | BF76: 16.74 | BG76: 10.5 | BH76: 14.52 | BI76: 10.56 | BJ76: 14.6 | BK76: 10.63 | BL76: 14.7 | BM76: Negativa | BN76: Grupo 3
A77: Natulab | B77: Medicamentos | C77: 7898133137457 | D77: 23982 | E77: 15000103 | F77: Pvpi Spray 100ml 1 X 50fr - Farma | G77: 30049099 | H77: ATIVO | I77: 50 | J77: 6.72 | L77: 6.6 | M77: 6.72 | N77: =IFERROR(100%-(J77/M77),0) -> 0 | P77: 7.23 | Q77: =IFERROR(100%-(M77/P77),0) -> 0.070539419 | S77: 7.77 | T77: =IFERROR(100%-(M77/S77),0) -> 0.13513514 | V77: 6.4367075 | W77: =IFERROR(100%-(M77/V77),0) -> -0.04401202 | Y77: 6.8755739 | Z77: =IFERROR(100%-(M77/Y77),0) -> 0.022627045 | AB77: 7.3786647 | AC77: =IFERROR(100%-(M77/AB77),0) -> 0.08926611 | AE77: 6.0812183 | AF77: =IFERROR(100%-(M77/AE77),0) -> -0.10504174 | AH77: 0 | AI77: =IFERROR(100%-(M77/AH77),0) -> 0 | AK77: 0 | AL77: =IFERROR(100%-(M77/AK77),0) -> 0 | AN77: 0 | AO77: =IFERROR(100%-(M77/AN77),0) -> 0 | AR77: =IFERROR(100%-(P77/AQ77),0) -> 0 | AT77: 25.64 | AU77: 20.46 | AV77: 27.44 | AW77: 23.64 | AX77: 31.57 | AY77: 25.28 | AZ77: 33.69 | BA77: 25.46 | BB77: 33.92 | BC77: 25.64 | BD77: 34.16 | BE77: 26.38 | BF77: 35.11 | BG77: 22.01 | BH77: 30.43 | BI77: 22.14 | BJ77: 30.61 | BK77: 22.28 | BL77: 30.8 | BM77: Negativa | BN77: Grupo 1
A78: Natulab | B78: Medicamentos | C78: 7898133134784 | D78: 34671 | E78: 15000134 | F78: Rifotrat Spray 20ml 1ct X 50fr - Farma | G78: 30042031 | H78: ATIVO | I78: 50 | J78: 3.95 | L78: 3.85 | M78: 3.95 | N78: =IFERROR(100%-(J78/M78),0) -> 0 | P78: 4.24 | Q78: =IFERROR(100%-(M78/P78),0) -> 0.068396226 | S78: 4.56 | T78: =IFERROR(100%-(M78/S78),0) -> 0.13377193 | V78: 3.997421 | W78: =IFERROR(100%-(M78/V78),0) -> 0.011862903 | Y78: 4.2699725 | Z78: =IFERROR(100%-(M78/Y78),0) -> 0.074935484 | AB78: 4.5824095 | AC78: =IFERROR(100%-(M78/AB78),0) -> 0.13800806 | AE78: 3.76 | AF78: =IFERROR(100%-(M78/AE78),0) -> -0.050531915 | AH78: 3.22 | AI78: =IFERROR(100%-(M78/AH78),0) -> -0.22670807 | AK78: 4.7 | AL78: =IFERROR(100%-(M78/AK78),0) -> 0.15957447 | AN78: 4.716873 | AO78: =IFERROR(100%-(M78/AN78),0) -> 0.1625808 | AR78: =IFERROR(100%-(P78/AQ78),0) -> 0 | AT78: 17.7 | AU78: 14.51 | AV78: 20.05 | AW78: 16.49 | AX78: 22.79 | AY78: 17.48 | AZ78: 24.16 | BA78: 17.59 | BB78: 24.31 | BC78: 17.7 | BD78: 24.47 | BE78: 18.14 | BF78: 25.08 | BG78: 17.49 | BH78: 24.18 | BI78: 17.59 | BJ78: 24.32 | BK78: 17.7 | BL78: 24.47 | BM78: Positiva | BN78: Grupo 3
A79: Natulab | B79: Medicamentos | C79: 7898133136047 | D79: 24694 | E79: 15000187 | F79: Seakalm 260mg 2bl X 10com X 50ct - Farma | G79: 30049099 | H79: ATIVO | I79: 50 | J79: 8.1 | L79: 7.95 | M79: 8.1 | N79: =IFERROR(100%-(J79/M79),0) -> 0 | P79: 8.71 | Q79: =IFERROR(100%-(M79/P79),0) -> 0.070034443 | S79: 9.37 | T79: =IFERROR(100%-(M79/S79),0) -> 0.13553895 | V79: 8.2097571 | W79: =IFERROR(100%-(M79/V79),0) -> 0.01336911 | Y79: 8.7695133 | Z79: =IFERROR(100%-(M79/Y79),0) -> 0.07634555 | AB79: 9.411185 | AC79: =IFERROR(100%-(M79/AB79),0) -> 0.13932199 | AE79: 7.4619289 | AF79: =IFERROR(100%-(M79/AE79),0) -> -0.085510204 | AH79: 7.72 | AI79: =IFERROR(100%-(M79/AH79),0) -> -0.049222798 | AK79: 13.6641 | AL79: =IFERROR(100%-(M79/AK79),0) -> 0.40720574 | AN79: 11.272329 | AO79: =IFERROR(100%-(M79/AN79),0) -> 0.2814262 | AR79: =IFERROR(100%-(P79/AQ79),0) -> 0 | AT79: 36.93 | AU79: 29.47 | AV79: 39.53 | AW79: 34.05 | AX79: 45.48 | AY79: 36.41 | AZ79: 48.53 | BA79: 36.67 | BB79: 48.86 | BC79: 36.93 | BD79: 49.2 | BE79: 38 | BF79: 50.58 | BG79: 31.7 | BH79: 43.82 | BI79: 31.9 | BJ79: 44.1 | BK79: 32.09 | BL79: 44.36 | BM79: Negativa | BN79: Grupo 1
A80: Natulab | B80: Medicamentos | C80: 7899470800882 | D80: 23994 | E80: 15000106 | F80: Seakalm Solucao 90mg 100ml 1ct X 50fr - Farma | G80: 30049099 | H80: ATIVO | I80: 50 | J80: 9.89 | L80: 9.7 | M80: 9.89 | N80: =IFERROR(100%-(J80/M80),0) -> 0 | P80: 10.63 | Q80: =IFERROR(100%-(M80/P80),0) -> 0.069614299 | S80: 11.43 | T80: =IFERROR(100%-(M80/S80),0) -> 0.13473316 | V80: 10.019102 | W80: =IFERROR(100%-(M80/V80),0) -> 0.012885552 | Y80: 10.702222 | Z80: =IFERROR(100%-(M80/Y80),0) -> 0.075892857 | AB80: 11.485312 | AC80: =IFERROR(100%-(M80/AB80),0) -> 0.13890016 | AE80: 9.0253807 | AF80: =IFERROR(100%-(M80/AE80),0) -> -0.09579865 | AH80: 9.42 | AI80: =IFERROR(100%-(M80/AH80),0) -> -0.049893843 | AK80: 15.9495 | AL80: =IFERROR(100%-(M80/AK80),0) -> 0.37991787 | AN80: 12.009202 | AO80: =IFERROR(100%-(M80/AN80),0) -> 0.17646483 | AR80: =IFERROR(100%-(P80/AQ80),0) -> 0 | AT80: 51.45 | AU80: 41.05 | AV80: 55.06 | AW80: 47.44 | AX80: 63.37 | AY80: 50.73 | AZ80: 67.61 | BA80: 51.09 | BB80: 68.08 | BC80: 51.45 | BD80: 68.55 | BE80: 52.94 | BF80: 70.47 | BG80: 44.17 | BH80: 61.06 | BI80: 44.44 | BJ80: 61.44 | BK80: 44.71 | BL80: 61.81 | BM80: Negativa | BN80: Grupo 1
A81: Natulab | B81: Medicamentos | C81: 7898133135163 | D81: 24054 | E81: 15000264 | F81: STARFOR C COM EFEVERSCENTE 1G X 10 | G81: 30045090 | H81: ATIVO | I81: 100 | J81: 6.92 | M81: 0 | N81: =IFERROR(100%-(J81/M81),0) -> 0 | P81: 0 | Q81: =IFERROR(100%-(M81/P81),0) -> 0 | S81: 0 | T81: =IFERROR(100%-(M81/S81),0) -> 0 | V81: 0 | W81: =IFERROR(100%-(M81/V81),0) -> 0 | Y81: 0 | Z81: =IFERROR(100%-(M81/Y81),0) -> 0 | AB81: 0 | AC81: =IFERROR(100%-(M81/AB81),0) -> 0 | AE81: 6.3248731 | AF81: =IFERROR(100%-(M81/AE81),0) -> 1 | AH81: 6.59 | AI81: =IFERROR(100%-(M81/AH81),0) -> 1 | AK81: 11.4205 | AL81: =IFERROR(100%-(M81/AK81),0) -> 1 | AN81: 0 | AO81: =IFERROR(100%-(M81/AN81),0) -> 0 | AR81: =IFERROR(100%-(P81/AQ81),0) -> 0 | AT81: 32.63 | AU81: 26.03 | AV81: 34.91 | AW81: 30.09 | AX81: 40.19 | AY81: 32.17 | AZ81: 42.88 | BA81: 32.4 | BB81: 43.17 | BC81: 32.63 | BD81: 43.47 | BE81: 33.58 | BF81: 44.7 | BG81: 28.01 | BH81: 38.72 | BI81: 28.18 | BJ81: 38.96 | BK81: 28.35 | BL81: 39.19 | BM81: Negativa | BN81: Grupo 2
A82: Natulab | B82: Medicamentos | C82: 7898133131509 | D82: 23996 | E82: 15000107 | F82: Tylemax Baby 15ml 1ct X 100fr - Farma | G82: 30049045 | H82: ATIVO | I82: 100 | J82: 3.38 | L82: 3.29 | M82: 3.38 | N82: =IFERROR(100%-(J82/M82),0) -> 0 | P82: 3.64 | Q82: =IFERROR(100%-(M82/P82),0) -> 0.071428571 | S82: 3.91 | T82: =IFERROR(100%-(M82/S82),0) -> 0.13554987 | V82: 3.3956587 | W82: =IFERROR(100%-(M82/V82),0) -> 0.0046113924 | Y82: 3.6271809 | Z82: =IFERROR(100%-(M82/Y82),0) -> 0.068146835 | AB82: 3.8925844 | AC82: =IFERROR(100%-(M82/AB82),0) -> 0.13168228 | AE82: 3.2081218 | AF82: =IFERROR(100%-(M82/AE82),0) -> -0.053575949 | AH82: 3.19 | AI82: =IFERROR(100%-(M82/AH82),0) -> -0.059561129 | AK82: 0 | AL82: =IFERROR(100%-(M82/AK82),0) -> 0 | AN82: 0 | AO82: =IFERROR(100%-(M82/AN82),0) -> 0 | AR82: =IFERROR(100%-(P82/AQ82),0) -> 0 | AT82: 25.81 | AU82: 20.59 | AV82: 27.62 | AW82: 23.8 | AX82: 31.79 | AY82: 25.45 | AZ82: 33.92 | BA82: 25.63 | BB82: 34.15 | BC82: 25.81 | BD82: 34.39 | BE82: 26.56 | BF82: 35.35 | BG82: 22.16 | BH82: 30.64 | BI82: 22.29 | BJ82: 30.82 | BK82: 22.43 | BL82: 31.01 | BM82: Negativa | BN82: Grupo 2
A83: Natulab | B83: Medicamentos | C83: 7898133130410 | D83: 24016 | E83: 15000109 | F83: Tylemax 15ml 1ct X 200fr - Farma | G83: 30049045 | H83: ATIVO | I83: 200 | J83: 1.53 | L83: 1.37 | M83: 1.53 | N83: =IFERROR(100%-(J83/M83),0) -> 0 | P83: 1.65 | Q83: =IFERROR(100%-(M83/P83),0) -> 0.072727273 | S83: 1.77 | T83: =IFERROR(100%-(M83/S83),0) -> 0.13559322 | V83: 1.4184397 | W83: =IFERROR(100%-(M83/V83),0) -> -0.07865 | Y83: 1.5151515 | Z83: =IFERROR(100%-(M83/Y83),0) -> -0.0098 | AB83: 1.6260163 | AC83: =IFERROR(100%-(M83/AB83),0) -> 0.05905 | AE83: 1.36 | AF83: =IFERROR(100%-(M83/AE83),0) -> -0.125 | AH83: 1.04 | AI83: =IFERROR(100%-(M83/AH83),0) -> -0.47115385 | AK83: 3.9849 | AL83: =IFERROR(100%-(M83/AK83),0) -> 0.61605059 | AN83: 3.7611 | AO83: =IFERROR(100%-(M83/AN83),0) -> 0.59320412 | AR83: =IFERROR(100%-(P83/AQ83),0) -> 0 | AT83: 10.77 | AU83: 8.59 | AV83: 11.52 | AW83: 9.93 | AX83: 13.26 | AY83: 10.62 | AZ83: 14.15 | BA83: 10.69 | BB83: 14.24 | BC83: 10.77 | BD83: 14.35 | BE83: 11.08 | BF83: 14.75 | BG83: 9.25 | BH83: 12.79 | BI83: 9.3 | BJ83: 12.86 | BK83: 9.36 | BL83: 12.94 | BM83: Negativa | BN83: Grupo 2
A84: Natulab | B84: Medicamentos | C84: 7898133137471 | D84: 24009 | E84: 15000108 | F84: Tylemax Crianca 60ml 1ct X 100fr - Farma | G84: 30049045 | H84: ATIVO | I84: 100 | J84: 3.23 | L84: 3.17 | M84: 3.23 | N84: =IFERROR(100%-(J84/M84),0) -> 0 | P84: 3.48 | Q84: =IFERROR(100%-(M84/P84),0) -> 0.07183908 | S84: 3.74 | T84: =IFERROR(100%-(M84/S84),0) -> 0.13636364 | V84: 3.2774554 | W84: =IFERROR(100%-(M84/V84),0) -> 0.014479344 | Y84: 3.5009183 | Z84: =IFERROR(100%-(M84/Y84),0) -> 0.077384918 | AB84: 3.757083 | AC84: =IFERROR(100%-(M84/AB84),0) -> 0.14029049 | AE84: 3.0964467 | AF84: =IFERROR(100%-(M84/AE84),0) -> -0.043131148 | AH84: 0 | AI84: =IFERROR(100%-(M84/AH84),0) -> 0 | AK84: 0 | AL84: =IFERROR(100%-(M84/AK84),0) -> 0 | AN84: 0 | AO84: =IFERROR(100%-(M84/AN84),0) -> 0 | AR84: =IFERROR(100%-(P84/AQ84),0) -> 0 | AT84: 20 | AU84: 15.96 | AV84: 21.41 | AW84: 18.44 | AX84: 24.63 | AY84: 19.72 | AZ84: 26.28 | BA84: 19.86 | BB84: 26.46 | BC84: 20 | BD84: 26.65 | BE84: 20.58 | BF84: 27.39 | BG84: 17.17 | BH84: 23.74 | BI84: 17.27 | BJ84: 23.88 | BK84: 17.38 | BL84: 24.03 | BM84: Negativa | BN84: Grupo 2
A85: Natulab | B85: Medicamentos | C85: 7899470805221 | D85: 24020 | E85: 15000110 | F85: Unhagold 30ml 1ct X 100fr - Farma | G85: 30049029 | H85: ATIVO | I85: 100 | J85: 9.05 | L85: 8.87 | M85: 9.05 | N85: =IFERROR(100%-(J85/M85),0) -> 0 | P85: 9.73 | Q85: =IFERROR(100%-(M85/P85),0) -> 0.069886948 | S85: 10.46 | T85: =IFERROR(100%-(M85/S85),0) -> 0.13479924 | V85: 9.1674189 | W85: =IFERROR(100%-(M85/V85),0) -> 0.01280828 | Y85: 9.7924702 | Z85: =IFERROR(100%-(M85/Y85),0) -> 0.075820518 | AB85: 10.508992 | AC85: =IFERROR(100%-(M85/AB85),0) -> 0.13883276 | AE85: 8.2614213 | AF85: =IFERROR(100%-(M85/AE85),0) -> -0.095453149 | AH85: 8.62 | AI85: =IFERROR(100%-(M85/AH85),0) -> -0.049883991 | AK85: 0 | AL85: =IFERROR(100%-(M85/AK85),0) -> 0 | AN85: 0 | AO85: =IFERROR(100%-(M85/AN85),0) -> 0 | AR85: =IFERROR(100%-(P85/AQ85),0) -> 0 | AT85: 63.4 | AU85: 50.59 | AV85: 67.86 | AW85: 58.46 | AX85: 78.09 | AY85: 62.52 | AZ85: 83.33 | BA85: 62.95 | BB85: 83.88 | BC85: 63.4 | BD85: 84.47 | BE85: 65.24 | BF85: 86.84 | BG85: 54.43 | BH85: 75.25 | BI85: 54.76 | BJ85: 75.7 | BK85: 55.09 | BL85: 76.16 | BM85: Negativa | BN85: Grupo 1
A86: Natulab | B86: Medicamentos | C86: 7898133137242 | D86: 24058 | E86: 15000178 | F86: Valessone 225.75mg 2bl X 10com X 50ct - Farma | G86: 30045090 | H86: ATIVO | I86: 50 | J86: 7.33 | L86: 7.19 | M86: 7.33 | N86: =IFERROR(100%-(J86/M86),0) -> 0 | P86: 7.88 | Q86: =IFERROR(100%-(M86/P86),0) -> 0.069796954 | S86: 8.48 | T86: =IFERROR(100%-(M86/S86),0) -> 0.13561321 | V86: 7.4285665 | W86: =IFERROR(100%-(M86/V86),0) -> 0.013268578 | Y86: 7.9350597 | Z86: =IFERROR(100%-(M86/Y86),0) -> 0.076251435 | AB86: 8.5156738 | AC86: =IFERROR(100%-(M86/AB86),0) -> 0.13923429 | AE86: 6.6944162 | AF86: =IFERROR(100%-(M86/AE86),0) -> -0.094942372 | AH86: 6.98 | AI86: =IFERROR(100%-(M86/AH86),0) -> -0.050143266 | AK86: 8.52 | AL86: =IFERROR(100%-(M86/AK86),0) -> 0.13967136 | AN86: 8.0514 | AO86: =IFERROR(100%-(M86/AN86),0) -> 0.089599324 | AR86: =IFERROR(100%-(P86/AQ86),0) -> 0 | AT86: 43.25 | AU86: 34.51 | AV86: 46.29 | AW86: 39.88 | AX86: 53.27 | AY86: 42.65 | AZ86: 56.84 | BA86: 42.94 | BB86: 57.22 | BC86: 43.25 | BD86: 57.62 | BE86: 44.5 | BF86: 59.23 | BG86: 37.13 | BH86: 51.33 | BI86: 37.35 | BJ86: 51.63 | BK86: 37.58 | BL86: 51.95 | BM86: Negativa | BN86: Grupo 2
A87: Natulab | B87: Medicamentos | C87: 7898133136450 | D87: 24061 | E87: 15000179 | F87: Varivax 100mg 3bl X 10com X 50ct - Farma | G87: 30049099 | H87: ATIVO | I87: 50 | J87: 7.65 | L87: 7.42 | M87: 7.65 | N87: =IFERROR(100%-(J87/M87),0) -> 0 | P87: 8.23 | Q87: =IFERROR(100%-(M87/P87),0) -> 0.070473876 | S87: 8.85 | T87: =IFERROR(100%-(M87/S87),0) -> 0.13559322 | V87: 7.59375 | W87: =IFERROR(100%-(M87/V87),0) -> -0.0074074074 | Y87: 8.2840909 | Z87: =IFERROR(100%-(M87/Y87),0) -> 0.07654321 | AB87: 9.0487805 | AC87: =IFERROR(100%-(M87/AB87),0) -> 0.15458221 | AE87: 7.42 | AF87: =IFERROR(100%-(M87/AE87),0) -> -0.030997305 | AH87: 6.92 | AI87: =IFERROR(100%-(M87/AH87),0) -> -0.10549133 | AK87: 17.9648 | AL87: =IFERROR(100%-(M87/AK87),0) -> 0.57416726 | AN87: 10.731722 | AO87: =IFERROR(100%-(M87/AN87),0) -> 0.28716009 | AR87: =IFERROR(100%-(P87/AQ87),0) -> 0 | AT87: 64.16 | AU87: 51.2 | AV87: 68.68 | AW87: 59.16 | AX87: 79.02 | AY87: 63.27 | AZ87: 84.33 | BA87: 63.71 | BB87: 84.9 | BC87: 64.16 | BD87: 85.48 | BE87: 66.02 | BF87: 87.88 | BG87: 55.08 | BH87: 76.15 | BI87: 55.41 | BJ87: 76.6 | BK87: 55.75 | BL87: 77.07 | BM87: Negativa | BN87: Grupo 2
A88: Natulab | B88: Medicamentos | C88: 7899470803975 | D88: 24065 | E88: 15000180 | F88: Varivax 300mg 3bl X 10com X 50ct - Farma | G88: 30049099 | H88: ATIVO | I88: 50 | J88: 10.8 | L88: 10.59 | M88: 10.8 | N88: =IFERROR(100%-(J88/M88),0) -> 0 | P88: 11.62 | Q88: =IFERROR(100%-(M88/P88),0) -> 0.070567986 | S88: 12.49 | T88: =IFERROR(100%-(M88/S88),0) -> 0.13530825 | V88: 10.71875 | W88: =IFERROR(100%-(M88/V88),0) -> -0.0075801749 | Y88: 11.693182 | Z88: =IFERROR(100%-(M88/Y88),0) -> 0.07638484 | AB88: 12.914634 | AC88: =IFERROR(100%-(M88/AB88),0) -> 0.16373938 | AE88: 10.59 | AF88: =IFERROR(100%-(M88/AE88),0) -> -0.019830028 | AH88: 10.09 | AI88: =IFERROR(100%-(M88/AH88),0) -> -0.0703667 | AK88: 19.348 | AL88: =IFERROR(100%-(M88/AK88),0) -> 0.44180277 | AN88: 14.822986 | AO88: =IFERROR(100%-(M88/AN88),0) -> 0.27140189 | AR88: =IFERROR(100%-(P88/AQ88),0) -> 0 | AT88: 69.1 | AU88: 55.14 | AV88: 73.96 | AW88: 63.72 | AX88: 85.11 | AY88: 68.14 | AZ88: 90.82 | BA88: 68.61 | BB88: 91.43 | BC88: 69.1 | BD88: 92.06 | BE88: 71.1 | BF88: 94.64 | BG88: 59.32 | BH88: 82.01 | BI88: 59.68 | BJ88: 82.5 | BK88: 60.04 | BL88: 83 | BM88: Negativa | BN88: Grupo 2
A89: Natulab | B89: Medicamentos | C89: 7898133135606 | D89: 24068 | E89: 15000181 | F89: Vitamin E 400mg 1fr X 30cap X 50ct - Farma | G89: 30049099 | H89: ATIVO | I89: 50 | J89: 7.87 | L89: 7.72 | M89: 7.87 | N89: =IFERROR(100%-(J89/M89),0) -> 0 | P89: 8.46 | Q89: =IFERROR(100%-(M89/P89),0) -> 0.069739953 | S89: 9.1 | T89: =IFERROR(100%-(M89/S89),0) -> 0.13516484 | V89: 7.8065993 | W89: =IFERROR(100%-(M89/V89),0) -> -0.0081214202 | Y89: 8.5162902 | Z89: =IFERROR(100%-(M89/Y89),0) -> 0.075888698 | AB89: 9.1394334 | AC89: =IFERROR(100%-(M89/AB89),0) -> 0.13889629 | AE89: 7.1878173 | AF89: =IFERROR(100%-(M89/AE89),0) -> -0.094908192 | AH89: 0 | AI89: =IFERROR(100%-(M89/AH89),0) -> 0 | AK89: 8.0604 | AL89: =IFERROR(100%-(M89/AK89),0) -> 0.023621656 | AN89: 0 | AO89: =IFERROR(100%-(M89/AN89),0) -> 0 | AR89: =IFERROR(100%-(P89/AQ89),0) -> 0 | AT89: 44.78 | AU89: 35.73 | AV89: 47.93 | AW89: 41.29 | AX89: 55.15 | AY89: 44.15 | AZ89: 58.84 | BA89: 44.46 | BB89: 59.24 | BC89: 44.78 | BD89: 59.66 | BE89: 46.08 | BF89: 61.33 | BG89: 38.44 | BH89: 53.14 | BI89: 38.67 | BJ89: 53.46 | BK89: 38.91 | BL89: 53.79 | BM89: Negativa | BN89: Grupo 2
A90: Natulab | B90: Medicamentos | C90: 7899470800325 | D90: 24099 | E90: 15000265 | F90: VITER C + ZINCO COM EFEVERSCENTE 1G X 10 | G90: 30045090 | H90: ATIVO | I90: 100 | J90: 5.13 | M90: 0 | N90: =IFERROR(100%-(J90/M90),0) -> 0 | P90: 0 | Q90: =IFERROR(100%-(M90/P90),0) -> 0 | S90: 0 | T90: =IFERROR(100%-(M90/S90),0) -> 0 | V90: 0 | W90: =IFERROR(100%-(M90/V90),0) -> 0 | Y90: 0 | Z90: =IFERROR(100%-(M90/Y90),0) -> 0 | AB90: 0 | AC90: =IFERROR(100%-(M90/AB90),0) -> 0 | AE90: 4.89 | AF90: =IFERROR(100%-(M90/AE90),0) -> 1 | AH90: 4.79 | AI90: =IFERROR(100%-(M90/AH90),0) -> 1 | AK90: 0 | AL90: =IFERROR(100%-(M90/AK90),0) -> 0 | AN90: 0 | AO90: =IFERROR(100%-(M90/AN90),0) -> 0 | AR90: =IFERROR(100%-(P90/AQ90),0) -> 0 | AT90: 25.97 | AU90: 20.72 | AV90: 27.79 | AW90: 23.94 | AX90: 31.97 | AY90: 25.61 | AZ90: 34.13 | BA90: 25.78 | BB90: 34.35 | BC90: 25.97 | BD90: 34.6 | BE90: 26.72 | BF90: 35.57 | BG90: 22.29 | BH90: 30.82 | BI90: 22.43 | BJ90: 31.01 | BK90: 22.57 | BL90: 31.2 | BM90: Negativa | BN90: Grupo 2
A91: Natulab | B91: Medicamentos | C91: 7898133136481 | D91: 24069 | E91: 15000182 | F91: Viter C Comprimidos 500mg 2bl X 10com X 100ct - Farma | G91: 30045090 | H91: ATIVO | I91: 100 | J91: 3.46 | L91: 3.39 | M91: 3.46 | N91: =IFERROR(100%-(J91/M91),0) -> 0 | P91: 3.72 | Q91: =IFERROR(100%-(M91/P91),0) -> 0.069892473 | S91: 4 | T91: =IFERROR(100%-(M91/S91),0) -> 0.135 | V91: 3.4284175 | W91: =IFERROR(100%-(M91/V91),0) -> -0.0092119736 | Y91: 3.7400918 | Z91: =IFERROR(100%-(M91/Y91),0) -> 0.074889024 | AB91: 4.0137571 | AC91: =IFERROR(100%-(M91/AB91),0) -> 0.13796477 | AE91: 3.1573604 | AF91: =IFERROR(100%-(M91/AE91),0) -> -0.09585209 | AH91: 3.29 | AI91: =IFERROR(100%-(M91/AH91),0) -> -0.051671733 | AK91: 6.7456 | AL91: =IFERROR(100%-(M91/AK91),0) -> 0.48707306 | AN91: 7.378 | AO91: =IFERROR(100%-(M91/AN91),0) -> 0.53103822 | AR91: =IFERROR(100%-(P91/AQ91),0) -> 0 | AT91: 21.08 | AU91: 16.82 | AV91: 22.56 | AW91: 19.43 | AX91: 25.95 | AY91: 20.78 | AZ91: 27.69 | BA91: 20.93 | BB91: 27.89 | BC91: 21.08 | BD91: 28.09 | BE91: 21.69 | BF91: 28.87 | BG91: 18.1 | BH91: 25.02 | BI91: 18.21 | BJ91: 25.17 | BK91: 18.32 | BL91: 25.33 | BM91: Negativa | BN91: Grupo 2
A92: Natulab | B92: Medicamentos | C92: 7899470800240 | D92: 24096 | E92: 15000263 | F92: VITER C COM EFEVERVESCENTE 1G X 10 | G92: 30045090 | H92: ATIVO | I92: 100 | J92: 3.89 | M92: 0 | N92: =IFERROR(100%-(J92/M92),0) -> 0 | P92: 0 | Q92: =IFERROR(100%-(M92/P92),0) -> 0 | S92: 0 | T92: =IFERROR(100%-(M92/S92),0) -> 0 | V92: 0 | W92: =IFERROR(100%-(M92/V92),0) -> 0 | Y92: 0 | Z92: =IFERROR(100%-(M92/Y92),0) -> 0 | AB92: 0 | AC92: =IFERROR(100%-(M92/AB92),0) -> 0 | AE92: 3.07 | AF92: =IFERROR(100%-(M92/AE92),0) -> 1 | AH92: 3.02 | AI92: =IFERROR(100%-(M92/AH92),0) -> 1 | AK92: 4.4229 | AL92: =IFERROR(100%-(M92/AK92),0) -> 1 | AN92: 4.6152 | AO92: =IFERROR(100%-(M92/AN92),0) -> 1 | AR92: =IFERROR(100%-(P92/AQ92),0) -> 0 | AT92: 19.23 | AU92: 15.34 | AV92: 20.57 | AW92: 17.73 | AX92: 23.68 | AY92: 18.96 | AZ92: 25.27 | BA92: 19.09 | BB92: 25.44 | BC92: 19.23 | BD92: 25.62 | BE92: 19.79 | BF92: 26.34 | BG92: 16.51 | BH92: 22.82 | BI92: 16.61 | BJ92: 22.96 | BK92: 16.71 | BL92: 23.1 | BM92: Negativa | BN92: Grupo 2
A93: Natulab | B93: Medicamentos | C93: 7899470802961 | D93: 28916 | E93: 15000125 | F93: Xarope De Guaco S/Acucar 100ml 1ct X 50fr - Farma | G93: 30049099 | H93: ATIVO | I93: 50 | J93: 2.92 | L93: 2.86 | M93: 2.92 | N93: =IFERROR(100%-(J93/M93),0) -> 0 | P93: 3.14 | Q93: =IFERROR(100%-(M93/P93),0) -> 0.070063694 | S93: 3.37 | T93: =IFERROR(100%-(M93/S93),0) -> 0.13353116 | V93: 2.9572319 | W93: =IFERROR(100%-(M93/V93),0) -> 0.012590116 | Y93: 3.1588613 | Z93: =IFERROR(100%-(M93/Y93),0) -> 0.075616279 | AB93: 3.3899975 | AC93: =IFERROR(100%-(M93/AB93),0) -> 0.13864244 | AE93: 2.6649746 | AF93: =IFERROR(100%-(M93/AE93),0) -> -0.095695238 | AH93: 0 | AI93: =IFERROR(100%-(M93/AH93),0) -> 0 | AK93: 0 | AL93: =IFERROR(100%-(M93/AK93),0) -> 0 | AN93: 0 | AO93: =IFERROR(100%-(M93/AN93),0) -> 0 | AR93: =IFERROR(100%-(P93/AQ93),0) -> 0 | AT93: 29.57 | AU93: 23.59 | AV93: 31.64 | AW93: 27.26 | AX93: 36.41 | AY93: 29.16 | AZ93: 38.86 | BA93: 29.36 | BB93: 39.12 | BC93: 29.57 | BD93: 39.4 | BE93: 30.43 | BF93: 40.5 | BG93: 25.38 | BH93: 35.09 | BI93: 25.54 | BJ93: 35.31 | BK93: 25.69 | BL93: 35.52 | BM93: Negativa | BN93: Grupo 1
A94: Natulab | B94: Medicamentos | C94: 7898133131837 | D94: 24104 | E94: 15000112 | F94: Xarope De Guaco S/Acucar 150ml 1ct X 50fr - Farma | G94: 30049099 | H94: ATIVO | I94: 50 | J94: 4.93 | L94: 4.83 | M94: 4.93 | N94: =IFERROR(100%-(J94/M94),0) -> 0 | P94: 5.3 | Q94: =IFERROR(100%-(M94/P94),0) -> 0.069811321 | S94: 5.7 | T94: =IFERROR(100%-(M94/S94),0) -> 0.13508772 | V94: 4.9918074 | W94: =IFERROR(100%-(M94/V94),0) -> 0.012381775 | Y94: 5.3321579 | Z94: =IFERROR(100%-(M94/Y94),0) -> 0.075421236 | AB94: 5.7223158 | AC94: =IFERROR(100%-(M94/AB94),0) -> 0.1384607 | AE94: 4.4984772 | AF94: =IFERROR(100%-(M94/AE94),0) -> -0.095926427 | AH94: 4.69 | AI94: =IFERROR(100%-(M94/AH94),0) -> -0.051172708 | AK94: 10.038 | AL94: =IFERROR(100%-(M94/AK94),0) -> 0.50886631 | AN94: 7.56 | AO94: =IFERROR(100%-(M94/AN94),0) -> 0.3478836 | AR94: =IFERROR(100%-(P94/AQ94),0) -> 0 | AT94: 33.46 | AU94: 26.7 | AV94: 35.81 | AW94: 30.85 | AX94: 41.2 | AY94: 32.99 | AZ94: 43.97 | BA94: 33.22 | BB94: 44.27 | BC94: 33.46 | BD94: 44.58 | BE94: 34.43 | BF94: 45.83 | BG94: 28.72 | BH94: 39.7 | BI94: 28.9 | BJ94: 39.95 | BK94: 29.07 | BL94: 40.19 | BM94: Negativa | BN94: Grupo 1
A95: Naturelife | B95: Alimentos | C95: 7899898601481 | D95: 21835 | E95: 15000257 | F95: CALCIOVITAL B12 SUS OR X 250ML | G95: 30045090 | H95: ATIVO | I95: 36 | J95: 5.2 | L95: 5.25 | M95: 5.2 | N95: =IFERROR(100%-(J95/M95),0) -> 0 | P95: 5.59 | Q95: =IFERROR(100%-(M95/P95),0) -> 0.069767442 | S95: 6.01 | T95: =IFERROR(100%-(M95/S95),0) -> 0.13477537 | V95: 5.2654202 | W95: =IFERROR(100%-(M95/V95),0) -> 0.01242449 | Y95: 5.6244261 | Z95: =IFERROR(100%-(M95/Y95),0) -> 0.075461224 | AB95: 6.0359695 | AC95: =IFERROR(100%-(M95/AB95),0) -> 0.13849796 | AE95: 4.9746193 | AF95: =IFERROR(100%-(M95/AE95),0) -> -0.045306122 | AH95: 0 | AI95: =IFERROR(100%-(M95/AH95),0) -> 0 | AK95: 0 | AL95: =IFERROR(100%-(M95/AK95),0) -> 0 | AN95: 0 | AO95: =IFERROR(100%-(M95/AN95),0) -> 0 | AR95: =IFERROR(100%-(P95/AQ95),0) -> 0 | AT95: 25.42 | AU95: 20.42 | AV95: 27.58 | AW95: 23.5 | AX95: 31.64 | AY95: 25.07 | AZ95: 33.7 | BA95: 25.24 | BB95: 33.92 | BC95: 25.42 | BD95: 34.16 | BE95: 26.13 | BF95: 35.09 | BG95: 22.59 | BH95: 31.23 | BI95: 22.72 | BJ95: 31.41 | BK95: 22.86 | BL95: 31.6 | BM95: Neutra | BN95: NÃO SE APLICA - LIBERADOS
A96: Naturelife | B96: Alimentos | C96: 7899898601146 | D96: 208 | E96: 15000253 | F96: Calciovital D3 625mg Com Rev X 60 | G96: 21069030 | H96: ATIVO | I96: 50 | J96: 9.53 | L96: 9.35 | M96: 9.53 | N96: =IFERROR(100%-(J96/M96),0) -> 0 | P96: 10.25 | Q96: =IFERROR(100%-(M96/P96),0) -> 0.070243902 | S96: 11.02 | T96: =IFERROR(100%-(M96/S96),0) -> 0.13520871 | V96: 9.6604341 | W96: =IFERROR(100%-(M96/V96),0) -> 0.013501891 | Y96: 10.3191 | Z96: =IFERROR(100%-(M96/Y96),0) -> 0.076469855 | AB96: 11.074156 | AC96: =IFERROR(100%-(M96/AB96),0) -> 0.13943782 | AE96: 9.1269036 | AF96: =IFERROR(100%-(M96/AE96),0) -> -0.04416574 | AH96: 0 | AI96: =IFERROR(100%-(M96/AH96),0) -> 0 | AK96: 0 | AL96: =IFERROR(100%-(M96/AK96),0) -> 0 | AN96: 0 | AO96: =IFERROR(100%-(M96/AN96),0) -> 0 | AR96: =IFERROR(100%-(P96/AQ96),0) -> 0 | AT96: 38.96 | AU96: 31.31 | AV96: 42.29 | AW96: 36.02 | AX96: 48.5 | AY96: 38.43 | AZ96: 51.66 | BA96: 38.69 | BB96: 52 | BC96: 38.96 | BD96: 52.36 | BE96: 40.05 | BF96: 53.79 | BG96: 34.62 | BH96: 47.86 | BI96: 34.83 | BJ96: 48.15 | BK96: 35.04 | BL96: 48.44 | BM96: Neutra | BN96: NÃO SE APLICA - LIBERADOS
A97: Naturelife | B97: Alimentos | C97: 7899898601061 | D97: 19794 | E97: 15000239 | F97: Calciovital D3 B12 Sol Or X 250ml | G97: 21069030 | H97: ATIVO | I97: 36 | J97: 5.29 | L97: 5.19 | M97: 5.29 | N97: =IFERROR(100%-(J97/M97),0) -> 0 | P97: 5.69 | Q97: =IFERROR(100%-(M97/P97),0) -> 0.07029877 | S97: 6.12 | T97: =IFERROR(100%-(M97/S97),0) -> 0.13562092 | V97: 5.362132 | W97: =IFERROR(100%-(M97/V97),0) -> 0.013452104 | Y97: 5.7277319 | Z97: =IFERROR(100%-(M97/Y97),0) -> 0.076423246 | AB97: 6.1468342 | AC97: =IFERROR(100%-(M97/AB97),0) -> 0.13939439 | AE97: 5.0659898 | AF97: =IFERROR(100%-(M97/AE97),0) -> -0.044218437 | AH97: 0 | AI97: =IFERROR(100%-(M97/AH97),0) -> 0 | AK97: 0 | AL97: =IFERROR(100%-(M97/AK97),0) -> 0 | AN97: 0 | AO97: =IFERROR(100%-(M97/AN97),0) -> 0 | AR97: =IFERROR(100%-(P97/AQ97),0) -> 0 | AT97: 20.64 | AU97: 16.58 | AV97: 22.39 | AW97: 19.08 | AX97: 25.69 | AY97: 20.36 | AZ97: 27.37 | BA97: 20.5 | BB97: 27.55 | BC97: 20.64 | BD97: 27.74 | BE97: 21.22 | BF97: 28.5 | BG97: 18.34 | BH97: 25.35 | BI97: 18.45 | BJ97: 25.51 | BK97: 18.56 | BL97: 25.66 | BM97: Neutra | BN97: NÃO SE APLICA - LIBERADOS
A98: Naturelife | B98: Alimentos | C98: 7898557141337 | D98: 14033 | E98: 15000236 | F98: Calciovital Kids 250ml 24ct - Farma | G98: 21069030 | H98: ATIVO | I98: 24 | J98: 6.35 | L98: 6.23 | M98: 6.35 | N98: =IFERROR(100%-(J98/M98),0) -> 0 | P98: 6.83 | Q98: =IFERROR(100%-(M98/P98),0) -> 0.070278184 | S98: 7.35 | T98: =IFERROR(100%-(M98/S98),0) -> 0.13605442 | V98: 6.4367075 | W98: =IFERROR(100%-(M98/V98),0) -> 0.013470785 | Y98: 6.8755739 | Z98: =IFERROR(100%-(M98/Y98),0) -> 0.076440735 | AB98: 7.3786647 | AC98: =IFERROR(100%-(M98/AB98),0) -> 0.13941068 | AE98: 6.0812183 | AF98: =IFERROR(100%-(M98/AE98),0) -> -0.044198664 | AH98: 0 | AI98: =IFERROR(100%-(M98/AH98),0) -> 0 | AK98: 0 | AL98: =IFERROR(100%-(M98/AK98),0) -> 0 | AN98: 0 | AO98: =IFERROR(100%-(M98/AN98),0) -> 0 | AR98: =IFERROR(100%-(P98/AQ98),0) -> 0 | AT98: 23.74 | AU98: 19.07 | AV98: 25.76 | AW98: 21.95 | AX98: 29.55 | AY98: 23.42 | AZ98: 31.48 | BA98: 23.58 | BB98: 31.69 | BC98: 23.74 | BD98: 31.91 | BE98: 24.4 | BF98: 32.77 | BG98: 21.09 | BH98: 29.16 | BI98: 21.22 | BJ98: 29.34 | BK98: 21.35 | BL98: 29.52 | BM98: Neutra | BN98: NÃO SE APLICA - LIBERADOS
A99: Naturelife | B99: Alimentos | C99: 7898557141115 | D99: 14275 | E99: 15000235 | F99: Deviter Solucao Oral Limao 20ml 200ct - Farma | G99: 21069030 | H99: ATIVO | I99: 200 | J99: 6.62 | L99: 6.49 | M99: 6.62 | N99: =IFERROR(100%-(J99/M99),0) -> 0 | P99: 7.11 | Q99: =IFERROR(100%-(M99/P99),0) -> 0.068917018 | S99: 7.65 | T99: =IFERROR(100%-(M99/S99),0) -> 0.13464052 | V99: 6.7553191 | W99: =IFERROR(100%-(M99/V99),0) -> 0.020031496 | Y99: 7.2159091 | Z99: =IFERROR(100%-(M99/Y99),0) -> 0.082582677 | AB99: 7.7439024 | AC99: =IFERROR(100%-(M99/AB99),0) -> 0.14513386 | AE99: 6.85 | AF99: =IFERROR(100%-(M99/AE99),0) -> 0.033576642 | AH99: 0 | AI99: =IFERROR(100%-(M99/AH99),0) -> 0 | AK99: 9.703 | AL99: =IFERROR(100%-(M99/AK99),0) -> 0.31773678 | AN99: 0 | AO99: =IFERROR(100%-(M99/AN99),0) -> 0 | AR99: =IFERROR(100%-(P99/AQ99),0) -> 0 | AT99: 31.53 | AU99: 25.33 | AV99: 34.22 | AW99: 29.15 | AX99: 39.25 | AY99: 31.1 | AZ99: 41.81 | BA99: 31.31 | BB99: 42.08 | BC99: 31.53 | BD99: 42.38 | BE99: 32.41 | BF99: 43.53 | BG99: 28.02 | BH99: 38.74 | BI99: 28.19 | BJ99: 38.97 | BK99: 28.36 | BL99: 39.21 | BM99: Neutra | BN99: NÃO SE APLICA - LIBERADOS
A100: Naturelife | B100: Alimentos | C100: 7899898601221 | D100: 20308 | E100: 15000247 | F100: Lactprev 10000 Cap Dura 500mg X 30 | G100: 21069030 | H100: ATIVO | I100: 24 | J100: 23.64 | L100: 21.19495 | M100: 23.64 | N100: =IFERROR(100%-(J100/M100),0) -> 0 | P100: 25.42 | Q100: =IFERROR(100%-(M100/P100),0) -> 0.070023603 | S100: 27.34 | T100: =IFERROR(100%-(M100/S100),0) -> 0.13533285 | V100: 22.107527 | W100: =IFERROR(100%-(M100/V100),0) -> -0.069319066 | Y100: 23.363636 | Z100: =IFERROR(100%-(M100/Y100),0) -> -0.011828794 | AB100: 25.073171 | AC100: =IFERROR(100%-(M100/AB100),0) -> 0.057159533 | AE100: 20.294416 | AF100: =IFERROR(100%-(M100/AE100),0) -> -0.16485243 | AH100: 0 | AI100: =IFERROR(100%-(M100/AH100),0) -> 0 | AK100: 0 | AL100: =IFERROR(100%-(M100/AK100),0) -> 0 | AN100: 0 | AO100: =IFERROR(100%-(M100/AN100),0) -> 0 | AR100: =IFERROR(100%-(P100/AQ100),0) -> 0 | AT100: 57.24 | AU100: 46 | AV100: 62.14 | AW100: 52.92 | AX100: 71.26 | AY100: 56.47 | AZ100: 75.92 | BA100: 56.85 | BB100: 76.41 | BC100: 57.24 | BD100: 76.93 | BE100: 58.84 | BF100: 79.02 | BG100: 50.86 | BH100: 70.31 | BI100: 51.17 | BJ100: 70.74 | BK100: 51.48 | BL100: 71.17 | BM100: Neutra | BN100: NÃO SE APLICA - LIBERADOS
A101: Naturelife | B101: Alimentos | C101: 7898557141054 | D101: 13802 | E101: 15000232 | F101: Lactulife Ameixa 120ml 50fr - Farma | G101: 21069030 | H101: ATIVO | I101: 50 | J101: 8.47 | L101: 8.31 | M101: 8.47 | N101: =IFERROR(100%-(J101/M101),0) -> 0 | P101: 9.11 | Q101: =IFERROR(100%-(M101/P101),0) -> 0.07025247 | S101: 9.8 | T101: =IFERROR(100%-(M101/S101),0) -> 0.13571429 | V101: 8.5858586 | W101: =IFERROR(100%-(M101/V101),0) -> 0.013494118 | Y101: 9.171258 | Z101: =IFERROR(100%-(M101/Y101),0) -> 0.076462578 | AB101: 9.8423257 | AC101: =IFERROR(100%-(M101/AB101),0) -> 0.13943104 | AE101: 7.7497462 | AF101: =IFERROR(100%-(M101/AE101),0) -> -0.092939019 | AH101: 0 | AI101: =IFERROR(100%-(M101/AH101),0) -> 0 | AK101: 0 | AL101: =IFERROR(100%-(M101/AK101),0) -> 0 | AN101: 0 | AO101: =IFERROR(100%-(M101/AN101),0) -> 0 | AR101: =IFERROR(100%-(P101/AQ101),0) -> 0 | AT101: 37.07 | AU101: 29.79 | AV101: 40.24 | AW101: 34.27 | AX101: 46.14 | AY101: 36.57 | AZ101: 49.16 | BA101: 36.82 | BB101: 49.49 | BC101: 37.07 | BD101: 49.82 | BE101: 38.11 | BF101: 51.18 | BG101: 32.94 | BH101: 45.54 | BI101: 33.14 | BJ101: 45.81 | BK101: 33.34 | BL101: 46.09 | BM101: Neutra | BN101: NÃO SE APLICA - LIBERADOS
A102: Naturelife | B102: Alimentos | C102: 7898557141061 | D102: 13806 | E102: 15000234 | F102: Lactulife Salada De Frutas 120ml 50fr - Farma | G102: 21069030 | H102: ATIVO | I102: 50 | J102: 8.47 | L102: 8.31 | M102: 8.47 | N102: =IFERROR(100%-(J102/M102),0) -> 0 | P102: 9.11 | Q102: =IFERROR(100%-(M102/P102),0) -> 0.07025247 | S102: 9.8 | T102: =IFERROR(100%-(M102/S102),0) -> 0.13571429 | V102: 8.5858586 | W102: =IFERROR(100%-(M102/V102),0) -> 0.013494118 | Y102: 9.171258 | Z102: =IFERROR(100%-(M102/Y102),0) -> 0.076462578 | AB102: 9.8423257 | AC102: =IFERROR(100%-(M102/AB102),0) -> 0.13943104 | AE102: 7.7497462 | AF102: =IFERROR(100%-(M102/AE102),0) -> -0.092939019 | AH102: 0 | AI102: =IFERROR(100%-(M102/AH102),0) -> 0 | AK102: 0 | AL102: =IFERROR(100%-(M102/AK102),0) -> 0 | AN102: 0 | AO102: =IFERROR(100%-(M102/AN102),0) -> 0 | AR102: =IFERROR(100%-(P102/AQ102),0) -> 0 | AT102: 36.04 | AU102: 28.96 | AV102: 39.12 | AW102: 33.32 | AX102: 44.86 | AY102: 35.55 | AZ102: 47.79 | BA102: 35.79 | BB102: 48.1 | BC102: 36.04 | BD102: 48.44 | BE102: 37.05 | BF102: 49.76 | BG102: 32.02 | BH102: 44.27 | BI102: 32.22 | BJ102: 44.54 | BK102: 32.41 | BL102: 44.81 | BM102: Neutra | BN102: NÃO SE APLICA - LIBERADOS
A103: Naturelife | B103: Alimentos | C103: 7898557147643 | D103: 17491 | E103: 15000228 | F103: Matherlly Gest 1000mg 30comx50ct - Farma | G103: 21069030 | H103: ATIVO | I103: 50 | J103: 11.66 | L103: 11.43 | M103: 11.66 | N103: =IFERROR(100%-(J103/M103),0) -> 0 | P103: 12.53 | Q103: =IFERROR(100%-(M103/P103),0) -> 0.06943336 | S103: 13.48 | T103: =IFERROR(100%-(M103/S103),0) -> 0.13501484 | V103: 11.809585 | W103: =IFERROR(100%-(M103/V103),0) -> 0.012666424 | Y103: 12.614784 | Z103: =IFERROR(100%-(M103/Y103),0) -> 0.075687716 | AB103: 13.537817 | AC103: =IFERROR(100%-(M103/AB103),0) -> 0.13870901 | AE103: 11.15736 | AF103: =IFERROR(100%-(M103/AE103),0) -> -0.045050045 | AH103: 11.1 | AI103: =IFERROR(100%-(M103/AH103),0) -> -0.05045045 | AK103: 14.6363 | AL103: =IFERROR(100%-(M103/AK103),0) -> 0.20335057 | AN103: 0 | AO103: =IFERROR(100%-(M103/AN103),0) -> 0 | AR103: =IFERROR(100%-(P103/AQ103),0) -> 0 | AT103: 50.47 | AU103: 40.55 | AV103: 54.78 | AW103: 46.66 | AX103: 62.83 | AY103: 49.79 | AZ103: 66.93 | BA103: 50.13 | BB103: 67.38 | BC103: 50.47 | BD103: 67.83 | BE103: 51.88 | BF103: 69.67 | BG103: 44.84 | BH103: 61.99 | BI103: 45.12 | BJ103: 62.38 | BK103: 45.39 | BL103: 62.75 | BM103: Neutra | BN103: NÃO SE APLICA - LIBERADOS
A104: Naturelife | B104: Alimentos | C104: 7898557147650 | D104: 17492 | E104: 15000229 | F104: Matherlly Lact 750mg Novo 30comx50ct - Farma | G104: 21069030 | H104: ATIVO | I104: 50 | J104: 11.66 | L104: 11.43 | M104: 11.66 | N104: =IFERROR(100%-(J104/M104),0) -> 0 | P104: 12.53 | Q104: =IFERROR(100%-(M104/P104),0) -> 0.06943336 | S104: 13.48 | T104: =IFERROR(100%-(M104/S104),0) -> 0.13501484 | V104: 11.809585 | W104: =IFERROR(100%-(M104/V104),0) -> 0.012666424 | Y104: 12.614784 | Z104: =IFERROR(100%-(M104/Y104),0) -> 0.075687716 | AB104: 13.537817 | AC104: =IFERROR(100%-(M104/AB104),0) -> 0.13870901 | AE104: 11.15736 | AF104: =IFERROR(100%-(M104/AE104),0) -> -0.045050045 | AH104: 0 | AI104: =IFERROR(100%-(M104/AH104),0) -> 0 | AK104: 0 | AL104: =IFERROR(100%-(M104/AK104),0) -> 0 | AN104: 0 | AO104: =IFERROR(100%-(M104/AN104),0) -> 0 | AR104: =IFERROR(100%-(P104/AQ104),0) -> 0 | AT104: 48.11 | AU104: 38.66 | AV104: 52.22 | AW104: 44.48 | AX104: 59.89 | AY104: 47.46 | AZ104: 63.8 | BA104: 47.78 | BB104: 64.22 | BC104: 48.11 | BD104: 64.66 | BE104: 49.45 | BF104: 66.41 | BG104: 42.75 | BH104: 59.1 | BI104: 43.01 | BJ104: 59.46 | BK104: 43.27 | BL104: 59.82 | BM104: Neutra | BN104: NÃO SE APLICA - LIBERADOS
... A106: Naturelife | B106: Alimentos | C106: 7899898601337 | D106: 19 | E106: 15000252 | F106: Nutrifort Sol Or X 240ml | G106: 21069030 | H106: ATIVO | I106: 24 | J106: 5.29 | L106: 5.19 | M106: 5.29 | N106: =IFERROR(100%-(J106/M106),0) -> 0 | P106: 5.69 | Q106: =IFERROR(100%-(M106/P106),0) -> 0.07029877 | S106: 6.12 | T106: =IFERROR(100%-(M106/S106),0) -> 0.13562092 | V106: 5.362132 | W106: =IFERROR(100%-(M106/V106),0) -> 0.013452104 | Y106: 5.7277319 | Z106: =IFERROR(100%-(M106/Y106),0) -> 0.076423246 | AB106: 6.1468342 | AC106: =IFERROR(100%-(M106/AB106),0) -> 0.13939439 | AE106: 5.0659898 | AF106: =IFERROR(100%-(M106/AE106),0) -> -0.044218437 | AH106: 0 | AI106: =IFERROR(100%-(M106/AH106),0) -> 0 | AK106: 0 | AL106: =IFERROR(100%-(M106/AK106),0) -> 0 | AN106: 0 | AO106: =IFERROR(100%-(M106/AN106),0) -> 0 | AR106: =IFERROR(100%-(P106/AQ106),0) -> 0 | AT106: 15.53 | AU106: 12.48 | AV106: 16.86 | AW106: 14.36 | AX106: 19.33 | AY106: 15.32 | AZ106: 20.59 | BA106: 15.42 | BB106: 20.72 | BC106: 15.53 | BD106: 20.87 | BE106: 15.96 | BF106: 21.43 | BG106: 13.8 | BH106: 19.08 | BI106: 13.88 | BJ106: 19.19 | BK106: 13.97 | BL106: 19.31 | BM106: Neutra | BN106: NÃO SE APLICA - LIBERADOS
A107: Naturelife | B107: Alimentos | C107: 7899898601283 | D107: 20504 | E107: 15000261 | F107: NUTRIVIT KIDS SOL OR X 120ML | G107: 21069030 | H107: ATIVO | I107: 50 | J107: 6.35 | M107: 0 | N107: =IFERROR(100%-(J107/M107),0) -> 0 | P107: 0 | Q107: =IFERROR(100%-(M107/P107),0) -> 0 | S107: 0 | T107: =IFERROR(100%-(M107/S107),0) -> 0 | V107: 0 | W107: =IFERROR(100%-(M107/V107),0) -> 0 | Y107: 0 | Z107: =IFERROR(100%-(M107/Y107),0) -> 0 | AB107: 0 | AC107: =IFERROR(100%-(M107/AB107),0) -> 0 | AE107: 6.0812183 | AF107: =IFERROR(100%-(M107/AE107),0) -> 1 | AH107: 0 | AI107: =IFERROR(100%-(M107/AH107),0) -> 0 | AK107: 0 | AL107: =IFERROR(100%-(M107/AK107),0) -> 0 | AN107: 0 | AO107: =IFERROR(100%-(M107/AN107),0) -> 0 | AR107: =IFERROR(100%-(P107/AQ107),0) -> 0 | AT107: 27.85 | AU107: 22.38 | AV107: 30.23 | AW107: 25.75 | AX107: 34.67 | AY107: 27.47 | AZ107: 36.93 | BA107: 27.66 | BB107: 37.18 | BC107: 27.85 | BD107: 37.43 | BE107: 28.63 | BF107: 38.45 | BG107: 24.75 | BH107: 34.22 | BI107: 24.9 | BJ107: 34.42 | BK107: 25.05 | BL107: 34.63 | BM107: Neutra | BN107: NÃO SE APLICA - LIBERADOS
A108: Naturelife | B108: Alimentos | C108: 7899898601450 | D108: 20746 | E108: 15000262 | F108: NUTRIVIT JUNIOR SOL OR X 240ML | G108: 21069030 | H108: ATIVO | I108: 24 | J108: 5.29 | M108: 0 | N108: =IFERROR(100%-(J108/M108),0) -> 0 | P108: 0 | Q108: =IFERROR(100%-(M108/P108),0) -> 0 | S108: 0 | T108: =IFERROR(100%-(M108/S108),0) -> 0 | V108: 0 | W108: =IFERROR(100%-(M108/V108),0) -> 0 | Y108: 0 | Z108: =IFERROR(100%-(M108/Y108),0) -> 0 | AB108: 0 | AC108: =IFERROR(100%-(M108/AB108),0) -> 0 | AE108: 5.0659898 | AF108: =IFERROR(100%-(M108/AE108),0) -> 1 | AH108: 0 | AI108: =IFERROR(100%-(M108/AH108),0) -> 0 | AK108: 0 | AL108: =IFERROR(100%-(M108/AK108),0) -> 0 | AN108: 0 | AO108: =IFERROR(100%-(M108/AN108),0) -> 0 | AR108: =IFERROR(100%-(P108/AQ108),0) -> 0 | AT108: 21.66 | AU108: 17.4 | AV108: 23.5 | AW108: 20.02 | AX108: 26.95 | AY108: 21.37 | AZ108: 28.73 | BA108: 21.51 | BB108: 28.91 | BC108: 21.66 | BD108: 29.11 | BE108: 22.27 | BF108: 29.91 | BG108: 19.25 | BH108: 26.61 | BI108: 19.36 | BJ108: 26.76 | BK108: 19.48 | BL108: 26.93 | BM108: Neutra | BN108: NÃO SE APLICA - LIBERADOS
A109: Naturelife | B109: Alimentos | C109: 7899898600996 | D109: 19584 | E109: 15000231 | F109: Osteofix D3 K2 1700mg 3bl X 10com X 24ct - Farma | G109: 21069030 | H109: ATIVO | I109: 24 | J109: 28.43 | L109: 27.91871 | M109: 28.43 | N109: =IFERROR(100%-(J109/M109),0) -> 0 | P109: 30.57 | Q109: =IFERROR(100%-(M109/P109),0) -> 0.070003271 | S109: 32.88 | T109: =IFERROR(100%-(M109/S109),0) -> 0.13534063 | V109: 29.11828 | W109: =IFERROR(100%-(M109/V109),0) -> 0.023637371 | Y109: 30.772727 | Z109: =IFERROR(100%-(M109/Y109),0) -> 0.076129985 | AB109: 33.02439 | AC109: =IFERROR(100%-(M109/AB109),0) -> 0.13912112 | AE109: 0 | AF109: =IFERROR(100%-(M109/AE109),0) -> 0 | AH109: 0 | AI109: =IFERROR(100%-(M109/AH109),0) -> 0 | AK109: 0 | AL109: =IFERROR(100%-(M109/AK109),0) -> 0 | AN109: 0 | AO109: =IFERROR(100%-(M109/AN109),0) -> 0 | AR109: =IFERROR(100%-(P109/AQ109),0) -> 0 | AT109: 133.45 | AU109: 107.24 | AV109: 144.87 | AW109: 123.39 | AX109: 166.15 | AY109: 131.66 | AZ109: 177 | BA109: 132.55 | BB109: 178.17 | BC109: 133.45 | BD109: 179.35 | BE109: 137.18 | BF109: 184.23 | BG109: 118.58 | BH109: 163.93 | BI109: 119.29 | BJ109: 164.91 | BK109: 120.02 | BL109: 165.92 | BM109: Neutra | BN109: NÃO SE APLICA - LIBERADOS
A110: Naturelife | B110: Alimentos | C110: 7899898600958 | D110: 19969 | E110: 15000241 | F110: Vitaz Az 630mg 60comx50ct - Farma | G110: 21069030 | H110: ATIVO | I110: 50 | J110: 9.44 | L110: 8.99 | M110: 9.44 | N110: =IFERROR(100%-(J110/M110),0) -> 0 | P110: 10.15 | Q110: =IFERROR(100%-(M110/P110),0) -> 0.069950739 | S110: 10.91 | T110: =IFERROR(100%-(M110/S110),0) -> 0.13473877 | V110: 9.3645833 | W110: =IFERROR(100%-(M110/V110),0) -> -0.0080533927 | Y110: 10.215909 | Z110: =IFERROR(100%-(M110/Y110),0) -> 0.075951057 | AB110: 10.963415 | AC110: =IFERROR(100%-(M110/AB110),0) -> 0.13895439 | AE110: 9.0808081 | AF110: =IFERROR(100%-(M110/AE110),0) -> -0.039555061 | AH110: 0 | AI110: =IFERROR(100%-(M110/AH110),0) -> 0 | AK110: 0 | AL110: =IFERROR(100%-(M110/AK110),0) -> 0 | AN110: 0 | AO110: =IFERROR(100%-(M110/AN110),0) -> 0 | AR110: =IFERROR(100%-(P110/AQ110),0) -> 0 | AT110: 35.53 | AU110: 28.55 | AV110: 38.57 | AW110: 32.85 | AX110: 44.23 | AY110: 35.05 | AZ110: 47.12 | BA110: 35.29 | BB110: 47.43 | BC110: 35.53 | BD110: 47.75 | BE110: 36.52 | BF110: 49.05 | BG110: 31.57 | BH110: 43.64 | BI110: 31.76 | BJ110: 43.91 | BK110: 31.96 | BL110: 44.18 | BM110: Neutra | BN110: NÃO SE APLICA - LIBERADOS
A111: Naturelife | B111: Alimentos | C111: 7899898601160 | D111: 19972 | E111: 15000244 | F111: Vitaz Cabelo Pele E Unhas 500mg 60capx50ct - Farma | G111: 21069030 | H111: ATIVO | I111: 50 | J111: 9.44 | L111: 8.99 | M111: 9.44 | N111: =IFERROR(100%-(J111/M111),0) -> 0 | P111: 10.15 | Q111: =IFERROR(100%-(M111/P111),0) -> 0.069950739 | S111: 10.91 | T111: =IFERROR(100%-(M111/S111),0) -> 0.13473877 | V111: 9.3645833 | W111: =IFERROR(100%-(M111/V111),0) -> -0.0080533927 | Y111: 10.215909 | Z111: =IFERROR(100%-(M111/Y111),0) -> 0.075951057 | AB111: 10.963415 | AC111: =IFERROR(100%-(M111/AB111),0) -> 0.13895439 | AE111: 9.0808081 | AF111: =IFERROR(100%-(M111/AE111),0) -> -0.039555061 | AH111: 0 | AI111: =IFERROR(100%-(M111/AH111),0) -> 0 | AK111: 0 | AL111: =IFERROR(100%-(M111/AK111),0) -> 0 | AN111: 0 | AO111: =IFERROR(100%-(M111/AN111),0) -> 0 | AR111: =IFERROR(100%-(P111/AQ111),0) -> 0 | AT111: 35.53 | AU111: 28.55 | AV111: 38.57 | AW111: 32.85 | AX111: 44.23 | AY111: 35.05 | AZ111: 47.12 | BA111: 35.29 | BB111: 47.43 | BC111: 35.53 | BD111: 47.75 | BE111: 36.52 | BF111: 49.05 | BG111: 31.57 | BH111: 43.64 | BI111: 31.76 | BJ111: 43.91 | BK111: 31.96 | BL111: 44.18 | BM111: Neutra | BN111: NÃO SE APLICA - LIBERADOS
A112: Naturelife | B112: Alimentos | C112: 7899898600972 | D112: 19970 | E112: 15000242 | F112: Vitaz Mulher 630mg 60comx50ct - Farma | G112: 21069030 | H112: ATIVO | I112: 50 | J112: 9.44 | L112: 8.99 | M112: 9.44 | N112: =IFERROR(100%-(J112/M112),0) -> 0 | P112: 10.15 | Q112: =IFERROR(100%-(M112/P112),0) -> 0.069950739 | S112: 10.91 | T112: =IFERROR(100%-(M112/S112),0) -> 0.13473877 | V112: 9.3645833 | W112: =IFERROR(100%-(M112/V112),0) -> -0.0080533927 | Y112: 10.215909 | Z112: =IFERROR(100%-(M112/Y112),0) -> 0.075951057 | AB112: 10.963415 | AC112: =IFERROR(100%-(M112/AB112),0) -> 0.13895439 | AE112: 9.0808081 | AF112: =IFERROR(100%-(M112/AE112),0) -> -0.039555061 | AH112: 0 | AI112: =IFERROR(100%-(M112/AH112),0) -> 0 | AK112: 0 | AL112: =IFERROR(100%-(M112/AK112),0) -> 0 | AN112: 0 | AO112: =IFERROR(100%-(M112/AN112),0) -> 0 | AR112: =IFERROR(100%-(P112/AQ112),0) -> 0 | AT112: 35.53 | AU112: 28.55 | AV112: 38.57 | AW112: 32.85 | AX112: 44.23 | AY112: 35.05 | AZ112: 47.12 | BA112: 35.29 | BB112: 47.43 | BC112: 35.53 | BD112: 47.75 | BE112: 36.52 | BF112: 49.05 | BG112: 31.57 | BH112: 43.64 | BI112: 31.76 | BJ112: 43.91 | BK112: 31.96 | BL112: 44.18 | BM112: Neutra | BN112: NÃO SE APLICA - LIBERADOS
A113: Naturelife | B113: Alimentos | C113: 7899898601207 | D113: 19974 | E113: 15000246 | F113: Vitaz Oleo De Peixe Ômega 3 Cap Mole X 120 | G113: 21069030 | H113: ATIVO | I113: 50 | J113: 15.73 | L113: 14.1 | M113: 15.73 | N113: =IFERROR(100%-(J113/M113),0) -> 0 | P113: 16.92 | Q113: =IFERROR(100%-(M113/P113),0) -> 0.070330969 | S113: 18.19 | T113: =IFERROR(100%-(M113/S113),0) -> 0.13523914 | V113: 14.25 | W113: =IFERROR(100%-(M113/V113),0) -> -0.10385965 | Y113: 15.545455 | Z113: =IFERROR(100%-(M113/Y113),0) -> -0.011871345 | AB113: 16.682927 | AC113: =IFERROR(100%-(M113/AB113),0) -> 0.057119883 | AE113: 13.68 | AF113: =IFERROR(100%-(M113/AE113),0) -> -0.1498538 | AH113: 0 | AI113: =IFERROR(100%-(M113/AH113),0) -> 0 | AK113: 0 | AL113: =IFERROR(100%-(M113/AK113),0) -> 0 | AN113: 0 | AO113: =IFERROR(100%-(M113/AN113),0) -> 0 | AR113: =IFERROR(100%-(P113/AQ113),0) -> 0 | AT113: 83.67 | AU113: 67.24 | AV113: 90.83 | AW113: 77.36 | AX113: 104.17 | AY113: 82.54 | AZ113: 110.96 | BA113: 83.1 | BB113: 111.7 | BC113: 83.67 | BD113: 112.45 | BE113: 86.01 | BF113: 115.51 | BG113: 74.34 | BH113: 102.77 | BI113: 74.79 | BJ113: 103.39 | BK113: 75.25 | BL113: 104.03 | BM113: Neutra | BN113: NÃO SE APLICA - LIBERADOS
A114: Naturelife | B114: Alimentos | C114: 7899898600989 | D114: 19971 | E114: 15000243 | F114: Vitaz Senior 630mg 60comx50ct - Farma | G114: 21069030 | H114: ATIVO | I114: 50 | J114: 9.44 | L114: 8.99 | M114: 9.44 | N114: =IFERROR(100%-(J114/M114),0) -> 0 | P114: 10.15 | Q114: =IFERROR(100%-(M114/P114),0) -> 0.069950739 | S114: 10.91 | T114: =IFERROR(100%-(M114/S114),0) -> 0.13473877 | V114: 9.3645833 | W114: =IFERROR(100%-(M114/V114),0) -> -0.0080533927 | Y114: 10.215909 | Z114: =IFERROR(100%-(M114/Y114),0) -> 0.075951057 | AB114: 10.963415 | AC114: =IFERROR(100%-(M114/AB114),0) -> 0.13895439 | AE114: 9.0808081 | AF114: =IFERROR(100%-(M114/AE114),0) -> -0.039555061 | AH114: 0 | AI114: =IFERROR(100%-(M114/AH114),0) -> 0 | AK114: 0 | AL114: =IFERROR(100%-(M114/AK114),0) -> 0 | AN114: 0 | AO114: =IFERROR(100%-(M114/AN114),0) -> 0 | AR114: =IFERROR(100%-(P114/AQ114),0) -> 0 | AT114: 35.53 | AU114: 28.55 | AV114: 38.57 | AW114: 32.85 | AX114: 44.23 | AY114: 35.05 | AZ114: 47.12 | BA114: 35.29 | BB114: 47.43 | BC114: 35.53 | BD114: 47.75 | BE114: 36.52 | BF114: 49.05 | BG114: 31.57 | BH114: 43.64 | BI114: 31.76 | BJ114: 43.91 | BK114: 31.96 | BL114: 44.18 | BM114: Neutra | BN114: NÃO SE APLICA - LIBERADOS
A115: Naturelife | B115: Alimentos | C115: 7899898601535 | D115: 22393 | E115: 15000259 | F115: Viter C Sol Or X 20ml | G115: 21069030 | H115: ATIVO | I115: 100 | J115: 1.6 | L115: 1.45 | M115: 1.6 | N115: =IFERROR(100%-(J115/M115),0) -> 0 | P115: 1.72 | Q115: =IFERROR(100%-(M115/P115),0) -> 0.069767442 | S115: 1.85 | T115: =IFERROR(100%-(M115/S115),0) -> 0.13513514 | V115: 1.4479167 | W115: =IFERROR(100%-(M115/V115),0) -> -0.10503597 | Y115: 1.5795455 | Z115: =IFERROR(100%-(M115/Y115),0) -> -0.01294964 | AB115: 1.7122444 | AC115: =IFERROR(100%-(M115/AB115),0) -> 0.065553957 | AE115: 2.7918782 | AF115: =IFERROR(100%-(M115/AE115),0) -> 0.42690909 | AH115: 0 | AI115: =IFERROR(100%-(M115/AH115),0) -> 0 | AK115: 0 | AL115: =IFERROR(100%-(M115/AK115),0) -> 0 | AN115: 0 | AO115: =IFERROR(100%-(M115/AN115),0) -> 0 | AR115: =IFERROR(100%-(P115/AQ115),0) -> 0 | AT115: 12.2 | AU115: 9.8 | AV115: 13.23 | AW115: 11.28 | AX115: 15.19 | AY115: 12.03 | AZ115: 16.17 | BA115: 12.11 | BB115: 16.27 | BC115: 12.2 | BD115: 16.4 | BE115: 12.54 | BF115: 16.84 | BG115: 10.84 | BH115: 14.99 | BI115: 10.91 | BJ115: 15.08 | BK115: 10.97 | BL115: 15.17 | BM115: Neutra | BN115: NÃO SE APLICA - LIBERADOS
A116: Natulab | B116: Hospitalar | C116: 7899470804873 | D116: 28994 | E116: 15000029 | F116: Ad-Vitam Gotas 10ml 1 X 200fr - Hosp | G116: 30045040 | H116: ATIVO | I116: 200 | J116: 4.25 | L116: 3.675 | M116: 0 | N116: =IFERROR(100%-(J116/M116),0) -> 0 | P116: 0 | Q116: =IFERROR(100%-(M116/P116),0) -> 0 | S116: 0 | T116: =IFERROR(100%-(M116/S116),0) -> 0 | V116: 0 | W116: =IFERROR(100%-(M116/V116),0) -> 0 | Y116: 0 | Z116: =IFERROR(100%-(M116/Y116),0) -> 0 | AB116: 0 | AC116: =IFERROR(100%-(M116/AB116),0) -> 0 | AE116: 0 | AF116: =IFERROR(100%-(M116/AE116),0) -> 0 | AH116: 0 | AI116: =IFERROR(100%-(M116/AH116),0) -> 0 | AK116: 0 | AL116: =IFERROR(100%-(M116/AK116),0) -> 0 | AN116: 0 | AO116: =IFERROR(100%-(M116/AN116),0) -> 0 | AR116: =IFERROR(100%-(P116/AQ116),0) -> 0 | AT116: 18.0043 | AU116: 2873.53 | AV116: 3854.73 | AW116: 3320.62 | AX116: 4435.63 | AY116: 3550.9 | AZ116: 4733.08 | BA116: 3575.7 | BB116: 4765.04 | BC116: 3600.86 | BD116: 4797.46 | BE116: 3705.11 | BF116: 4931.63 | BG116: 3091.15 | BH116: 4273.33 | BI116: 3109.89 | BJ116: 4299.24 | BK116: 3128.85 | BL116: 4325.45 | BM116: Negativa | BN116: Grupo 2
A117: Natulab | B117: Hospitalar | C117: 7898133136580 | D117: 23667 | E117: 15000045 | F117: Afolic Comprimido 5mg 25bl X 20com X 10ct - Hosp | G117: 30045090 | H117: ATIVO | I117: 10 | J117: 17.5 | L117: 16.2225 | M117: 0 | N117: =IFERROR(100%-(J117/M117),0) -> 0 | P117: 0 | Q117: =IFERROR(100%-(M117/P117),0) -> 0 | S117: 0 | T117: =IFERROR(100%-(M117/S117),0) -> 0 | V117: 0 | W117: =IFERROR(100%-(M117/V117),0) -> 0 | Y117: 0 | Z117: =IFERROR(100%-(M117/Y117),0) -> 0 | AB117: 0 | AC117: =IFERROR(100%-(M117/AB117),0) -> 0 | AE117: 0 | AF117: =IFERROR(100%-(M117/AE117),0) -> 0 | AH117: 0 | AI117: =IFERROR(100%-(M117/AH117),0) -> 0 | AK117: 0 | AL117: =IFERROR(100%-(M117/AK117),0) -> 0 | AN117: 0 | AO117: =IFERROR(100%-(M117/AN117),0) -> 0 | AR117: =IFERROR(100%-(P117/AQ117),0) -> 0 | AT117: 116.72 | AU117: 93.14 | AV117: 124.94 | AW117: 107.63 | AX117: 143.77 | AY117: 115.1 | AZ117: 153.42 | BA117: 115.9 | BB117: 154.45 | BC117: 116.72 | BD117: 155.51 | BE117: 120.1 | BF117: 159.86 | BG117: 100.2 | BH117: 138.52 | BI117: 100.81 | BJ117: 139.36 | BK117: 101.42 | BL117: 140.21 | BM117: Negativa | BN117: Grupo 3
A118: Natulab | B118: Hospitalar | C118: 7898133138423 | D118: 35601 | E118: 15000036 | F118: Afolic Infantil 0.2mg C/ Cgt 30ml 1 X 100fr - Hosp | G118: 30045090 | H118: ATIVO | I118: 100 | J118: 4.33 | L118: 4.326 | M118: 0 | N118: =IFERROR(100%-(J118/M118),0) -> 0 | P118: 0 | Q118: =IFERROR(100%-(M118/P118),0) -> 0 | S118: 0 | T118: =IFERROR(100%-(M118/S118),0) -> 0 | V118: 0 | W118: =IFERROR(100%-(M118/V118),0) -> 0 | Y118: 0 | Z118: =IFERROR(100%-(M118/Y118),0) -> 0 | AB118: 0 | AC118: =IFERROR(100%-(M118/AB118),0) -> 0 | AE118: 0 | AF118: =IFERROR(100%-(M118/AE118),0) -> 0 | AH118: 0 | AI118: =IFERROR(100%-(M118/AH118),0) -> 0 | AK118: 0 | AL118: =IFERROR(100%-(M118/AK118),0) -> 0 | AN118: 0 | AO118: =IFERROR(100%-(M118/AN118),0) -> 0 | AR118: =IFERROR(100%-(P118/AQ118),0) -> 0 | AT118: 10.9873 | AU118: 876.8 | AV118: 1176.19 | AW118: 1013.22 | AX118: 1353.44 | AY118: 1083.48 | AZ118: 1444.19 | BA118: 1091.05 | BB118: 1453.95 | BC118: 1098.73 | BD118: 1463.85 | BE118: 1130.54 | BF118: 1504.79 | BG118: 943.2 | BH118: 1303.92 | BI118: 948.92 | BJ118: 1311.83 | BK118: 954.71 | BL118: 1319.83 | BM118: Negativa | BN118: Grupo 2
A119: Natulab | B119: Hospitalar | C119: 7899470801476 | D119: 23720 | E119: 15000047 | F119: Alcachofra Natulab 300mg 50bl X 15cap X 10ct - Hosp | G119: 30044990 | H119: ATIVO | I119: 10 | J119: 146.16 | M119: 0 | N119: =IFERROR(100%-(J119/M119),0) -> 0 | P119: 0 | Q119: =IFERROR(100%-(M119/P119),0) -> 0 | S119: 0 | T119: =IFERROR(100%-(M119/S119),0) -> 0 | V119: 0 | W119: =IFERROR(100%-(M119/V119),0) -> 0 | Y119: 0 | Z119: =IFERROR(100%-(M119/Y119),0) -> 0 | AB119: 0 | AC119: =IFERROR(100%-(M119/AB119),0) -> 0 | AE119: 0 | AF119: =IFERROR(100%-(M119/AE119),0) -> 0 | AH119: 0 | AI119: =IFERROR(100%-(M119/AH119),0) -> 0 | AK119: 0 | AL119: =IFERROR(100%-(M119/AK119),0) -> 0 | AN119: 0 | AO119: =IFERROR(100%-(M119/AN119),0) -> 0 | AR119: =IFERROR(100%-(P119/AQ119),0) -> 0 | AT119: 704.68 | AU119: 562.34 | AV119: 754.35 | AW119: 649.83 | AX119: 868.03 | AY119: 694.9 | AZ119: 926.24 | BA119: 699.75 | BB119: 932.5 | BC119: 704.68 | BD119: 938.85 | BE119: 725.08 | BF119: 965.11 | BG119: 604.93 | BH119: 836.28 | BI119: 608.6 | BJ119: 841.35 | BK119: 612.31 | BL119: 846.48 | BM119: Negativa | BN119: Grupo 2
A120: Natulab | B120: Hospitalar | C120: 7899470807034 | D120: 35630 | E120: 15000037 | F120: Alumimax 100ml Fn 1 X 50fr - Hosp | G120: 30049099 | H120: ATIVO | I120: 50 | J120: 1.65 | L120: 1.6275 | M120: 0 | N120: =IFERROR(100%-(J120/M120),0) -> 0 | P120: 0 | Q120: =IFERROR(100%-(M120/P120),0) -> 0 | S120: 0 | T120: =IFERROR(100%-(M120/S120),0) -> 0 | V120: 0 | W120: =IFERROR(100%-(M120/V120),0) -> 0 | Y120: 0 | Z120: =IFERROR(100%-(M120/Y120),0) -> 0 | AB120: 0 | AC120: =IFERROR(100%-(M120/AB120),0) -> 0 | AE120: 0 | AF120: =IFERROR(100%-(M120/AE120),0) -> 0 | AH120: 0 | AI120: =IFERROR(100%-(M120/AH120),0) -> 0 | AK120: 0 | AL120: =IFERROR(100%-(M120/AK120),0) -> 0 | AN120: 0 | AO120: =IFERROR(100%-(M120/AN120),0) -> 0 | AR120: =IFERROR(100%-(P120/AQ120),0) -> 0 | AT120: 8.69 | AU120: 6.93 | AV120: 9.29 | AW120: 8.01 | AX120: 10.7 | AY120: 8.56 | AZ120: 11.41 | BA120: 8.62 | BB120: 11.48 | BC120: 8.69 | BD120: 11.58 | BE120: 8.94 | BF120: 11.9 | BG120: 7.46 | BH120: 10.31 | BI120: 7.51 | BJ120: 10.38 | BK120: 7.55 | BL120: 10.44 | BM120: Negativa | BN120: Grupo 1
A121: Natulab | B121: Hospitalar | C121: 7899470807041 | D121: 35636 | E121: 15000038 | F121: Alumimax 150ml Fn 1 X 50fr - Hosp | G121: 30049099 | H121: ATIVO | I121: 50 | J121: 1.96 | M121: 0 | N121: =IFERROR(100%-(J121/M121),0) -> 0 | P121: 0 | Q121: =IFERROR(100%-(M121/P121),0) -> 0 | S121: 0 | T121: =IFERROR(100%-(M121/S121),0) -> 0 | V121: 0 | W121: =IFERROR(100%-(M121/V121),0) -> 0 | Y121: 0 | Z121: =IFERROR(100%-(M121/Y121),0) -> 0 | AB121: 0 | AC121: =IFERROR(100%-(M121/AB121),0) -> 0 | AE121: 0 | AF121: =IFERROR(100%-(M121/AE121),0) -> 0 | AH121: 0 | AI121: =IFERROR(100%-(M121/AH121),0) -> 0 | AK121: 0 | AL121: =IFERROR(100%-(M121/AK121),0) -> 0 | AN121: 0 | AO121: =IFERROR(100%-(M121/AN121),0) -> 0 | AR121: =IFERROR(100%-(P121/AQ121),0) -> 0 | AT121: 10.43 | AU121: 8.32 | AV121: 11.16 | AW121: 9.61 | AX121: 12.83 | AY121: 10.28 | AZ121: 13.7 | BA121: 10.35 | BB121: 13.79 | BC121: 10.43 | BD121: 13.9 | BE121: 10.73 | BF121: 14.28 | BG121: 8.95 | BH121: 12.37 | BI121: 9.01 | BJ121: 12.46 | BK121: 9.06 | BL121: 12.53 | BM121: Negativa | BN121: Grupo 1
A122: Natulab | B122: Hospitalar | C122: 7899470802763 | D122: 23671 | E122: 15000046 | F122: Arpynflan 450mg 50bl X 15cap X 10ct - Hosp | G122: 30049099 | H122: ATIVO | I122: 10 | J122: 373.38 | M122: 0 | N122: =IFERROR(100%-(J122/M122),0) -> 0 | P122: 0 | Q122: =IFERROR(100%-(M122/P122),0) -> 0 | S122: 0 | T122: =IFERROR(100%-(M122/S122),0) -> 0 | V122: 0 | W122: =IFERROR(100%-(M122/V122),0) -> 0 | Y122: 0 | Z122: =IFERROR(100%-(M122/Y122),0) -> 0 | AB122: 0 | AC122: =IFERROR(100%-(M122/AB122),0) -> 0 | AE122: 0 | AF122: =IFERROR(100%-(M122/AE122),0) -> 0 | AH122: 0 | AI122: =IFERROR(100%-(M122/AH122),0) -> 0 | AK122: 0 | AL122: =IFERROR(100%-(M122/AK122),0) -> 0 | AN122: 0 | AO122: =IFERROR(100%-(M122/AN122),0) -> 0 | AR122: =IFERROR(100%-(P122/AQ122),0) -> 0 | AT122: 1869.64 | AU122: 1491.99 | AV122: 2001.45 | AW122: 1724.13 | AX122: 2303.06 | AY122: 1843.7 | AZ122: 2457.51 | BA122: 1856.58 | BB122: 2474.11 | BC122: 1869.64 | BD122: 2490.94 | BE122: 1923.77 | BF122: 2560.6 | BG122: 1604.99 | BH122: 2218.81 | BI122: 1614.72 | BJ122: 2232.26 | BK122: 1624.56 | BL122: 2245.86 | BM122: Negativa | BN122: Grupo 2
A123: Natulab | B123: Hospitalar | C123: 7898133138577 | D123: 23777 | E123: 15000048 | F123: Beviter 300mg 50bl X 10com X 10ct - Hosp | G123: 30045090 | H123: ATIVO | I123: 10 | J123: 114.18 | M123: 0 | N123: =IFERROR(100%-(J123/M123),0) -> 0 | P123: 0 | Q123: =IFERROR(100%-(M123/P123),0) -> 0 | S123: 0 | T123: =IFERROR(100%-(M123/S123),0) -> 0 | V123: 0 | W123: =IFERROR(100%-(M123/V123),0) -> 0 | Y123: 0 | Z123: =IFERROR(100%-(M123/Y123),0) -> 0 | AB123: 0 | AC123: =IFERROR(100%-(M123/AB123),0) -> 0 | AE123: 0 | AF123: =IFERROR(100%-(M123/AE123),0) -> 0 | AH123: 0 | AI123: =IFERROR(100%-(M123/AH123),0) -> 0 | AK123: 0 | AL123: =IFERROR(100%-(M123/AK123),0) -> 0 | AN123: 0 | AO123: =IFERROR(100%-(M123/AN123),0) -> 0 | AR123: =IFERROR(100%-(P123/AQ123),0) -> 0 | AT123: 162.53 | AU123: 129.7 | AV123: 173.98 | AW123: 149.88 | AX123: 200.2 | AY123: 160.27 | AZ123: 213.62 | BA123: 161.39 | BB123: 215.07 | BC123: 162.53 | BD123: 216.54 | BE123: 167.24 | BF123: 222.6 | BG123: 139.52 | BH123: 192.88 | BI123: 140.37 | BJ123: 194.05 | BK123: 141.23 | BL123: 195.24 | BM123: Negativa | BN123: Grupo 3
A124: Natulab | B124: Hospitalar | C124: 7899470805993 | D124: 30024 | E124: 15000030 | F124: Bronqtrat 100ml 1 X 50fr - Hosp Novo | G124: 30049039 | H124: ATIVO | I124: 50 | J124: 1.26 | M124: 0 | N124: =IFERROR(100%-(J124/M124),0) -> 0 | P124: 0 | Q124: =IFERROR(100%-(M124/P124),0) -> 0 | S124: 0 | T124: =IFERROR(100%-(M124/S124),0) -> 0 | V124: 0 | W124: =IFERROR(100%-(M124/V124),0) -> 0 | Y124: 0 | Z124: =IFERROR(100%-(M124/Y124),0) -> 0 | AB124: 0 | AC124: =IFERROR(100%-(M124/AB124),0) -> 0 | AE124: 0 | AF124: =IFERROR(100%-(M124/AE124),0) -> 0 | AH124: 0 | AI124: =IFERROR(100%-(M124/AH124),0) -> 0 | AK124: 0 | AL124: =IFERROR(100%-(M124/AK124),0) -> 0 | AN124: 0 | AO124: =IFERROR(100%-(M124/AN124),0) -> 0 | AR124: =IFERROR(100%-(P124/AQ124),0) -> 0 | AT124: 10.1864 | AU124: 406.44 | AV124: 545.22 | AW124: 469.68 | AX124: 627.39 | AY124: 502.25 | AZ124: 669.46 | BA124: 505.76 | BB124: 673.98 | BC124: 509.32 | BD124: 678.57 | BE124: 524.07 | BF124: 697.56 | BG124: 437.23 | BH124: 604.45 | BI124: 439.88 | BJ124: 608.11 | BK124: 442.56 | BL124: 611.81 | BM124: Negativa | BN124: Grupo 2
A125: Natulab | B125: Hospitalar | C125: 7899470806006 | D125: 30025 | E125: 15000031 | F125: Bronqtrat 120ml 1 X 50fr - Hosp Novo | G125: 30049039 | H125: ATIVO | I125: 50 | J125: 1.33 | M125: 0 | N125: =IFERROR(100%-(J125/M125),0) -> 0 | P125: 0 | Q125: =IFERROR(100%-(M125/P125),0) -> 0 | S125: 0 | T125: =IFERROR(100%-(M125/S125),0) -> 0 | V125: 0 | W125: =IFERROR(100%-(M125/V125),0) -> 0 | Y125: 0 | Z125: =IFERROR(100%-(M125/Y125),0) -> 0 | AB125: 0 | AC125: =IFERROR(100%-(M125/AB125),0) -> 0 | AE125: 0 | AF125: =IFERROR(100%-(M125/AE125),0) -> 0 | AH125: 0 | AI125: =IFERROR(100%-(M125/AH125),0) -> 0 | AK125: 0 | AL125: =IFERROR(100%-(M125/AK125),0) -> 0 | AN125: 0 | AO125: =IFERROR(100%-(M125/AN125),0) -> 0 | AR125: =IFERROR(100%-(P125/AQ125),0) -> 0 | AT125: 14.5384 | AU125: 580.09 | AV125: 778.17 | AW125: 670.34 | AX125: 895.42 | AY125: 716.83 | AZ125: 955.48 | BA125: 721.84 | BB125: 961.93 | BC125: 726.92 | BD125: 968.48 | BE125: 747.97 | BF125: 995.57 | BG125: 624.02 | BH125: 862.67 | BI125: 627.81 | BJ125: 867.91 | BK125: 631.63 | BL125: 873.19 | BM125: Negativa | BN125: Grupo 2
A126: Natulab | B126: Hospitalar | C126: 7899470806600 | D126: 34432 | E126: 15000034 | F126: Bronqtrat Infantil C/ Cp Med 100ml 1 X 50fr - Hosp | G126: 30049039 | H126: ATIVO | I126: 50 | J126: 1.9 | L126: 1.6485 | M126: 0 | N126: =IFERROR(100%-(J126/M126),0) -> 0 | P126: 0 | Q126: =IFERROR(100%-(M126/P126),0) -> 0 | S126: 0 | T126: =IFERROR(100%-(M126/S126),0) -> 0 | V126: 0 | W126: =IFERROR(100%-(M126/V126),0) -> 0 | Y126: 0 | Z126: =IFERROR(100%-(M126/Y126),0) -> 0 | AB126: 0 | AC126: =IFERROR(100%-(M126/AB126),0) -> 0 | AE126: 0 | AF126: =IFERROR(100%-(M126/AE126),0) -> 0 | AH126: 0 | AI126: =IFERROR(100%-(M126/AH126),0) -> 0 | AK126: 0 | AL126: =IFERROR(100%-(M126/AK126),0) -> 0 | AN126: 0 | AO126: =IFERROR(100%-(M126/AN126),0) -> 0 | AR126: =IFERROR(100%-(P126/AQ126),0) -> 0 | AT126: 6.6834 | AU126: 266.67 | AV126: 357.72 | AW126: 308.16 | AX126: 411.63 | AY126: 329.53 | AZ126: 439.23 | BA126: 331.83 | BB126: 442.2 | BC126: 334.17 | BD126: 445.22 | BE126: 343.85 | BF126: 457.68 | BG126: 286.87 | BH126: 396.58 | BI126: 288.61 | BJ126: 398.99 | BK126: 290.37 | BL126: 401.42 | BM126: Negativa | BN126: Grupo 2
A127: Natulab | B127: Hospitalar | C127: 7899470802596 | D127: 28481 | E127: 15000027 | F127: Buscoplex Composto Gotas 20ml 200fr - Hosp | G127: 30044990 | H127: ATIVO | I127: 200 | J127: 5.51 | L127: 5.5125 | M127: 0 | N127: =IFERROR(100%-(J127/M127),0) -> 0 | P127: 0 | Q127: =IFERROR(100%-(M127/P127),0) -> 0 | S127: 0 | T127: =IFERROR(100%-(M127/S127),0) -> 0 | V127: 0 | W127: =IFERROR(100%-(M127/V127),0) -> 0 | Y127: 0 | Z127: =IFERROR(100%-(M127/Y127),0) -> 0 | AB127: 0 | AC127: =IFERROR(100%-(M127/AB127),0) -> 0 | AE127: 0 | AF127: =IFERROR(100%-(M127/AE127),0) -> 0 | AH127: 0 | AI127: =IFERROR(100%-(M127/AH127),0) -> 0 | AK127: 0 | AL127: =IFERROR(100%-(M127/AK127),0) -> 0 | AN127: 0 | AO127: =IFERROR(100%-(M127/AN127),0) -> 0 | AR127: =IFERROR(100%-(P127/AQ127),0) -> 0 | AT127: 11.4432 | AU127: 1826.36 | AV127: 2449.99 | AW127: 2110.52 | AX127: 2819.19 | AY127: 2256.89 | AZ127: 3008.26 | BA127: 2272.65 | BB127: 3028.57 | BC127: 2288.64 | BD127: 3049.17 | BE127: 2354.9 | BF127: 3134.45 | BG127: 1964.68 | BH127: 2716.06 | BI127: 1976.59 | BJ127: 2732.52 | BK127: 1988.64 | BL127: 2749.18 | BM127: Negativa | BN127: Grupo 2
A128: Natulab | B128: Hospitalar | C128: 7899470805788 | D128: 33550 | E128: 15000032 | F128: Butalab C/ Cp Med 100ml 1 X 50fr - Hosp | G128: 30039099 | H128: ATIVO | I128: 50 | J128: 0.87 | L128: 0.8715 | M128: 0 | N128: =IFERROR(100%-(J128/M128),0) -> 0 | P128: 0 | Q128: =IFERROR(100%-(M128/P128),0) -> 0 | S128: 0 | T128: =IFERROR(100%-(M128/S128),0) -> 0 | V128: 0 | W128: =IFERROR(100%-(M128/V128),0) -> 0 | Y128: 0 | Z128: =IFERROR(100%-(M128/Y128),0) -> 0 | AB128: 0 | AC128: =IFERROR(100%-(M128/AB128),0) -> 0 | AE128: 0 | AF128: =IFERROR(100%-(M128/AE128),0) -> 0 | AH128: 0 | AI128: =IFERROR(100%-(M128/AH128),0) -> 0 | AK128: 0 | AL128: =IFERROR(100%-(M128/AK128),0) -> 0 | AN128: 0 | AO128: =IFERROR(100%-(M128/AN128),0) -> 0 | AR128: =IFERROR(100%-(P128/AQ128),0) -> 0 | AT128: 4.0424 | AU128: 165.73 | AV128: 229.11 | AW128: 188.33 | AX128: 260.35 | AY128: 199.68 | AZ128: 276.04 | BA128: 200.89 | BB128: 277.71 | BC128: 202.12 | BD128: 279.42 | BE128: 207.17 | BF128: 286.4 | BG128: 199.69 | BH128: 276.06 | BI128: 200.9 | BJ128: 277.73 | BK128: 202.12 | BL128: 279.42 | BM128: Positiva | BN128: Grupo 3
A129: Natulab | B129: Hospitalar | C129: 7899470805795 | D129: 33551 | E129: 15000033 | F129: Butalab C/ Cp Med 120ml 1 X 50fr - Hosp | G129: 30039099 | H129: ATIVO | I129: 50 | J129: 0.9 | M129: 0 | N129: =IFERROR(100%-(J129/M129),0) -> 0 | P129: 0 | Q129: =IFERROR(100%-(M129/P129),0) -> 0 | S129: 0 | T129: =IFERROR(100%-(M129/S129),0) -> 0 | V129: 0 | W129: =IFERROR(100%-(M129/V129),0) -> 0 | Y129: 0 | Z129: =IFERROR(100%-(M129/Y129),0) -> 0 | AB129: 0 | AC129: =IFERROR(100%-(M129/AB129),0) -> 0 | AE129: 0 | AF129: =IFERROR(100%-(M129/AE129),0) -> 0 | AH129: 0 | AI129: =IFERROR(100%-(M129/AH129),0) -> 0 | AK129: 0 | AL129: =IFERROR(100%-(M129/AK129),0) -> 0 | AN129: 0 | AO129: =IFERROR(100%-(M129/AN129),0) -> 0 | AR129: =IFERROR(100%-(P129/AQ129),0) -> 0 | AT129: 4.3194 | AU129: 177.09 | AV129: 244.81 | AW129: 201.24 | AX129: 278.2 | AY129: 213.36 | AZ129: 294.95 | BA129: 214.66 | BB129: 296.75 | BC129: 215.97 | BD129: 298.57 | BE129: 221.37 | BF129: 306.03 | BG129: 213.37 | BH129: 294.97 | BI129: 214.66 | BJ129: 296.76 | BK129: 215.97 | BL129: 298.57 | BM129: Positiva | BN129: Grupo 3
A130: Natulab | B130: Hospitalar | C130: 7898133137679 | D130: 23781 | E130: 15000049 | F130: Comple B Comprimidos 25bl X 20com X 10ct - Hosp | G130: 30045090 | H130: ATIVO | I130: 10 | J130: 18.39 | L130: 18.3855 | M130: 0 | N130: =IFERROR(100%-(J130/M130),0) -> 0 | P130: 0 | Q130: =IFERROR(100%-(M130/P130),0) -> 0 | S130: 0 | T130: =IFERROR(100%-(M130/S130),0) -> 0 | V130: 0 | W130: =IFERROR(100%-(M130/V130),0) -> 0 | Y130: 0 | Z130: =IFERROR(100%-(M130/Y130),0) -> 0 | AB130: 0 | AC130: =IFERROR(100%-(M130/AB130),0) -> 0 | AE130: 0 | AF130: =IFERROR(100%-(M130/AE130),0) -> 0 | AH130: 0 | AI130: =IFERROR(100%-(M130/AH130),0) -> 0 | AK130: 0 | AL130: =IFERROR(100%-(M130/AK130),0) -> 0 | AN130: 0 | AO130: =IFERROR(100%-(M130/AN130),0) -> 0 | AR130: =IFERROR(100%-(P130/AQ130),0) -> 0 | AT130: 99.72 | AU130: 79.57 | AV130: 106.74 | AW130: 91.95 | AX130: 122.82 | AY130: 98.33 | AZ130: 131.06 | BA130: 99.02 | BB130: 131.95 | BC130: 99.72 | BD130: 132.86 | BE130: 102.61 | BF130: 136.58 | BG130: 85.6 | BH130: 118.34 | BI130: 86.12 | BJ130: 119.06 | BK130: 86.65 | BL130: 119.79 | BM130: Negativa | BN130: Grupo 2
...

Sheet Proposta Distr e Redes única
F2: Tabela retail de out/21 - última atualização 2021 | N2: DPN - AUTONOMIA GR | V2: RCA | W2: PRIME | Y2: * OBS: REVISAR EM 2022 TABELAS REDES. CRIAR TABELAS PRO CANA, POIS TEM REDES EM DPN/PRIME, DIFICULTANDO A PRECIFICAÇÃO DAS REDES
N3: 0.15 | O3: 0.14 | P3: 0.13 | Q3: 0.12 | R3: 0.11 | S3: 0.1 | T3: 0.09 | U3: 0.08 | V3: 0.07 | W3: 0.1 | X3: 0
A4: LISTA DE PREÇO: Nº 052021 - Vigência: 01/08/2021
A5: LISTA DE PREÇO FABRICA E PREÇO MÁXIMO CONSUMIDOR | J5: Preço Lista | M5: 0.17 | N5: AUTONOMIA GNR | O5: Autonomia - KAM | Y5: REVISAR EM 2022* | AD5: ICMS 0% | AF5: ICMS 12% | AH5: ICMS 17% | AJ5: ICMS 17,5% | AL5: ICMS 18% | AN5: ICMS 20% | AP5: ICMS 17% (ALC) | AR5: ICMS 17,5% (ALC) | AT5: ICMS 18% (ALC)
A6: Empresa | B6: Canal | C6: EAN | D6: Código CIGAM | E6: Código SAP | F6: Descrição | G6: NCM | H6: Status | I6: UN/CX | J6: PV BASE | L6: Preço Médio | M6: Nova PV Base | N6: 0.15 | O6: 0.14 | P6: 0.13 | Q6: 0.12 | R6: 0.11 | S6: 0.1 | T6: 0.09 | U6: 0.08 | V6: 0.07 | W6: 0.035 | X6: 0 | Y6: PAGUE MENOS | Z6: RD | AA6: DPSP | AC6: PF 18% (SAP) | AD6: PF | AE6: PMC | AF6: PF | AG6: PMC | AH6: PF | AI6: PMC | AJ6: PF | AK6: PMC | AL6: PF | AM6: PMC | AN6: PF | AO6: PMC | AP6: PF | AQ6: PMC | AR6: PF | AS6: PMC | AT6: PF | AU6: PMC | AV6: Lista PIS/COFINS | AW6: Categoria de Grupo CMED
A7: Natulab | B7: Medicamentos | C7: 7899470804828 | D7: 43890 | E7: 15000145 | F7: AD-VITAM SOL GOT X 20ML | G7: 30045040 | H7: ATIVO | I7: 50 | J7: ='LISTA PREÇO 2022-Vigen 01.02.22'!J7 -> 4.23 | L7: 4.15 | M7: =J7/(100%-$M$5) -> 5.0963855 | N7: =$M7*(100%-N$6) -> 4.3319277 | O7: =$M7*(100%-O$6) -> 4.3828916 | P7: =$M7*(100%-P$6) -> 4.4338554 | Q7: =$M7*(100%-Q$6) -> 4.4848193 | R7: =$M7*(100%-R$6) -> 4.5357831 | S7: =$M7*(100%-S$6) -> 4.586747 | T7: =$M7*(100%-T$6) -> 4.6377108 | U7: =$M7*(100%-U$6) -> 4.6886747 | ... X7: =$M7*(100%-X$6) -> 5.0963855 | Y7: 0 | Z7: 0 | AA7: 0 | AC7: 12.14 | AD7: 9.68 | AE7: 12.98 | AF7: 11.19 | AG7: 14.94 | AH7: 11.97 | AI7: 15.95 | AJ7: 12.05 | AK7: 16.05 | AL7: 12.14 | AM7: 16.17 | AN7: 12.49 | AO7: 16.63 | AP7: 10.42 | AQ7: 14.41 | AR7: 10.49 | AS7: 14.5 | AT7: 10.55 | AU7: 14.59 | AV7: Negativa | AW7: Grupo 2
A8: Natulab | B8: Medicamentos | C8: 7898133136535 | D8: 23646 | E8: 15000153 | F8: Afolic Comprimido 5mg 1bl X 20com X 200ct - Farma | G8: 30045090 | H8: ATIVO | I8: 200 | J8: ='LISTA PREÇO 2022-Vigen 01.02.22'!J8 -> 1.47 | L8: 1.54 | M8: =J8/(100%-$M$5) -> 1.7710843 | N8: =$M8*(100%-N$6) -> 1.5054217 | O8: =$M8*(100%-O$6) -> 1.5231325 | P8: =$M8*(100%-P$6) -> 1.5408434 | Q8: =$M8*(100%-Q$6) -> 1.5585542 | R8: =$M8*(100%-R$6) -> 1.5762651 | S8: =$M8*(100%-S$6) -> 1.5939759 | T8: =$M8*(100%-T$6) -> 1.6116867 | U8: =$M8*(100%-U$6) -> 1.6293976 | ... X8: =$M8*(100%-X$6) -> 1.7710843 | Y8: 1.4 | Z8: 4.3575 | AA8: 0 | AC8: 8.83 | AD8: 7.04 | AE8: 9.44 | AF8: 8.14 | AG8: 10.87 | AH8: 8.7 | AI8: 11.59 | AJ8: 8.76 | AK8: 11.67 | AL8: 8.83 | AM8: 11.76 | AN8: 9.09 | AO8: 12.1 | AP8: 7.58 | AQ8: 10.48 | AR8: 7.63 | AS8: 10.55 | AT8: 7.67 | AU8: 10.6 | AV8: Negativa | AW8: Grupo 3
A9: Natulab | B9: Medicamentos | C9: 7898133139741 | D9: 34232 | E9: 15000133 | F9: Aftliv 25ml 1ct X 100fr - Farma | G9: 30042029 | H9: ATIVO | I9: 200 | J9: ='LISTA PREÇO 2022-Vigen 01.02.22'!J9 -> 7.12 | L9: 6.98 | M9: =J9/(100%-$M$5) -> 8.5783133 | N9: =$M9*(100%-N$6) -> 7.2915663 | O9: =$M9*(100%-O$6) -> 7.3773494 | P9: =$M9*(100%-P$6) -> 7.4631325 | Q9: =$M9*(100%-Q$6) -> 7.5489157 | R9: =$M9*(100%-R$6) -> 7.6346988 | S9: =$M9*(100%-S$6) -> 7.7204819 | T9: =$M9*(100%-T$6) -> 7.8062651 | U9: =$M9*(100%-U$6) -> 7.8920482 | ... X9: =$M9*(100%-X$6) -> 8.5783133 | Y9: 6.78 | Z9: 9.9596 | AA9: 0 | AC9: 35.57 | AD9: 28.38 | AE9: 38.07 | AF9: 32.8 | AG9: 43.81 | AH9: 35.07 | AI9: 46.74 | AJ9: 35.32 | AK9: 47.06 | AL9: 35.57 | AM9: 47.39 | AN9: 36.6 | AO9: 48.72 | AP9: 30.54 | AQ9: 42.22 | AR9: 30.72 | AS9: 42.47 | AT9: 30.91 | AU9: 42.73 | AV9: Negativa | AW9: Grupo 1
A10: Natulab | B10: Medicamentos | C10: 7899470801414 | D10: 23719 | E10: 15000155 | F10: Alcachofra Natulab 300mg 2bl X 15cap X 50ct - Farma | G10: 30044990 | H10: ATIVO | I10: 50 | J10: ='LISTA PREÇO 2022-Vigen 01.02.22'!J10 -> 7.85 | L10: 7.69 | M10: =J10/(100%-$M$5) -> 9.4578313 | N10: =$M10*(100%-N$6) -> 8.0391566 | O10: =$M10*(100%-O$6) -> 8.1337349 | P10: =$M10*(100%-P$6) -> 8.2283133 | Q10: =$M10*(100%-Q$6) -> 8.3228916 | R10: =$M10*(100%-R$6) -> 8.4174699 | S10: =$M10*(100%-S$6) -> 8.5120482 | T10: =$M10*(100%-T$6) -> 8.6066265 | U10: =$M10*(100%-U$6) -> 8.7012048 | ... X10: =$M10*(100%-X$6) -> 9.4578313 | Y10: 0 | Z10: 0 | AA10: 0 | AC10: 28.88 | AD10: 23.04 | AE10: 30.9 | AF10: 26.63 | AG10: 35.57 | AH10: 28.47 | AI10: 37.94 | AJ10: 28.67 | AK10: 38.2 | AL10: 28.88 | AM10: 38.48 | AN10: 29.72 | AO10: 39.56 | AP10: 24.79 | AQ10: 34.27 | AR10: 24.94 | AS10: 34.48 | AT10: 25.09 | AU10: 34.69 | AV10: Negativa | AW10: Grupo 2
A11: Natulab | B11: Medicamentos | C11: 7898133134456 | D11: 28582 | E11: 15000120 | F11: Alumimax 100ml Fn 1ct X 50fr - Farma | G11: 30049099 | H11: ATIVO | I11: 50 | J11: ='LISTA PREÇO 2022-Vigen 01.02.22'!J11 -> 3.04 | L11: 2.98 | M11: =J11/(100%-$M$5) -> 3.6626506 | N11: =$M11*(100%-N$6) -> 3.113253 | O11: =$M11*(100%-O$6) -> 3.1498795 | P11: =$M11*(100%-P$6) -> 3.186506 | Q11: =$M11*(100%-Q$6) -> 3.2231325 | R11: =$M11*(100%-R$6) -> 3.259759 | S11: =$M11*(100%-S$6) -> 3.2963855 | T11: =$M11*(100%-T$6) -> 3.333012 | U11: =$M11*(100%-U$6) -> 3.3696386 | ... X11: =$M11*(100%-X$6) -> 3.6626506 | Y11: 0 | Z11: 0 | AA11: 0 | AC11: 16.84 | AD11: 13.43 | AE11: 18.01 | AF11: 15.52 | AG11: 20.73 | AH11: 16.6 | AI11: 22.12 | AJ11: 16.72 | AK11: 22.28 | AL11: 16.84 | AM11: 22.44 | AN11: 17.33 | AO11: 23.07 | AP11: 14.46 | AQ11: 19.99 | AR11: 14.54 | AS11: 20.1 | AT11: 14.63 | AU11: 20.23 | AV11: Negativa | AW11: Grupo 1
A12: Natulab | B12: Medicamentos | C12: 7898133134630 | D12: 28578 | E12: 15000119 | F12: Alumimax 150ml Fn 1ct X 60fr - Farma | G12: 30049099 | H12: ATIVO | I12: 60 | J12: ='LISTA PREÇO 2022-Vigen 01.02.22'!J12 -> 4.02 | L12: 3.94 | M12: =J12/(100%-$M$5) -> 4.8433735 | N12: =$M12*(100%-N$6) -> 4.1168675 | O12: =$M12*(100%-O$6) -> 4.1653012 | P12: =$M12*(100%-P$6) -> 4.2137349 | Q12: =$M12*(100%-Q$6) -> 4.2621687 | R12: =$M12*(100%-R$6) -> 4.3106024 | S12: =$M12*(100%-S$6) -> 4.3590361 | T12: =$M12*(100%-T$6) -> 4.4074699 | U12: =$M12*(100%-U$6) -> 4.4559036 | ... X12: =$M12*(100%-X$6) -> 4.8433735 | Y12: 0 | Z12: 0 | AA12: 0 | AC12: 20.91 | AD12: 16.68 | AE12: 22.37 | AF12: 19.28 | AG12: 25.75 | AH12: 20.62 | AI12: 27.48 | AJ12: 20.76 | AK12: 27.66 | AL12: 20.91 | AM12: 27.86 | AN12: 21.52 | AO12: 28.64 | AP12: 17.95 | AQ12: 24.82 | AR12: 18.06 | AS12: 24.97 | AT12: 18.17 | AU12: 25.12 | AV12: Negativa | AW12: Grupo 1
A13: Natulab | B13: Medicamentos | C13: 7898133136634 | D13: 23792 | E13: 15000068 | F13: Arlivry 100ml Cereja 1ct X 50fr - Farma | G13: 30049099 | H13: ATIVO | I13: 50 | J13: ='LISTA PREÇO 2022-Vigen 01.02.22'!J13 -> 3.61 | L13: 3.54 | M13: =J13/(100%-$M$5) -> 4.3493976 | N13: =$M13*(100%-N$6) -> 3.696988 | O13: =$M13*(100%-O$6) -> 3.7404819 | P13: =$M13*(100%-P$6) -> 3.7839759 | Q13: =$M13*(100%-Q$6) -> 3.8274699 | R13: =$M13*(100%-R$6) -> 3.8709639 | S13: =$M13*(100%-S$6) -> 3.9144578 | T13: =$M13*(100%-T$6) -> 3.9579518 | U13: =$M13*(100%-U$6) -> 4.0014458 | ... X13: =$M13*(100%-X$6) -> 4.3493976 | Y13: 3.3 | Z13: 13.133 | AA13: 12.515 | AC13: 19.93 | AD13: 15.9 | AE13: 21.32 | AF13: 18.37 | AG13: 24.53 | AH13: 19.65 | AI13: 26.19 | AJ13: 19.79 | AK13: 26.37 | AL13: 19.93 | AM13: 26.55 | AN13: 20.51 | AO13: 27.3 | AP13: 17.11 | AQ13: 23.65 | AR13: 17.21 | AS13: 23.79 | AT13: 17.32 | AU13: 23.94 | AV13: Negativa | AW13: Grupo 2
A14: Natulab | B14: Medicamentos | C14: 7898133136757 | D14: 23794 | E14: 15000069 | F14: Arlivry 100ml Mel 1ct X 50fr - Farma | G14: 30049099 | H14: ATIVO | I14: 50 | J14: ='LISTA PREÇO 2022-Vigen 01.02.22'!J14 -> 3.61 | L14: 3.54 | M14: =J14/(100%-$M$5) -> 4.3493976 | N14: =$M14*(100%-N$6) -> 3.696988 | O14: =$M14*(100%-O$6) -> 3.7404819 | P14: =$M14*(100%-P$6) -> 3.7839759 | Q14: =$M14*(100%-Q$6) -> 3.8274699 | R14: =$M14*(100%-R$6) -> 3.8709639 | S14: =$M14*(100%-S$6) -> 3.9144578 | T14: =$M14*(100%-T$6) -> 3.9579518 | U14: =$M14*(100%-U$6) -> 4.0014458 | ... X14: =$M14*(100%-X$6) -> 4.3493976 | Y14: 3.3 | Z14: 13.144 | AA14: 12.515 | AC14: 25.03 | AD14: 19.97 | AE14: 26.78 | AF14: 23.08 | AG14: 30.83 | AH14: 24.68 | AI14: 32.89 | AJ14: 24.85 | AK14: 33.11 | AL14: 25.03 | AM14: 33.35 | AN14: 25.76 | AO14: 34.29 | AP14: 21.49 | AQ14: 29.71 | AR14: 21.62 | AS14: 29.89 | AT14: 21.75 | AU14: 30.07 | AV14: Negativa | AW14: Grupo 2
A15: Natulab | B15: Medicamentos | C15: 7899470802725 | D15: 23670 | E15: 15000154 | F15: Arpynflan 450mg 2bl X 15cap X 100ct - Farma | G15: 30049099 | H15: ATIVO | I15: 100 | J15: ='LISTA PREÇO 2022-Vigen 01.02.22'!J15 -> 21.2 | L15: 20.79 | M15: =J15/(100%-$M$5) -> 25.542169 | N15: =$M15*(100%-N$6) -> 21.710843 | O15: =$M15*(100%-O$6) -> 21.966265 | P15: =$M15*(100%-P$6) -> 22.221687 | Q15: =$M15*(100%-Q$6) -> 22.477108 | R15: =$M15*(100%-R$6) -> 22.73253 | S15: =$M15*(100%-S$6) -> 22.987952 | T15: =$M15*(100%-T$6) -> 23.243373 | U15: =$M15*(100%-U$6) -> 23.498795 | ... X15: =$M15*(100%-X$6) -> 25.542169 | Y15: 0 | Z15: 0 | AA15: 0 | AC15: 82.28 | AD15: 65.66 | AE15: 88.08 | AF15: 75.87 | AG15: 101.34 | AH15: 81.13 | AI15: 108.14 | AJ15: 81.7 | AK15: 108.87 | AL15: 82.28 | AM15: 109.62 | AN15: 84.66 | AO15: 112.69 | AP15: 70.63 | AQ15: 97.64 | AR15: 71.06 | AS15: 98.24 | AT15: 71.49 | AU15: 98.83 | AV15: Negativa | AW15: Grupo 2
A16: Natulab | B16: Medicamentos | C16: 7899470805726 | D16: 27414 | E16: 15000220 | F16: Baby D - Pomada Para Assadura 45g 1bg X 100ct - Farma | G16: 30049099 | H16: ATIVO | I16: 100 | J16: ='LISTA PREÇO 2022-Vigen 01.02.22'!J16 -> 3.79 | L16: 3.71 | M16: =J16/(100%-$M$5) -> 4.5662651 | N16: =$M16*(100%-N$6) -> 3.8813253 | O16: =$M16*(100%-O$6) -> 3.926988 | P16: =$M16*(100%-P$6) -> 3.9726506 | Q16: =$M16*(100%-Q$6) -> 4.0183133 | R16: =$M16*(100%-R$6) -> 4.0639759 | S16: =$M16*(100%-S$6) -> 4.1096386 | T16: =$M16*(100%-T$6) -> 4.1553012 | U16: =$M16*(100%-U$6) -> 4.2009639 | ... X16: =$M16*(100%-X$6) -> 4.5662651 | Y16: 0 | Z16: 0 | AA16: 0 | AC16: 20.49 | AD16: 16.35 | AE16: 21.93 | AF16: 18.89 | AG16: 25.23 | AH16: 20.2 | AI16: 26.92 | AJ16: 20.34 | AK16: 27.1 | AL16: 20.49 | AM16: 27.3 | AN16: 21.08 | AO16: 28.06 | AP16: 17.59 | AQ16: 24.32 | AR16: 17.7 | AS16: 24.47 | AT16: 17.8 | AU16: 24.61 | AV16: Negativa | AW16: Grupo 1
A17: Natulab | B17: Medicamentos | C17: 7899470805955 | D17: 30023 | E17: 15000130 | F17: Bronqtrat 100ml 1ct X 50fr - Farma Novo | G17: 30049039 | H17: ATIVO | I17: 50 | J17: ='LISTA PREÇO 2022-Vigen 01.02.22'!J17 -> 2.69 | M17: =J17/(100%-$M$5) -> 3.2409639 | N17: =$M17*(100%-N$6) -> 2.7548193 | O17: =$M17*(100%-O$6) -> 2.7872289 | P17: =$M17*(100%-P$6) -> 2.8196386 | Q17: =$M17*(100%-Q$6) -> 2.8520482 | R17: =$M17*(100%-R$6) -> 2.8844578 | S17: =$M17*(100%-S$6) -> 2.9168675 | T17: =$M17*(100%-T$6) -> 2.9492771 | U17: =$M17*(100%-U$6) -> 2.9816867 | ... X17: =$M17*(100%-X$6) -> 3.2409639 | Y17: 0 | Z17: 0 | AA17: 0 | AC17: 26.65 | AD17: 21.26 | AE17: 28.52 | AF17: 24.57 | AG17: 32.82 | AH17: 26.28 | AI17: 35.02 | AJ17: 26.46 | AK17: 35.26 | AL17: 26.65 | AM17: 35.51 | AN17: 27.42 | AO17: 36.5 | AP17: 22.88 | AQ17: 31.63 | AR17: 23.02 | AS17: 31.82 | AT17: 23.16 | AU17: 32.02 | AV17: Negativa | AW17: Grupo 2
A18: Natulab | B18: Medicamentos | C18: 7898133135941 | D18: 23805 | E18: 15000071 | F18: Bronqtrat Infantil 100ml 1ct X 50fr - Farma | G18: 30049039 | H18: ATIVO | I18: 50 | J18: ='LISTA PREÇO 2022-Vigen 01.02.22'!J18 -> 2.81 | L18: 2.76 | M18: =J18/(100%-$M$5) -> 3.3855422 | N18: =$M18*(100%-N$6) -> 2.8777108 | O18: =$M18*(100%-O$6) -> 2.9115663 | P18: =$M18*(100%-P$6) -> 2.9454217 | Q18: =$M18*(100%-Q$6) -> 2.9792771 | R18: =$M18*(100%-R$6) -> 3.0131325 | S18: =$M18*(100%-S$6) -> 3.046988 | T18: =$M18*(100%-T$6) -> 3.0808434 | U18: =$M18*(100%-U$6) -> 3.1146988 | ... X18: =$M18*(100%-X$6) -> 3.3855422 | Y18: 0 | Z18: 0 | AA18: 0 | AC18: 27.79 | AD18: 22.17 | AE18: 29.74 | AF18: 25.62 | AG18: 34.22 | AH18: 27.4 | AI18: 36.52 | AJ18: 27.59 | AK18: 36.76 | AL18: 27.79 | AM18: 37.03 | AN18: 28.6 | AO18: 38.07 | AP18: 23.86 | AQ18: 32.99 | AR18: 24 | AS18: 33.18 | AT18: 24.15 | AU18: 33.39 | AV18: Negativa | AW18: Grupo 2
A19: Natulab | B19: Medicamentos | C19: 7899470802565 | D19: 28440 | E19: 15000117 | F19: Buscoplex Composto Gotas 20ml 1ct X 200fr - Farma | G19: 30044990 | H19: ATIVO | I19: 200 | J19: ='LISTA PREÇO 2022-Vigen 01.02.22'!J19 -> 5.6 | L19: 5.45 | M19: =J19/(100%-$M$5) -> 6.746988 | N19: =$M19*(100%-N$6) -> 5.7349398 | O19: =$M19*(100%-O$6) -> 5.8024096 | P19: =$M19*(100%-P$6) -> 5.8698795 | Q19: =$M19*(100%-Q$6) -> 5.9373494 | R19: =$M19*(100%-R$6) -> 6.0048193 | S19: =$M19*(100%-S$6) -> 6.0722892 | T19: =$M19*(100%-T$6) -> 6.139759 | U19: =$M19*(100%-U$6) -> 6.2072289 | ... X19: =$M19*(100%-X$6) -> 6.746988 | Y19: 5.29 | Z19: 8.1765 | AA19: 0 | AC19: 10.84 | AD19: 8.65 | AE19: 11.6 | AF19: 9.99 | AG19: 13.34 | AH19: 10.69 | AI19: 14.24 | AJ19: 10.76 | AK19: 14.33 | AL19: 10.84 | AM19: 14.44 | AN19: 11.15 | AO19: 14.84 | AP19: 9.31 | AQ19: 12.87 | AR19: 9.36 | AS19: 12.94 | AT19: 9.42 | AU19: 13.02 | AV19: Negativa | AW19: Grupo 2
A20: Natulab | B20: Medicamentos | C20: 7899470805849 | D20: 33549 | E20: 15000131 | F20: Butalab C/ Cp Med 100ml 1ct X 50fr - Farma | G20: 30039099 | H20: ATIVO | I20: 50 | J20: ='LISTA PREÇO 2022-Vigen 01.02.22'!J20 -> 1.77 | L20: 1.74 | M20: =J20/(100%-$M$5) -> 2.1325301 | N20: =$M20*(100%-N$6) -> 1.8126506 | O20: =$M20*(100%-O$6) -> 1.8339759 | P20: =$M20*(100%-P$6) -> 1.8553012 | Q20: =$M20*(100%-Q$6) -> 1.8766265 | R20: =$M20*(100%-R$6) -> 1.8979518 | S20: =$M20*(100%-S$6) -> 1.9192771 | T20: =$M20*(100%-T$6) -> 1.9406024 | U20: =$M20*(100%-U$6) -> 1.9619277 | ... X20: =$M20*(100%-X$6) -> 2.1325301 | Y20: 0 | Z20: 0 | AA20: 0 | AC20: 5.48 | AD20: 4.49 | AE20: 6.2 | AF20: 5.1 | AG20: 7.05 | AH20: 5.41 | AI20: 7.47 | AJ20: 5.44 | AK20: 7.52 | AL20: 5.48 | AM20: 7.58 | AN20: 5.62 | AO20: 7.77 | AP20: 5.41 | AQ20: 7.48 | AR20: 5.45 | AS20: 7.53 | AT20: 5.48 | AU20: 7.58 | AV20: Positiva | AW20: Grupo 3
A21: Natulab | B21: Medicamentos | C21: 7899470804200 | D21: 44983 | E21: 15000211 | F21: Cardomarin 127mg 2bl X 10com X 100ct - Farma | G21: 30049099 | H21: ATIVO | I21: 100 | J21: ='LISTA PREÇO 2022-Vigen 01.02.22'!J21 -> 11.98 | L21: 11.75 | M21: =J21/(100%-$M$5) -> 14.433735 | N21: =$M21*(100%-N$6) -> 12.268675 | O21: =$M21*(100%-O$6) -> 12.413012 | P21: =$M21*(100%-P$6) -> 12.557349 | Q21: =$M21*(100%-Q$6) -> 12.701687 | R21: =$M21*(100%-R$6) -> 12.846024 | S21: =$M21*(100%-S$6) -> 12.990361 | T21: =$M21*(100%-T$6) -> 13.134699 | U21: =$M21*(100%-U$6) -> 13.279036 | ... X21: =$M21*(100%-X$6) -> 14.433735 | Y21: 0 | Z21: 0 | AA21: 0 | AC21: 50.38 | AD21: 40.2 | AE21: 53.92 | AF21: 46.45 | AG21: 62.04 | AH21: 49.68 | AI21: 66.22 | AJ21: 50.02 | AK21: 66.65 | AL21: 50.38 | AM21: 67.12 | AN21: 51.84 | AO21: 69 | AP21: 43.25 | AQ21: 59.79 | AR21: 43.51 | AS21: 60.15 | AT21: 43.78 | AU21: 60.52 | AV21: Negativa | AW21: Grupo 1
A22: Natulab | B22: Medicamentos | C22: 7899470803647 | D22: 23815 | E22: 15000074 | F22: Cardomarin 18.05mg 100ml 1ct X 50fr - Farma | G22: 30049099 | H22: ATIVO | I22: 50 | J22: ='LISTA PREÇO 2022-Vigen 01.02.22'!J22 -> 15.39 | L22: 0 | M22: =J22/(100%-$M$5) -> 18.542169 | N22: =$M22*(100%-N$6) -> 15.760843 | O22: =$M22*(100%-O$6) -> 15.946265 | P22: =$M22*(100%-P$6) -> 16.131687 | Q22: =$M22*(100%-Q$6) -> 16.317108 | R22: =$M22*(100%-R$6) -> 16.50253 | S22: =$M22*(100%-S$6) -> 16.687952 | T22: =$M22*(100%-T$6) -> 16.873373 | U22: =$M22*(100%-U$6) -> 17.058795 | ... X22: =$M22*(100%-X$6) -> 18.542169 | Y22: 0 | Z22: 0 | AA22: 0 | AC22: 50.25 | AD22: 40.1 | AE22: 53.79 | AF22: 46.33 | AG22: 61.88 | AH22: 49.55 | AI22: 66.04 | AJ22: 49.89 | AK22: 66.48 | AL22: 50.25 | AM22: 66.95 | AN22: 51.71 | AO22: 68.83 | AP22: 43.14 | AQ22: 59.64 | AR22: 43.4 | AS22: 60 | AT22: 43.66 | AU22: 60.36 | AV22: Negativa | AW22: Grupo 1
A23: Natulab | B23: Medicamentos | C23: 7899470804149 | D23: 45087 | E23: 15000213 | F23: Cardomarin Cap Dura 254Mg X 20 | G23: 30049099 | H23: ATIVO | I23: 50 | J23: ='LISTA PREÇO 2022-Vigen 01.02.22'!J23 -> 16.96 | L23: 16.63 | M23: =J23/(100%-$M$5) -> 20.433735 | N23: =$M23*(100%-N$6) -> 17.368675 | O23: =$M23*(100%-O$6) -> 17.573012 | P23: =$M23*(100%-P$6) -> 17.777349 | Q23: =$M23*(100%-Q$6) -> 17.981687 | R23: =$M23*(100%-R$6) -> 18.186024 | S23: =$M23*(100%-S$6) -> 18.390361 | T23: =$M23*(100%-T$6) -> 18.594699 | U23: =$M23*(100%-U$6) -> 18.799036 | ... X23: =$M23*(100%-X$6) -> 20.433735 | Y23: 16.15 | Z23: 29.4546 | AA23: 0 | AC23: 70.13 | AD23: 55.96 | AE23: 75.06 | AF23: 64.67 | AG23: 86.38 | AH23: 69.15 | AI23: 92.17 | AJ23: 69.64 | AK23: 92.8 | AL23: 70.13 | AM23: 93.44 | AN23: 72.16 | AO23: 96.05 | AP23: 60.2 | AQ23: 83.22 | AR23: 60.57 | AS23: 83.73 | AT23: 60.94 | AU23: 84.25 | AV23: Negativa | AW23: Grupo 1
A24: Natulab | B24: Medicamentos | C24: 7898133137549 | D24: 23780 | E24: 15000158 | F24: Comple B Comprimidos 1fr X 50com X 100ct - Farma | G24: 30045090 | H24: ATIVO | I24: 100 | J24: ='LISTA PREÇO 2022-Vigen 01.02.22'!J24 -> 4.23 | L24: 3.79 | M24: =J24/(100%-$M$5) -> 5.0963855 | N24: =$M24*(100%-N$6) -> 4.3319277 | O24: =$M24*(100%-O$6) -> 4.3828916 | P24: =$M24*(100%-P$6) -> 4.4338554 | Q24: =$M24*(100%-Q$6) -> 4.4848193 | R24: =$M24*(100%-R$6) -> 4.5357831 | S24: =$M24*(100%-S$6) -> 4.586747 | T24: =$M24*(100%-T$6) -> 4.6377108 | U24: =$M24*(100%-U$6) -> 4.6886747 | ... X24: =$M24*(100%-X$6) -> 5.0963855 | Y24: 3.68 | Z24: 5.08 | AA24: 0 | AC24: 25.56 | AD24: 20.39 | AE24: 27.35 | AF24: 23.57 | AG24: 31.48 | AH24: 25.2 | AI24: 33.59 | AJ24: 25.38 | AK24: 33.82 | AL24: 25.56 | AM24: 34.05 | AN24: 26.3 | AO24: 35.01 | AP24: 21.94 | AQ24: 30.33 | AR24: 22.08 | AS24: 30.52 | AT24: 22.21 | AU24: 30.7 | AV24: Negativa | AW24: Grupo 2
A25: Natulab | B25: Medicamentos | C25: 7899470802282 | D25: 23783 | E25: 15000159 | F25: Epaphyto Cap Dura 300mg x 30 | G25: 30044990 | H25: ATIVO | I25: 100 | J25: ='LISTA PREÇO 2022-Vigen 01.02.22'!J25 -> 9.53 | L25: 9.35 | M25: =J25/(100%-$M$5) -> 11.481928 | N25: =$M25*(100%-N$6) -> 9.7596386 | O25: =$M25*(100%-O$6) -> 9.8744578 | P25: =$M25*(100%-P$6) -> 9.9892771 | Q25: =$M25*(100%-Q$6) -> 10.104096 | R25: =$M25*(100%-R$6) -> 10.218916 | S25: =$M25*(100%-S$6) -> 10.333735 | T25: =$M25*(100%-T$6) -> 10.448554 | U25: =$M25*(100%-U$6) -> 10.563373 | ... X25: =$M25*(100%-X$6) -> 11.481928 | Y25: 0 | Z25: 0 | AA25: 0 | AC25: 38.29 | AD25: 30.55 | AE25: 40.98 | AF25: 35.31 | AG25: 47.16 | AH25: 37.75 | AI25: 50.31 | AJ25: 38.02 | AK25: 50.66 | AL25: 38.29 | AM25: 51.01 | AN25: 39.4 | AO25: 52.44 | AP25: 32.87 | AQ25: 45.44 | AR25: 33.07 | AS25: 45.72 | AT25: 33.27 | AU25: 45.99 | AV25: Negativa | AW25: Grupo 2
A26: Natulab | B26: Medicamentos | C26: 7899470803067 | D26: 24129 | E26: 15000114 | F26: Epaphyto Sol Or 14mg X 150ml | G26: 30044990 | H26: ATIVO | I26: 60 | J26: ='LISTA PREÇO 2022-Vigen 01.02.22'!J26 -> 10.85 | L26: 10.649524 | M26: =J26/(100%-$M$5) -> 13.072289 | N26: =$M26*(100%-N$6) -> 11.111446 | O26: =$M26*(100%-O$6) -> 11.242169 | P26: =$M26*(100%-P$6) -> 11.372892 | Q26: =$M26*(100%-Q$6) -> 11.503614 | R26: =$M26*(100%-R$6) -> 11.634337 | S26: =$M26*(100%-S$6) -> 11.76506 | T26: =$M26*(100%-T$6) -> 11.895783 | U26: =$M26*(100%-U$6) -> 12.026506 | ... X26: =$M26*(100%-X$6) -> 13.072289 | Y26: 0 | Z26: 0 | AA26: 0 | AC26: 43.4 | AD26: 34.63 | AE26: 46.45 | AF26: 40.02 | AG26: 53.45 | AH26: 42.79 | AI26: 57.03 | AJ26: 43.09 | AK26: 57.42 | AL26: 43.4 | AM26: 57.82 | AN26: 44.66 | AO26: 59.44 | AP26: 37.26 | AQ26: 51.51 | AR26: 37.48 | AS26: 51.81 | AT26: 37.71 | AU26: 52.13 | AV26: Negativa | AW26: Grupo 2
A27: Natulab | B27: Medicamentos | C27: 7899470802299 | D27: 23830 | E27: 15000160 | F27: Espinheira Santa Natulab 380mg 3bl X 15cap X 50ct - Farma | G27: 30049099 | H27: ATIVO | I27: 50 | J27: ='LISTA PREÇO 2022-Vigen 01.02.22'!J27 -> 11.03 | L27: 10.82 | M27: =J27/(100%-$M$5) -> 13.289157 | N27: =$M27*(100%-N$6) -> 11.295783 | O27: =$M27*(100%-O$6) -> 11.428675 | P27: =$M27*(100%-P$6) -> 11.561566 | Q27: =$M27*(100%-Q$6) -> 11.694458 | R27: =$M27*(100%-R$6) -> 11.827349 | S27: =$M27*(100%-S$6) -> 11.960241 | T27: =$M27*(100%-T$6) -> 12.093133 | U27: =$M27*(100%-U$6) -> 12.226024 | ... X27: =$M27*(100%-X$6) -> 13.289157 | Y27: 0 | Z27: 0 | AA27: 0 | AC27: 52.01 | AD27: 41.5 | AE27: 55.67 | AF27: 47.96 | AG27: 64.06 | AH27: 51.28 | AI27: 68.35 | AJ27: 51.64 | AK27: 68.81 | AL27: 52.01 | AM27: 69.29 | AN27: 53.52 | AO27: 71.24 | AP27: 44.65 | AQ27: 61.73 | AR27: 44.92 | AS27: 62.1 | AT27: 45.19 | AU27: 62.47 | AV27: Negativa | AW27: Grupo 2
A28: Natulab | B28: Medicamentos | C28: 7898133131110 | D28: 23825 | E28: 15000078 | F28: Expectoflui 120ml 1 X 30fr - Farma | G28: 30049039 | H28: ATIVO | I28: 30 | J28: ='LISTA PREÇO 2022-Vigen 01.02.22'!J28 -> 3.62 | L28: 3.55 | M28: =J28/(100%-$M$5) -> 4.3614458 | N28: =$M28*(100%-N$6) -> 3.7072289 | O28: =$M28*(100%-O$6) -> 3.7508434 | P28: =$M28*(100%-P$6) -> 3.7944578 | Q28: =$M28*(100%-Q$6) -> 3.8380723 | R28: =$M28*(100%-R$6) -> 3.8816867 | S28: =$M28*(100%-S$6) -> 3.9253012 | T28: =$M28*(100%-T$6) -> 3.9689157 | U28: =$M28*(100%-U$6) -> 4.0125301 | ... X28: =$M28*(100%-X$6) -> 4.3614458 | Y28: 0 | Z28: 0 | AA28: 0 | AC28: 15.13 | AD28: 12.07 | AE28: 16.19 | AF28: 13.95 | AG28: 18.63 | AH28: 14.92 | AI28: 19.88 | AJ28: 15.02 | AK28: 20.01 | AL28: 15.13 | AM28: 20.16 | AN28: 15.57 | AO28: 20.72 | AP28: 12.99 | AQ28: 17.96 | AR28: 13.07 | AS28: 18.07 | AT28: 13.15 | AU28: 18.18 | AV28: Negativa | AW28: Grupo 2
A29: Natulab | B29: Medicamentos | C29: 7898133131400 | D29: 23828 | E29: 15000079 | F29: Helmilab S/Acucar 30m 1ct X 200fr - Farma | G29: 30049099 | H29: ATIVO | I29: 200 | J29: ='LISTA PREÇO 2022-Vigen 01.02.22'!J29 -> 1.48 | L29: 1.45 | M29: =J29/(100%-$M$5) -> 1.7831325 | N29: =$M29*(100%-N$6) -> 1.5156627 | O29: =$M29*(100%-O$6) -> 1.533494 | P29: =$M29*(100%-P$6) -> 1.5513253 | Q29: =$M29*(100%-Q$6) -> 1.5691566 | R29: =$M29*(100%-R$6) -> 1.586988 | S29: =$M29*(100%-S$6) -> 1.6048193 | T29: =$M29*(100%-T$6) -> 1.6226506 | U29: =$M29*(100%-U$6) -> 1.6404819 | ... X29: =$M29*(100%-X$6) -> 1.7831325 | Y29: 1.4 | Z29: 0 | AA29: 0 | AC29: 6.92 | AD29: 5.52 | AE29: 7.4 | AF29: 6.38 | AG29: 8.52 | AH29: 6.82 | AI29: 9.09 | AJ29: 6.87 | AK29: 9.15 | AL29: 6.92 | AM29: 9.22 | AN29: 7.12 | AO29: 9.48 | AP29: 5.94 | AQ29: 8.21 | AR29: 5.98 | AS29: 8.27 | AT29: 6.01 | AU29: 8.31 | AV29: Negativa | AW29: Grupo 2
... A42: Natulab | B42: Medicamentos | C42: 7898133134760 | D42: 23857 | E42: 15000086 | F42: Ibuprotrat Infantil C/Seringa 100ml 1ct X 50fr - Farma | G42: 30049029 | H42: ATIVO | I42: 50 | J42: ='LISTA PREÇO 2022-Vigen 01.02.22'!J42 -> 4.34 | L42: 4.2622 | M42: =J42/(100%-$M$5) -> 5.2289157 | N42: =$M42*(100%-N$6) -> 4.4445783 | O42: =$M42*(100%-O$6) -> 4.4968675 | P42: =$M42*(100%-P$6) -> 4.5491566 | Q42: =$M42*(100%-Q$6) -> 4.6014458 | R42: =$M42*(100%-R$6) -> 4.6537349 | S42: =$M42*(100%-S$6) -> 4.7060241 | T42: =$M42*(100%-T$6) -> 4.7583133 | U42: =$M42*(100%-U$6) -> 4.8106024 | ... X42: =$M42*(100%-X$6) -> 5.2289157 | Y42: 0 | Z42: 0 | AA42: 0 | AC42: 23.93 | AD42: 19.09 | AE42: 25.6 | AF42: 22.06 | AG42: 29.46 | AH42: 23.59 | AI42: 31.44 | AJ42: 23.76 | AK42: 31.66 | AL42: 23.93 | AM42: 31.88 | AN42: 24.62 | AO42: 32.77 | AP42: 20.54 | AQ42: 28.4 | AR42: 20.67 | AS42: 28.58 | AT42: 20.79 | AU42: 28.74 | AV42: Negativa | AW42: Grupo 2
A43: Natulab | B43: Medicamentos | C43: 7898133130281 | D43: 23863 | E43: 15000087 | F43: Iodenax 100ml 1ct X 50fr - Farma | G43: 30049099 | H43: ATIVO | I43: 50 | J43: ='LISTA PREÇO 2022-Vigen 01.02.22'!J43 -> 3.54 | M43: =J43/(100%-$M$5) -> 4.2650602 | N43: =$M43*(100%-N$6) -> 3.6253012 | O43: =$M43*(100%-O$6) -> 3.6679518 | P43: =$M43*(100%-P$6) -> 3.7106024 | Q43: =$M43*(100%-Q$6) -> 3.753253 | R43: =$M43*(100%-R$6) -> 3.7959036 | S43: =$M43*(100%-S$6) -> 3.8385542 | T43: =$M43*(100%-T$6) -> 3.8812048 | U43: =$M43*(100%-U$6) -> 3.9238554 | ... X43: =$M43*(100%-X$6) -> 4.2650602 | Y43: 0 | Z43: 0 | AA43: 0 | AC43: 21.63 | AD43: 17.26 | AE43: 23.15 | AF43: 19.94 | AG43: 26.63 | AH43: 21.33 | AI43: 28.43 | AJ43: 21.47 | AK43: 28.61 | AL43: 21.63 | AM43: 28.82 | AN43: 22.26 | AO43: 29.63 | AP43: 18.57 | AQ43: 25.67 | AR43: 18.68 | AS43: 25.82 | AT43: 18.8 | AU43: 25.99 | AV43: Negativa | AW43: Grupo 1
A44: Natulab | B44: Medicamentos | C44: 7898133134753 | D44: 23868 | E44: 15000088 | F44: Kalonat 10ml 1ct X 100fr - Farma | G44: 30049029 | H44: ATIVO | I44: 100 | J44: ='LISTA PREÇO 2022-Vigen 01.02.22'!J44 -> 5.09 | M44: =J44/(100%-$M$5) -> 6.1325301 | N44: =$M44*(100%-N$6) -> 5.2126506 | O44: =$M44*(100%-O$6) -> 5.2739759 | P44: =$M44*(100%-P$6) -> 5.3353012 | Q44: =$M44*(100%-Q$6) -> 5.3966265 | R44: =$M44*(100%-R$6) -> 5.4579518 | S44: =$M44*(100%-S$6) -> 5.5192771 | T44: =$M44*(100%-T$6) -> 5.5806024 | U44: =$M44*(100%-U$6) -> 5.6419277 | ... X44: =$M44*(100%-X$6) -> 6.1325301 | Y44: 4.85 | Z44: 9.8115 | AA44: 0 | AC44: 31.65 | AD44: 25.25 | AE44: 33.87 | AF44: 29.18 | AG44: 38.97 | AH44: 31.21 | AI44: 41.6 | AJ44: 31.42 | AK44: 41.87 | AL44: 31.65 | AM44: 42.17 | AN44: 32.57 | AO44: 43.35 | AP44: 27.17 | AQ44: 37.56 | AR44: 27.34 | AS44: 37.8 | AT44: 27.5 | AU44: 38.02 | AV44: Negativa | AW44: Grupo 1
A45: Natulab | B45: Medicamentos | C45: 7898133136092 | D45: 28605 | E45: 15000122 | F45: Kollangel 150ml Hortela Fn 1ct X 60fr - Farma | G45: 30039099 | H45: ATIVO | I45: 60 | J45: ='LISTA PREÇO 2022-Vigen 01.02.22'!J45 -> 4.93 | L45: 4.84 | M45: =J45/(100%-$M$5) -> 5.939759 | N45: =$M45*(100%-N$6) -> 5.0487952 | O45: =$M45*(100%-O$6) -> 5.1081928 | P45: =$M45*(100%-P$6) -> 5.1675904 | Q45: =$M45*(100%-Q$6) -> 5.226988 | R45: =$M45*(100%-R$6) -> 5.2863855 | S45: =$M45*(100%-S$6) -> 5.3457831 | T45: =$M45*(100%-T$6) -> 5.4051807 | U45: =$M45*(100%-U$6) -> 5.4645783 | ... X45: =$M45*(100%-X$6) -> 5.939759 | Y45: 0 | Z45: 0 | AA45: 0 | AC45: 24.4 | AD45: 19.47 | AE45: 26.11 | AF45: 22.5 | AG45: 30.05 | AH45: 24.06 | AI45: 32.07 | AJ45: 24.23 | AK45: 32.28 | AL45: 24.4 | AM45: 32.51 | AN45: 25.11 | AO45: 33.42 | AP45: 20.95 | AQ45: 28.96 | AR45: 21.07 | AS45: 29.13 | AT45: 21.2 | AU45: 29.31 | AV45: Negativa | AW45: Grupo 1
A46: Natulab | B46: Medicamentos | C46: 7898133136085 | D46: 28607 | E46: 15000123 | F46: Kollangel 150ml Morango Fn 1ct X 60fr - Farma | G46: 30039099 | H46: ATIVO | I46: 60 | J46: ='LISTA PREÇO 2022-Vigen 01.02.22'!J46 -> 4.93 | L46: 4.84 | M46: =J46/(100%-$M$5) -> 5.939759 | N46: =$M46*(100%-N$6) -> 5.0487952 | O46: =$M46*(100%-O$6) -> 5.1081928 | P46: =$M46*(100%-P$6) -> 5.1675904 | Q46: =$M46*(100%-Q$6) -> 5.226988 | R46: =$M46*(100%-R$6) -> 5.2863855 | S46: =$M46*(100%-S$6) -> 5.3457831 | T46: =$M46*(100%-T$6) -> 5.4051807 | U46: =$M46*(100%-U$6) -> 5.4645783 | ... X46: =$M46*(100%-X$6) -> 5.939759 | Y46: 0 | Z46: 0 | AA46: 0 | AC46: 25.57 | AD46: 20.4 | AE46: 27.36 | AF46: 23.58 | AG46: 31.49 | AH46: 25.21 | AI46: 33.6 | AJ46: 25.39 | AK46: 33.83 | AL46: 25.57 | AM46: 34.07 | AN46: 26.31 | AO46: 35.02 | AP46: 21.95 | AQ46: 30.35 | AR46: 22.08 | AS46: 30.52 | AT46: 22.22 | AU46: 30.72 | AV46: Negativa | AW46: Grupo 1
A47: Natulab | B47: Medicamentos | C47: 7898133134661 | D47: 28603 | E47: 15000121 | F47: Kollangel 150ml Papaia Fn 1ct X 60fr - Farma | G47: 30039099 | H47: ATIVO | I47: 60 | J47: ='LISTA PREÇO 2022-Vigen 01.02.22'!J47 -> 4.93 | M47: =J47/(100%-$M$5) -> 5.939759 | N47: =$M47*(100%-N$6) -> 5.0487952 | O47: =$M47*(100%-O$6) -> 5.1081928 | P47: =$M47*(100%-P$6) -> 5.1675904 | Q47: =$M47*(100%-Q$6) -> 5.226988 | R47: =$M47*(100%-R$6) -> 5.2863855 | S47: =$M47*(100%-S$6) -> 5.3457831 | T47: =$M47*(100%-T$6) -> 5.4051807 | U47: =$M47*(100%-U$6) -> 5.4645783 | ... X47: =$M47*(100%-X$6) -> 5.939759 | Y47: 0 | Z47: 0 | AA47: 0 | AC47: 25.57 | AD47: 20.4 | AE47: 27.36 | AF47: 23.58 | AG47: 31.49 | AH47: 25.21 | AI47: 33.6 | AJ47: 25.39 | AK47: 33.83 | AL47: 25.57 | AM47: 34.07 | AN47: 26.31 | AO47: 35.02 | AP47: 21.95 | AQ47: 30.35 | AR47: 22.08 | AS47: 30.52 | AT47: 22.22 | AU47: 30.72 | AV47: Negativa | AW47: Grupo 1
A48: Natulab | B48: Medicamentos | C48: 7898133139420 | D48: 23876 | E48: 15000090 | F48: L-Enema 130ml 1ct X 50fr - Farma | G48: 30049099 | H48: ATIVO | I48: 50 | J48: ='LISTA PREÇO 2022-Vigen 01.02.22'!J48 -> 7.65 | L48: 7.5 | M48: =J48/(100%-$M$5) -> 9.2168675 | N48: =$M48*(100%-N$6) -> 7.8343373 | O48: =$M48*(100%-O$6) -> 7.926506 | P48: =$M48*(100%-P$6) -> 8.0186747 | Q48: =$M48*(100%-Q$6) -> 8.1108434 | R48: =$M48*(100%-R$6) -> 8.203012 | S48: =$M48*(100%-S$6) -> 8.2951807 | T48: =$M48*(100%-T$6) -> 8.3873494 | U48: =$M48*(100%-U$6) -> 8.4795181 | ... X48: =$M48*(100%-X$6) -> 9.2168675 | Y48: 7.28 | Z48: 6.435 | AA48: 8.88 | AC48: 11.7 | AD48: 9.33 | AE48: 12.51 | AF48: 10.78 | AG48: 14.4 | AH48: 11.53 | AI48: 15.36 | AJ48: 11.61 | AK48: 15.47 | AL48: 11.7 | AM48: 15.59 | AN48: 12.04 | AO48: 16.03 | AP48: 10.04 | AQ48: 13.88 | AR48: 10.11 | AS48: 13.98 | AT48: 10.17 | AU48: 14.06 | AV48: Negativa | AW48: Grupo 1
A49: Natulab | B49: Medicamentos | C49: 7898133134715 | D49: 23879 | E49: 15000091 | F49: Limonada Purgativa 200ml 1 X 60fr - Farma | G49: 30039099 | H49: ATIVO | I49: 60 | J49: ='LISTA PREÇO 2022-Vigen 01.02.22'!J49 -> 4.36 | L49: 4.27 | M49: =J49/(100%-$M$5) -> 5.253012 | N49: =$M49*(100%-N$6) -> 4.4650602 | O49: =$M49*(100%-O$6) -> 4.5175904 | P49: =$M49*(100%-P$6) -> 4.5701205 | Q49: =$M49*(100%-Q$6) -> 4.6226506 | R49: =$M49*(100%-R$6) -> 4.6751807 | S49: =$M49*(100%-S$6) -> 4.7277108 | T49: =$M49*(100%-T$6) -> 4.780241 | U49: =$M49*(100%-U$6) -> 4.8327711 | ... X49: =$M49*(100%-X$6) -> 5.253012 | Y49: 0 | Z49: 0 | AA49: 0 | AC49: 29.33 | AD49: 23.4 | AE49: 31.39 | AF49: 27.04 | AG49: 36.12 | AH49: 28.92 | AI49: 38.54 | AJ49: 29.12 | AK49: 38.8 | AL49: 29.33 | AM49: 39.08 | AN49: 30.18 | AO49: 40.17 | AP49: 25.18 | AQ49: 34.81 | AR49: 25.33 | AS49: 35.02 | AT49: 25.49 | AU49: 35.24 | AV49: Negativa | AW49: Grupo 1
A50: Natulab | B50: Medicamentos | C50: 7898133137969 | D50: 35686 | E50: 15000135 | F50: Lufbem Gotas 15ml 1ct X 100 - Farma | G50: 30049099 | H50: ATIVO | I50: 100 | J50: ='LISTA PREÇO 2022-Vigen 01.02.22'!J50 -> 1.78 | L50: 1.75 | M50: =J50/(100%-$M$5) -> 2.1445783 | N50: =$M50*(100%-N$6) -> 1.8228916 | O50: =$M50*(100%-O$6) -> 1.8443373 | P50: =$M50*(100%-P$6) -> 1.8657831 | Q50: =$M50*(100%-Q$6) -> 1.8872289 | R50: =$M50*(100%-R$6) -> 1.9086747 | S50: =$M50*(100%-S$6) -> 1.9301205 | T50: =$M50*(100%-T$6) -> 1.9515663 | U50: =$M50*(100%-U$6) -> 1.973012 | ... X50: =$M50*(100%-X$6) -> 2.1445783 | Y50: 1.45 | Z50: 5.2775 | AA50: 0 | AC50: 21.11 | AD50: 16.84 | AE50: 22.59 | AF50: 19.46 | AG50: 25.99 | AH50: 20.81 | AI50: 27.73 | AJ50: 20.96 | AK50: 27.93 | AL50: 21.11 | AM50: 28.13 | AN50: 21.72 | AO50: 28.91 | AP50: 18.12 | AQ50: 25.05 | AR50: 18.23 | AS50: 25.2 | AT50: 18.34 | AU50: 25.35 | AV50: Negativa | AW50: Grupo 1
A51: Natulab | B51: Medicamentos | C51: 7899470802275 | D51: 23883 | E51: 15000093 | F51: Magmax Hortela 100ml 1 X 100fr - Farma | G51: 30049099 | H51: ATIVO | I51: 100 | J51: ='LISTA PREÇO 2022-Vigen 01.02.22'!J51 -> 3.07 | L51: 3.01 | M51: =J51/(100%-$M$5) -> 3.6987952 | N51: =$M51*(100%-N$6) -> 3.1439759 | O51: =$M51*(100%-O$6) -> 3.1809639 | P51: =$M51*(100%-P$6) -> 3.2179518 | Q51: =$M51*(100%-Q$6) -> 3.2549398 | R51: =$M51*(100%-R$6) -> 3.2919277 | S51: =$M51*(100%-S$6) -> 3.3289157 | T51: =$M51*(100%-T$6) -> 3.3659036 | U51: =$M51*(100%-U$6) -> 3.4028916 | ... X51: =$M51*(100%-X$6) -> 3.6987952 | Y51: 2.92 | Z51: 0 | AA51: 0 | AC51: 15.38 | AD51: 12.27 | AE51: 16.46 | AF51: 14.18 | AG51: 18.94 | AH51: 15.16 | AI51: 20.2 | AJ51: 15.27 | AK51: 20.34 | AL51: 15.38 | AM51: 20.49 | AN51: 15.83 | AO51: 21.07 | AP51: 13.2 | AQ51: 18.25 | AR51: 13.28 | AS51: 18.36 | AT51: 13.36 | AU51: 18.47 | AV51: Negativa | AW51: Grupo 1
A52: Natulab | B52: Medicamentos | C52: 7899470802268 | D52: 23881 | E52: 15000092 | F52: Magmax Tradicional 100ml 1 X 100fr - Farma | G52: 30049099 | H52: ATIVO | I52: 100 | J52: ='LISTA PREÇO 2022-Vigen 01.02.22'!J52 -> 3.07 | L52: 3.01 | M52: =J52/(100%-$M$5) -> 3.6987952 | N52: =$M52*(100%-N$6) -> 3.1439759 | O52: =$M52*(100%-O$6) -> 3.1809639 | P52: =$M52*(100%-P$6) -> 3.2179518 | Q52: =$M52*(100%-Q$6) -> 3.2549398 | R52: =$M52*(100%-R$6) -> 3.2919277 | S52: =$M52*(100%-S$6) -> 3.3289157 | T52: =$M52*(100%-T$6) -> 3.3659036 | U52: =$M52*(100%-U$6) -> 3.4028916 | ... X52: =$M52*(100%-X$6) -> 3.6987952 | Y52: 2.92 | Z52: 4.944 | AA52: 3.399 | AC52: 15.45 | AD52: 12.32 | AE52: 16.52 | AF52: 14.24 | AG52: 19.02 | AH52: 15.23 | AI52: 20.3 | AJ52: 15.34 | AK52: 20.44 | AL52: 15.45 | AM52: 20.58 | AN52: 15.9 | AO52: 21.16 | AP52: 13.26 | AQ52: 18.33 | AR52: 13.34 | AS52: 18.44 | AT52: 13.43 | AU52: 18.57 | AV52: Negativa | AW52: Grupo 1
A53: Natulab | B53: Medicamentos | C53: 7899470807225 | D53: 38804 | E53: 15000194 | F53: Masferol Comprimidos 109mg 2bl X 20com X 200ct - Farma | G53: 30039099 | H53: ATIVO | I53: 200 | J53: ='LISTA PREÇO 2022-Vigen 01.02.22'!J53 -> 3.25 | L53: 3.18 | M53: =J53/(100%-$M$5) -> 3.9156627 | N53: =$M53*(100%-N$6) -> 3.3283133 | O53: =$M53*(100%-O$6) -> 3.3674699 | P53: =$M53*(100%-P$6) -> 3.4066265 | Q53: =$M53*(100%-Q$6) -> 3.4457831 | R53: =$M53*(100%-R$6) -> 3.4849398 | S53: =$M53*(100%-S$6) -> 3.5240964 | T53: =$M53*(100%-T$6) -> 3.563253 | U53: =$M53*(100%-U$6) -> 3.6024096 | ... X53: =$M53*(100%-X$6) -> 3.9156627 | Y53: 3.09 | Z53: 4.1752 | AA53: 0 | AC53: 12.28 | AD53: 9.8 | AE53: 13.14 | AF53: 11.32 | AG53: 15.12 | AH53: 12.11 | AI53: 16.14 | AJ53: 12.19 | AK53: 16.24 | AL53: 12.28 | AM53: 16.36 | AN53: 12.64 | AO53: 16.82 | AP53: 10.54 | AQ53: 14.57 | AR53: 10.61 | AS53: 14.67 | AT53: 10.67 | AU53: 14.75 | AV53: Negativa | AW53: Grupo 1
A54: Natulab | B54: Medicamentos | C54: 7898133134999 | D54: 41484 | E54: 15000143 | F54: MASFEROL SOL OR 25MG/ML X 100ML | G54: 30039099 | H54: ATIVO | I54: 50 | J54: ='LISTA PREÇO 2022-Vigen 01.02.22'!J54 -> 2.19 | L54: 2.15 | M54: =J54/(100%-$M$5) -> 2.6385542 | N54: =$M54*(100%-N$6) -> 2.2427711 | O54: =$M54*(100%-O$6) -> 2.2691566 | P54: =$M54*(100%-P$6) -> 2.2955422 | Q54: =$M54*(100%-Q$6) -> 2.3219277 | R54: =$M54*(100%-R$6) -> 2.3483133 | S54: =$M54*(100%-S$6) -> 2.3746988 | T54: =$M54*(100%-T$6) -> 2.4010843 | U54: =$M54*(100%-U$6) -> 2.4274699 | ... X54: =$M54*(100%-X$6) -> 2.6385542 | Y54: 2.09 | Z54: 2.7792 | AA54: 0 | AC54: 11.58 | AD54: 9.24 | AE54: 12.39 | AF54: 10.67 | AG54: 14.25 | AH54: 11.41 | AI54: 15.2 | AJ54: 11.49 | AK54: 15.31 | AL54: 11.58 | AM54: 15.43 | AN54: 11.92 | AO54: 15.87 | AP54: 9.94 | AQ54: 13.74 | AR54: 10 | AS54: 13.82 | AT54: 10.06 | AU54: 13.91 | AV54: Negativa | AW54: Grupo 2
A55: Natulab | B55: Medicamentos | C55: 7898133131028 | D55: 23912 | E55: 15000096 | F55: Maxalgina 100ml 1ct X 50fr - Farma | G55: 30049069 | H55: ATIVO | I55: 50 | J55: ='LISTA PREÇO 2022-Vigen 01.02.22'!J55 -> 2.85 | L55: 2.8 | M55: =J55/(100%-$M$5) -> 3.4337349 | N55: =$M55*(100%-N$6) -> 2.9186747 | O55: =$M55*(100%-O$6) -> 2.953012 | P55: =$M55*(100%-P$6) -> 2.9873494 | Q55: =$M55*(100%-Q$6) -> 3.0216867 | R55: =$M55*(100%-R$6) -> 3.0560241 | S55: =$M55*(100%-S$6) -> 3.0903614 | T55: =$M55*(100%-T$6) -> 3.1246988 | U55: =$M55*(100%-U$6) -> 3.1590361 | ... X55: =$M55*(100%-X$6) -> 3.4337349 | Y55: 0 | Z55: 0 | AA55: 2.90792 | AC55: 17.84 | AD55: 14.23 | AE55: 19.08 | AF55: 16.45 | AG55: 21.97 | AH55: 17.59 | AI55: 23.44 | AJ55: 17.71 | AK55: 23.6 | AL55: 17.84 | AM55: 23.77 | AN55: 18.36 | AO55: 24.44 | AP55: 15.32 | AQ55: 21.18 | AR55: 15.41 | AS55: 21.3 | AT55: 15.5 | AU55: 21.43 | AV55: Negativa | AW55: Grupo 2
A56: Natulab | B56: Medicamentos | C56: 7898133130403 | D56: 23892 | E56: 15000094 | F56: Maxalgina 10ml 1ct X 240fr - Farma | G56: 30049069 | H56: ATIVO | I56: 240 | J56: ='LISTA PREÇO 2022-Vigen 01.02.22'!J56 -> 1.14 | L56: 1.02 | M56: =J56/(100%-$M$5) -> 1.373494 | N56: =$M56*(100%-N$6) -> 1.1674699 | O56: =$M56*(100%-O$6) -> 1.1812048 | P56: =$M56*(100%-P$6) -> 1.1949398 | Q56: =$M56*(100%-Q$6) -> 1.2086747 | R56: =$M56*(100%-R$6) -> 1.2224096 | S56: =$M56*(100%-S$6) -> 1.2361446 | T56: =$M56*(100%-T$6) -> 1.2498795 | U56: =$M56*(100%-U$6) -> 1.2636145 | ... X56: =$M56*(100%-X$6) -> 1.373494 | Y56: 0.99 | Z56: 0 | AA56: 1.02376 | AC56: 7.64 | AD56: 6.09 | AE56: 8.17 | AF56: 7.04 | AG56: 9.4 | AH56: 7.53 | AI56: 10.03 | AJ56: 7.58 | AK56: 10.1 | AL56: 7.64 | AM56: 10.18 | AN56: 7.86 | AO56: 10.46 | AP56: 6.56 | AQ56: 9.07 | AR56: 6.6 | AS56: 9.12 | AT56: 6.64 | AU56: 9.18 | AV56: Negativa | AW56: Grupo 2
A57: Natulab | B57: Medicamentos | C57: 7898133131011 | D57: 23906 | E57: 15000095 | F57: Maxalgina 20ml 1ct X 200fr - Farma | G57: 30049069 | H57: ATIVO | I57: 200 | J57: ='LISTA PREÇO 2022-Vigen 01.02.22'!J57 -> 1.76 | L57: 1.6 | M57: =J57/(100%-$M$5) -> 2.1204819 | N57: =$M57*(100%-N$6) -> 1.8024096 | O57: =$M57*(100%-O$6) -> 1.8236145 | P57: =$M57*(100%-P$6) -> 1.8448193 | Q57: =$M57*(100%-Q$6) -> 1.8660241 | R57: =$M57*(100%-R$6) -> 1.8872289 | S57: =$M57*(100%-S$6) -> 1.9084337 | T57: =$M57*(100%-T$6) -> 1.9296386 | U57: =$M57*(100%-U$6) -> 1.9508434 | ... X57: =$M57*(100%-X$6) -> 2.1204819 | Y57: 1.49 | Z57: 1.651 | AA57: 1.6497 | AC57: 12.69 | AD57: 10.12 | AE57: 13.57 | AF57: 11.7 | AG57: 15.62 | AH57: 12.51 | AI57: 16.67 | AJ57: 12.6 | AK57: 16.79 | AL57: 12.69 | AM57: 16.91 | AN57: 13.06 | AO57: 17.38 | AP57: 10.89 | AQ57: 15.06 | AR57: 10.96 | AS57: 15.15 | AT57: 11.03 | AU57: 15.25 | AV57: Negativa | AW57: Grupo 2
A58: Natulab | B58: Medicamentos | C58: 7899470804576 | D58: 34071 | E58: 15000191 | F58: Maxalgina 500mg 3bl X 10com X 100ct - Farma | G58: 30049069 | H58: ATIVO | I58: 100 | J58: ='LISTA PREÇO 2022-Vigen 01.02.22'!J58 -> 4.23 | L58: 4.15 | M58: =J58/(100%-$M$5) -> 5.0963855 | N58: =$M58*(100%-N$6) -> 4.3319277 | O58: =$M58*(100%-O$6) -> 4.3828916 | P58: =$M58*(100%-P$6) -> 4.4338554 | Q58: =$M58*(100%-Q$6) -> 4.4848193 | R58: =$M58*(100%-R$6) -> 4.5357831 | S58: =$M58*(100%-S$6) -> 4.586747 | T58: =$M58*(100%-T$6) -> 4.6377108 | U58: =$M58*(100%-U$6) -> 4.6886747 | ... X58: =$M58*(100%-X$6) -> 5.0963855 | Y58: 0 | Z58: 0 | AA58: 4.01191 | AC58: 15.49 | AD58: 12.36 | AE58: 16.58 | AF58: 14.28 | AG58: 19.07 | AH58: 15.27 | AI58: 20.35 | AJ58: 15.38 | AK58: 20.49 | AL58: 15.49 | AM58: 20.64 | AN58: 15.94 | AO58: 21.22 | AP58: 13.3 | AQ58: 18.39 | AR58: 13.38 | AS58: 18.5 | AT58: 13.46 | AU58: 18.61 | AV58: Negativa | AW58: Grupo 2
A59: Natulab | B59: Medicamentos | C59: 7898133138751 | D59: 23916 | E59: 15000097 | F59: Maxalgina C/Seringa 100ml 1ct X 50fr - Farma | G59: 30049069 | H59: ATIVO | I59: 50 | J59: ='LISTA PREÇO 2022-Vigen 01.02.22'!J59 -> 3.6 | L59: 0 | M59: =J59/(100%-$M$5) -> 4.3373494 | N59: =$M59*(100%-N$6) -> 3.686747 | O59: =$M59*(100%-O$6) -> 3.7301205 | P59: =$M59*(100%-P$6) -> 3.773494 | Q59: =$M59*(100%-Q$6) -> 3.8168675 | R59: =$M59*(100%-R$6) -> 3.860241 | S59: =$M59*(100%-S$6) -> 3.9036145 | T59: =$M59*(100%-T$6) -> 3.946988 | U59: =$M59*(100%-U$6) -> 3.9903614 | ... X59: =$M59*(100%-X$6) -> 4.3373494 | Y59: 0 | Z59: 0 | AA59: 3.75066 | AC59: 18.66 | AD59: 14.89 | AE59: 19.97 | AF59: 17.2 | AG59: 22.97 | AH59: 18.4 | AI59: 24.52 | AJ59: 18.53 | AK59: 24.69 | AL59: 18.66 | AM59: 24.86 | AN59: 19.2 | AO59: 25.56 | AP59: 16.02 | AQ59: 22.15 | AR59: 16.12 | AS59: 22.29 | AT59: 16.21 | AU59: 22.41 | AV59: Negativa | AW59: Grupo 2
... A74: Natulab | B74: Medicamentos | C74: 7899470806020 | D74: 36393 | E74: 15000193 | F74: Pausefemme 150mg 3bl X 10com X 50ct - Farma | G74: 30049099 | H74: ATIVO | I74: 50 | J74: ='LISTA PREÇO 2022-Vigen 01.02.22'!J74 -> 27.41 | L74: 21 | M74: =J74/(100%-$M$5) -> 33.024096 | N74: =$M74*(100%-N$6) -> 28.070482 | O74: =$M74*(100%-O$6) -> 28.400723 | P74: =$M74*(100%-P$6) -> 28.730964 | Q74: =$M74*(100%-Q$6) -> 29.061205 | R74: =$M74*(100%-R$6) -> 29.391446 | S74: =$M74*(100%-S$6) -> 29.721687 | T74: =$M74*(100%-T$6) -> 30.051928 | U74: =$M74*(100%-U$6) -> 30.382169 | ... X74: =$M74*(100%-X$6) -> 33.024096 | Y74: 0 | Z74: 0 | AA74: 0 | AC74: 81.32 | AD74: 64.89 | AE74: 87.04 | AF74: 74.99 | AG74: 100.17 | AH74: 80.19 | AI74: 106.88 | AJ74: 80.75 | AK74: 107.6 | AL74: 81.32 | AM74: 108.34 | AN74: 83.67 | AO74: 111.37 | AP74: 69.81 | AQ74: 96.51 | AR74: 70.23 | AS74: 97.09 | AT74: 70.66 | AU74: 97.68 | AV74: Negativa | AW74: Grupo 2
A75: Natulab | B75: Medicamentos | C75: 7899470803104 | D75: 24038 | E75: 15000176 | F75: Plantolaxy 5g 10env X 50ct - Farma | G75: 30049099 | H75: ATIVO | I75: 50 | J75: ='LISTA PREÇO 2022-Vigen 01.02.22'!J75 -> 11.99 | M75: =J75/(100%-$M$5) -> 14.445783 | N75: =$M75*(100%-N$6) -> 12.278916 | O75: =$M75*(100%-O$6) -> 12.423373 | P75: =$M75*(100%-P$6) -> 12.567831 | Q75: =$M75*(100%-Q$6) -> 12.712289 | R75: =$M75*(100%-R$6) -> 12.856747 | S75: =$M75*(100%-S$6) -> 13.001205 | T75: =$M75*(100%-T$6) -> 13.145663 | U75: =$M75*(100%-U$6) -> 13.29012 | ... X75: =$M75*(100%-X$6) -> 14.445783 | Y75: 0 | Z75: 0 | AA75: 0 | AC75: 42.22 | AD75: 33.69 | AE75: 45.19 | AF75: 38.93 | AG75: 52 | AH75: 41.63 | AI75: 55.49 | AJ75: 41.92 | AK75: 55.86 | AL75: 42.22 | AM75: 56.25 | AN75: 43.44 | AO75: 57.82 | AP75: 36.24 | AQ75: 50.1 | AR75: 36.46 | AS75: 50.4 | AT75: 36.69 | AU75: 50.72 | AV75: Negativa | AW75: Grupo 2
A76: Natulab | B76: Medicamentos | C76: 7898133131066 | D76: 23974 | E76: 15000102 | F76: Polaradex 100ml 1ct X 50fr - Farma | G76: 30049069 | H76: ATIVO | I76: 50 | J76: ='LISTA PREÇO 2022-Vigen 01.02.22'!J76 -> 2.53 | L76: 2.4852762 | M76: =J76/(100%-$M$5) -> 3.0481928 | N76: =$M76*(100%-N$6) -> 2.5909639 | O76: =$M76*(100%-O$6) -> 2.6214458 | P76: =$M76*(100%-P$6) -> 2.6519277 | Q76: =$M76*(100%-Q$6) -> 2.6824096 | R76: =$M76*(100%-R$6) -> 2.7128916 | S76: =$M76*(100%-S$6) -> 2.7433735 | T76: =$M76*(100%-T$6) -> 2.7738554 | U76: =$M76*(100%-U$6) -> 2.8043373 | ... X76: =$M76*(100%-X$6) -> 3.0481928 | Y76: 2.38 | Z76: 0 | AA76: 0 | AC76: 12.23 | AD76: 9.76 | AE76: 13.09 | AF76: 11.27 | AG76: 15.05 | AH76: 12.06 | AI76: 16.07 | AJ76: 12.14 | AK76: 16.17 | AL76: 12.23 | AM76: 16.29 | AN76: 12.58 | AO76: 16.74 | AP76: 10.5 | AQ76: 14.52 | AR76: 10.56 | AS76: 14.6 | AT76: 10.63 | AU76: 14.7 | AV76: Negativa | AW76: Grupo 3
A77: Natulab | B77: Medicamentos | C77: 7898133137457 | D77: 23982 | E77: 15000103 | F77: Pvpi Spray 100ml 1 X 50fr - Farma | G77: 30049099 | H77: ATIVO | I77: 50 | J77: ='LISTA PREÇO 2022-Vigen 01.02.22'!J77 -> 6.72 | L77: 6.6 | M77: =J77/(100%-$M$5) -> 8.0963855 | N77: =$M77*(100%-N$6) -> 6.8819277 | O77: =$M77*(100%-O$6) -> 6.9628916 | P77: =$M77*(100%-P$6) -> 7.0438554 | Q77: =$M77*(100%-Q$6) -> 7.1248193 | R77: =$M77*(100%-R$6) -> 7.2057831 | S77: =$M77*(100%-S$6) -> 7.286747 | T77: =$M77*(100%-T$6) -> 7.3677108 | U77: =$M77*(100%-U$6) -> 7.4486747 | ... X77: =$M77*(100%-X$6) -> 8.0963855 | Y77: 0 | Z77: 0 | AA77: 0 | AC77: 25.64 | AD77: 20.46 | AE77: 27.44 | AF77: 23.64 | AG77: 31.57 | AH77: 25.28 | AI77: 33.69 | AJ77: 25.46 | AK77: 33.92 | AL77: 25.64 | AM77: 34.16 | AN77: 26.38 | AO77: 35.11 | AP77: 22.01 | AQ77: 30.43 | AR77: 22.14 | AS77: 30.61 | AT77: 22.28 | AU77: 30.8 | AV77: Negativa | AW77: Grupo 1
A78: Natulab | B78: Medicamentos | C78: 7898133134784 | D78: 34671 | E78: 15000134 | F78: Rifotrat Spray 20ml 1ct X 50fr - Farma | G78: 30042031 | H78: ATIVO | I78: 50 | J78: ='LISTA PREÇO 2022-Vigen 01.02.22'!J78 -> 3.95 | L78: 3.85 | M78: =J78/(100%-$M$5) -> 4.7590361 | N78: =$M78*(100%-N$6) -> 4.0451807 | O78: =$M78*(100%-O$6) -> 4.0927711 | P78: =$M78*(100%-P$6) -> 4.1403614 | Q78: =$M78*(100%-Q$6) -> 4.1879518 | R78: =$M78*(100%-R$6) -> 4.2355422 | S78: =$M78*(100%-S$6) -> 4.2831325 | T78: =$M78*(100%-T$6) -> 4.3307229 | U78: =$M78*(100%-U$6) -> 4.3783133 | ... X78: =$M78*(100%-X$6) -> 4.7590361 | Y78: 3.22 | Z78: 4.7 | AA78: 4.9914 | AC78: 17.7 | AD78: 14.51 | AE78: 20.05 | AF78: 16.49 | AG78: 22.79 | AH78: 17.48 | AI78: 24.16 | AJ78: 17.59 | AK78: 24.31 | AL78: 17.7 | AM78: 24.47 | AN78: 18.14 | AO78: 25.08 | AP78: 17.49 | AQ78: 24.18 | AR78: 17.59 | AS78: 24.32 | AT78: 17.7 | AU78: 24.47 | AV78: Positiva | AW78: Grupo 3
A79: Natulab | B79: Medicamentos | C79: 7898133136047 | D79: 24694 | E79: 15000187 | F79: Seakalm 260mg 2bl X 10com X 50ct - Farma | G79: 30049099 | H79: ATIVO | I79: 50 | J79: ='LISTA PREÇO 2022-Vigen 01.02.22'!J79 -> 8.1 | L79: 7.95 | M79: =J79/(100%-$M$5) -> 9.7590361 | N79: =$M79*(100%-N$6) -> 8.2951807 | O79: =$M79*(100%-O$6) -> 8.3927711 | P79: =$M79*(100%-P$6) -> 8.4903614 | Q79: =$M79*(100%-Q$6) -> 8.5879518 | R79: =$M79*(100%-R$6) -> 8.6855422 | S79: =$M79*(100%-S$6) -> 8.7831325 | T79: =$M79*(100%-T$6) -> 8.8807229 | U79: =$M79*(100%-U$6) -> 8.9783133 | ... X79: =$M79*(100%-X$6) -> 9.7590361 | Y79: 7.72 | Z79: 13.6641 | AA79: 11.92839 | AC79: 36.93 | AD79: 29.47 | AE79: 39.53 | AF79: 34.05 | AG79: 45.48 | AH79: 36.41 | AI79: 48.53 | AJ79: 36.67 | AK79: 48.86 | AL79: 36.93 | AM79: 49.2 | AN79: 38 | AO79: 50.58 | AP79: 31.7 | AQ79: 43.82 | AR79: 31.9 | AS79: 44.1 | AT79: 32.09 | AU79: 44.36 | AV79: Negativa | AW79: Grupo 1
A80: Natulab | B80: Medicamentos | C80: 7899470800882 | D80: 23994 | E80: 15000106 | F80: Seakalm Solucao 90mg 100ml 1ct X 50fr - Farma | G80: 30049099 | H80: ATIVO | I80: 50 | J80: ='LISTA PREÇO 2022-Vigen 01.02.22'!J80 -> 9.89 | L80: 9.7 | M80: =J80/(100%-$M$5) -> 11.915663 | N80: =$M80*(100%-N$6) -> 10.128313 | O80: =$M80*(100%-O$6) -> 10.24747 | P80: =$M80*(100%-P$6) -> 10.366627 | Q80: =$M80*(100%-Q$6) -> 10.485783 | R80: =$M80*(100%-R$6) -> 10.60494 | S80: =$M80*(100%-S$6) -> 10.724096 | T80: =$M80*(100%-T$6) -> 10.843253 | U80: =$M80*(100%-U$6) -> 10.96241 | ... X80: =$M80*(100%-X$6) -> 11.915663 | Y80: 9.42 | Z80: 15.9495 | AA80: 12.70815 | AC80: 51.45 | AD80: 41.05 | AE80: 55.06 | AF80: 47.44 | AG80: 63.37 | AH80: 50.73 | AI80: 67.61 | AJ80: 51.09 | AK80: 68.08 | AL80: 51.45 | AM80: 68.55 | AN80: 52.94 | AO80: 70.47 | AP80: 44.17 | AQ80: 61.06 | AR80: 44.44 | AS80: 61.44 | AT80: 44.71 | AU80: 61.81 | AV80: Negativa | AW80: Grupo 1
A81: Natulab | B81: Medicamentos | C81: 7898133135163 | D81: 24054 | E81: 15000177 | F81: Starfor C 1tb X 10com X 100ct - Farma | G81: 30045090 | H81: ATIVO | I81: 100 | J81: ='LISTA PREÇO 2022-Vigen 01.02.22'!J81 -> 6.92 | M81: =J81/(100%-$M$5) -> 8.3373494 | N81: =$M81*(100%-N$6) -> 7.086747 | O81: =$M81*(100%-O$6) -> 7.1701205 | P81: =$M81*(100%-P$6) -> 7.253494 | Q81: =$M81*(100%-Q$6) -> 7.3368675 | R81: =$M81*(100%-R$6) -> 7.420241 | S81: =$M81*(100%-S$6) -> 7.5036145 | T81: =$M81*(100%-T$6) -> 7.586988 | U81: =$M81*(100%-U$6) -> 7.6703614 | ... X81: =$M81*(100%-X$6) -> 8.3373494 | Y81: 6.59 | Z81: 11.4205 | AA81: 0 | AC81: 32.63 | AD81: 26.03 | AE81: 34.91 | AF81: 30.09 | AG81: 40.19 | AH81: 32.17 | AI81: 42.88 | AJ81: 32.4 | AK81: 43.17 | AL81: 32.63 | AM81: 43.47 | AN81: 33.58 | AO81: 44.7 | AP81: 28.01 | AQ81: 38.72 | AR81: 28.18 | AS81: 38.96 | AT81: 28.35 | AU81: 39.19 | AV81: Negativa | AW81: Grupo 2
A82: Natulab | B82: Medicamentos | C82: 7898133131509 | D82: 23996 | E82: 15000107 | F82: Tylemax Baby 15ml 1ct X 100fr - Farma | G82: 30049045 | H82: ATIVO | I82: 100 | J82: ='LISTA PREÇO 2022-Vigen 01.02.22'!J82 -> 3.38 | L82: 3.29 | M82: =J82/(100%-$M$5) -> 4.0722892 | N82: =$M82*(100%-N$6) -> 3.4614458 | O82: =$M82*(100%-O$6) -> 3.5021687 | P82: =$M82*(100%-P$6) -> 3.5428916 | Q82: =$M82*(100%-Q$6) -> 3.5836145 | R82: =$M82*(100%-R$6) -> 3.6243373 | S82: =$M82*(100%-S$6) -> 3.6650602 | T82: =$M82*(100%-T$6) -> 3.7057831 | U82: =$M82*(100%-U$6) -> 3.746506 | ... X82: =$M82*(100%-X$6) -> 4.0722892 | Y82: 3.19 | Z82: 0 | AA82: 0 | AC82: 25.81 | AD82: 20.59 | AE82: 27.62 | AF82: 23.8 | AG82: 31.79 | AH82: 25.45 | AI82: 33.92 | AJ82: 25.63 | AK82: 34.15 | AL82: 25.81 | AM82: 34.39 | AN82: 26.56 | AO82: 35.35 | AP82: 22.16 | AQ82: 30.64 | AR82: 22.29 | AS82: 30.82 | AT82: 22.43 | AU82: 31.01 | AV82: Negativa | AW82: Grupo 2
A83: Natulab | B83: Medicamentos | C83: 7898133130410 | D83: 24016 | E83: 15000109 | F83: Tylemax 15ml 1ct X 200fr - Farma | G83: 30049045 | H83: ATIVO | I83: 200 | J83: ='LISTA PREÇO 2022-Vigen 01.02.22'!J83 -> 1.53 | L83: 1.37 | M83: =J83/(100%-$M$5) -> 1.8433735 | N83: =$M83*(100%-N$6) -> 1.5668675 | O83: =$M83*(100%-O$6) -> 1.5853012 | P83: =$M83*(100%-P$6) -> 1.6037349 | Q83: =$M83*(100%-Q$6) -> 1.6221687 | R83: =$M83*(100%-R$6) -> 1.6406024 | S83: =$M83*(100%-S$6) -> 1.6590361 | T83: =$M83*(100%-T$6) -> 1.6774699 | U83: =$M83*(100%-U$6) -> 1.6959036 | ... X83: =$M83*(100%-X$6) -> 1.8433735 | Y83: 1.04 | Z83: 3.9849 | AA83: 0 | AC83: 10.77 | AD83: 8.59 | AE83: 11.52 | AF83: 9.93 | AG83: 13.26 | AH83: 10.62 | AI83: 14.15 | AJ83: 10.69 | AK83: 14.24 | AL83: 10.77 | AM83: 14.35 | AN83: 11.08 | AO83: 14.75 | AP83: 9.25 | AQ83: 12.79 | AR83: 9.3 | AS83: 12.86 | AT83: 9.36 | AU83: 12.94 | AV83: Negativa | AW83: Grupo 2
A84: Natulab | B84: Medicamentos | C84: 7898133137471 | D84: 24009 | E84: 15000108 | F84: Tylemax Crianca 60ml 1ct X 100fr - Farma | G84: 30049045 | H84: ATIVO | I84: 100 | J84: ='LISTA PREÇO 2022-Vigen 01.02.22'!J84 -> 3.23 | L84: 3.17 | M84: =J84/(100%-$M$5) -> 3.8915663 | N84: =$M84*(100%-N$6) -> 3.3078313 | O84: =$M84*(100%-O$6) -> 3.346747 | P84: =$M84*(100%-P$6) -> 3.3856627 | Q84: =$M84*(100%-Q$6) -> 3.4245783 | R84: =$M84*(100%-R$6) -> 3.463494 | S84: =$M84*(100%-S$6) -> 3.5024096 | T84: =$M84*(100%-T$6) -> 3.5413253 | U84: =$M84*(100%-U$6) -> 3.580241 | ... X84: =$M84*(100%-X$6) -> 3.8915663 | Y84: 0 | Z84: 0 | AA84: 0 | AC84: 20 | AD84: 15.96 | AE84: 21.41 | AF84: 18.44 | AG84: 24.63 | AH84: 19.72 | AI84: 26.28 | AJ84: 19.86 | AK84: 26.46 | AL84: 20 | AM84: 26.65 | AN84: 20.58 | AO84: 27.39 | AP84: 17.17 | AQ84: 23.74 | AR84: 17.27 | AS84: 23.88 | AT84: 17.38 | AU84: 24.03 | AV84: Negativa | AW84: Grupo 2
A85: Natulab | B85: Medicamentos | C85: 7899470805221 | D85: 24020 | E85: 15000110 | F85: Unhagold 30ml 1ct X 100fr - Farma | G85: 30049029 | H85: ATIVO | I85: 100 | J85: ='LISTA PREÇO 2022-Vigen 01.02.22'!J85 -> 9.05 | L85: 8.87 | M85: =J85/(100%-$M$5) -> 10.903614 | N85: =$M85*(100%-N$6) -> 9.2680723 | O85: =$M85*(100%-O$6) -> 9.3771084 | P85: =$M85*(100%-P$6) -> 9.4861446 | Q85: =$M85*(100%-Q$6) -> 9.5951807 | R85: =$M85*(100%-R$6) -> 9.7042169 | S85: =$M85*(100%-S$6) -> 9.813253 | T85: =$M85*(100%-T$6) -> 9.9222892 | U85: =$M85*(100%-U$6) -> 10.031325 | ... X85: =$M85*(100%-X$6) -> 10.903614 | Y85: 8.62 | Z85: 0 | AA85: 0 | AC85: 63.4 | AD85: 50.59 | AE85: 67.86 | AF85: 58.46 | AG85: 78.09 | AH85: 62.52 | AI85: 83.33 | AJ85: 62.95 | AK85: 83.88 | AL85: 63.4 | AM85: 84.47 | AN85: 65.24 | AO85: 86.84 | AP85: 54.43 | AQ85: 75.25 | AR85: 54.76 | AS85: 75.7 | AT85: 55.09 | AU85: 76.16 | AV85: Negativa | AW85: Grupo 1
A86: Natulab | B86: Medicamentos | C86: 7898133137242 | D86: 24058 | E86: 15000178 | F86: Valessone 225.75mg 2bl X 10com X 50ct - Farma | G86: 30045090 | H86: ATIVO | I86: 50 | J86: ='LISTA PREÇO 2022-Vigen 01.02.22'!J86 -> 7.33 | L86: 7.19 | M86: =J86/(100%-$M$5) -> 8.8313253 | N86: =$M86*(100%-N$6) -> 7.5066265 | O86: =$M86*(100%-O$6) -> 7.5949398 | P86: =$M86*(100%-P$6) -> 7.683253 | Q86: =$M86*(100%-Q$6) -> 7.7715663 | R86: =$M86*(100%-R$6) -> 7.8598795 | S86: =$M86*(100%-S$6) -> 7.9481928 | T86: =$M86*(100%-T$6) -> 8.036506 | U86: =$M86*(100%-U$6) -> 8.1248193 | ... X86: =$M86*(100%-X$6) -> 8.8313253 | Y86: 6.98 | Z86: 23.7875 | AA86: 8.52 | AC86: 43.25 | AD86: 34.51 | AE86: 46.29 | AF86: 39.88 | AG86: 53.27 | AH86: 42.65 | AI86: 56.84 | AJ86: 42.94 | AK86: 57.22 | AL86: 43.25 | AM86: 57.62 | AN86: 44.5 | AO86: 59.23 | AP86: 37.13 | AQ86: 51.33 | AR86: 37.35 | AS86: 51.63 | AT86: 37.58 | AU86: 51.95 | AV86: Negativa | AW86: Grupo 2
A87: Natulab | B87: Medicamentos | C87: 7898133136450 | D87: 24061 | E87: 15000179 | F87: Varivax 100mg 3bl X 10com X 50ct - Farma | G87: 30049099 | H87: ATIVO | I87: 50 | J87: ='LISTA PREÇO 2022-Vigen 01.02.22'!J87 -> 7.65 | L87: 7.42 | M87: =J87/(100%-$M$5) -> 9.2168675 | N87: =$M87*(100%-N$6) -> 7.8343373 | O87: =$M87*(100%-O$6) -> 7.926506 | P87: =$M87*(100%-P$6) -> 8.0186747 | Q87: =$M87*(100%-Q$6) -> 8.1108434 | R87: =$M87*(100%-R$6) -> 8.203012 | S87: =$M87*(100%-S$6) -> 8.2951807 | T87: =$M87*(100%-T$6) -> 8.3873494 | U87: =$M87*(100%-U$6) -> 8.4795181 | ... X87: =$M87*(100%-X$6) -> 9.2168675 | Y87: 6.92 | Z87: 17.9648 | AA87: 11.35632 | AC87: 64.16 | AD87: 51.2 | AE87: 68.68 | AF87: 59.16 | AG87: 79.02 | AH87: 63.27 | AI87: 84.33 | AJ87: 63.71 | AK87: 84.9 | AL87: 64.16 | AM87: 85.48 | AN87: 66.02 | AO87: 87.88 | AP87: 55.08 | AQ87: 76.15 | AR87: 55.41 | AS87: 76.6 | AT87: 55.75 | AU87: 77.07 | AV87: Negativa | AW87: Grupo 2
A88: Natulab | B88: Medicamentos | C88: 7899470803975 | D88: 24065 | E88: 15000180 | F88: Varivax 300mg 3bl X 10com X 50ct - Farma | G88: 30049099 | H88: ATIVO | I88: 50 | J88: ='LISTA PREÇO 2022-Vigen 01.02.22'!J88 -> 10.8 | L88: 10.59 | M88: =J88/(100%-$M$5) -> 13.012048 | N88: =$M88*(100%-N$6) -> 11.060241 | O88: =$M88*(100%-O$6) -> 11.190361 | P88: =$M88*(100%-P$6) -> 11.320482 | Q88: =$M88*(100%-Q$6) -> 11.450602 | R88: =$M88*(100%-R$6) -> 11.580723 | S88: =$M88*(100%-S$6) -> 11.710843 | T88: =$M88*(100%-T$6) -> 11.840964 | U88: =$M88*(100%-U$6) -> 11.971084 | ... X88: =$M88*(100%-X$6) -> 13.012048 | Y88: 10.09 | Z88: 19.348 | AA88: 15.6857 | AC88: 69.1 | AD88: 55.14 | AE88: 73.96 | AF88: 63.72 | AG88: 85.11 | AH88: 68.14 | AI88: 90.82 | AJ88: 68.61 | AK88: 91.43 | AL88: 69.1 | AM88: 92.06 | AN88: 71.1 | AO88: 94.64 | AP88: 59.32 | AQ88: 82.01 | AR88: 59.68 | AS88: 82.5 | AT88: 60.04 | AU88: 83 | AV88: Negativa | AW88: Grupo 2
A89: Natulab | B89: Medicamentos | C89: 7898133135606 | D89: 24068 | E89: 15000181 | F89: Vitamin E 400mg 1fr X 30cap X 50ct - Farma | G89: 30049099 | H89: ATIVO | I89: 50 | J89: ='LISTA PREÇO 2022-Vigen 01.02.22'!J89 -> 7.87 | L89: 7.72 | M89: =J89/(100%-$M$5) -> 9.4819277 | N89: =$M89*(100%-N$6) -> 8.0596386 | O89: =$M89*(100%-O$6) -> 8.1544578 | P89: =$M89*(100%-P$6) -> 8.2492771 | Q89: =$M89*(100%-Q$6) -> 8.3440964 | R89: =$M89*(100%-R$6) -> 8.4389157 | S89: =$M89*(100%-S$6) -> 8.5337349 | T89: =$M89*(100%-T$6) -> 8.6285542 | U89: =$M89*(100%-U$6) -> 8.7233735 | ... X89: =$M89*(100%-X$6) -> 9.4819277 | Y89: 0 | Z89: 8.0604 | AA89: 0 | AC89: 44.78 | AD89: 35.73 | AE89: 47.93 | AF89: 41.29 | AG89: 55.15 | AH89: 44.15 | AI89: 58.84 | AJ89: 44.46 | AK89: 59.24 | AL89: 44.78 | AM89: 59.66 | AN89: 46.08 | AO89: 61.33 | AP89: 38.44 | AQ89: 53.14 | AR89: 38.67 | AS89: 53.46 | AT89: 38.91 | AU89: 53.79 | AV89: Negativa | AW89: Grupo 2
A90: Natulab | B90: Medicamentos | C90: 7899470800325 | D90: 24099 | E90: 15000185 | F90: Viter C + Zinco Efervescente 1tb X 10com X 100ct - Farma | G90: 30045090 | H90: ATIVO | I90: 100 | J90: ='LISTA PREÇO 2022-Vigen 01.02.22'!J90 -> 5.13 | M90: =J90/(100%-$M$5) -> 6.1807229 | N90: =$M90*(100%-N$6) -> 5.2536145 | O90: =$M90*(100%-O$6) -> 5.3154217 | P90: =$M90*(100%-P$6) -> 5.3772289 | Q90: =$M90*(100%-Q$6) -> 5.4390361 | R90: =$M90*(100%-R$6) -> 5.5008434 | S90: =$M90*(100%-S$6) -> 5.5626506 | T90: =$M90*(100%-T$6) -> 5.6244578 | U90: =$M90*(100%-U$6) -> 5.6862651 | ... X90: =$M90*(100%-X$6) -> 6.1807229 | Y90: 4.79 | Z90: 0 | AA90: 0 | AC90: 25.97 | AD90: 20.72 | AE90: 27.79 | AF90: 23.94 | AG90: 31.97 | AH90: 25.61 | AI90: 34.13 | AJ90: 25.78 | AK90: 34.35 | AL90: 25.97 | AM90: 34.6 | AN90: 26.72 | AO90: 35.57 | AP90: 22.29 | AQ90: 30.82 | AR90: 22.43 | AS90: 31.01 | AT90: 22.57 | AU90: 31.2 | AV90: Negativa | AW90: Grupo 2
A91: Natulab | B91: Medicamentos | C91: 7898133136481 | D91: 24069 | E91: 15000182 | F91: Viter C Comprimidos 500mg 2bl X 10com X 100ct - Farma | G91: 30045090 | H91: ATIVO | I91: 100 | J91: ='LISTA PREÇO 2022-Vigen 01.02.22'!J91 -> 3.46 | L91: 3.39 | M91: =J91/(100%-$M$5) -> 4.1686747 | N91: =$M91*(100%-N$6) -> 3.5433735 | O91: =$M91*(100%-O$6) -> 3.5850602 | P91: =$M91*(100%-P$6) -> 3.626747 | Q91: =$M91*(100%-Q$6) -> 3.6684337 | R91: =$M91*(100%-R$6) -> 3.7101205 | S91: =$M91*(100%-S$6) -> 3.7518072 | T91: =$M91*(100%-T$6) -> 3.793494 | U91: =$M91*(100%-U$6) -> 3.8351807 | ... X91: =$M91*(100%-X$6) -> 4.1686747 | Y91: 3.29 | Z91: 6.7456 | AA91: 7.378 | AC91: 21.08 | AD91: 16.82 | AE91: 22.56 | AF91: 19.43 | AG91: 25.95 | AH91: 20.78 | AI91: 27.69 | AJ91: 20.93 | AK91: 27.89 | AL91: 21.08 | AM91: 28.09 | AN91: 21.69 | AO91: 28.87 | AP91: 18.1 | AQ91: 25.02 | AR91: 18.21 | AS91: 25.17 | AT91: 18.32 | AU91: 25.33 | AV91: Negativa | AW91: Grupo 2
A92: Natulab | B92: Medicamentos | C92: 7899470800240 | D92: 24096 | E92: 15000183 | F92: Viter C Efervescente 1g 1tb X 10com X 100ct - Farma | G92: 30045090 | H92: ATIVO | I92: 100 | J92: ='LISTA PREÇO 2022-Vigen 01.02.22'!J92 -> 3.89 | M92: =J92/(100%-$M$5) -> 4.686747 | N92: =$M92*(100%-N$6) -> 3.9837349 | O92: =$M92*(100%-O$6) -> 4.0306024 | P92: =$M92*(100%-P$6) -> 4.0774699 | Q92: =$M92*(100%-Q$6) -> 4.1243373 | R92: =$M92*(100%-R$6) -> 4.1712048 | S92: =$M92*(100%-S$6) -> 4.2180723 | T92: =$M92*(100%-T$6) -> 4.2649398 | U92: =$M92*(100%-U$6) -> 4.3118072 | ... X92: =$M92*(100%-X$6) -> 4.686747 | Y92: 3.02 | Z92: 4.4229 | AA92: 4.6152 | AC92: 19.23 | AD92: 15.34 | AE92: 20.57 | AF92: 17.73 | AG92: 23.68 | AH92: 18.96 | AI92: 25.27 | AJ92: 19.09 | AK92: 25.44 | AL92: 19.23 | AM92: 25.62 | AN92: 19.79 | AO92: 26.34 | AP92: 16.51 | AQ92: 22.82 | AR92: 16.61 | AS92: 22.96 | AT92: 16.71 | AU92: 23.1 | AV92: Negativa | AW92: Grupo 2
A93: Natulab | B93: Medicamentos | C93: 7899470802961 | D93: 28916 | E93: 15000125 | F93: Xarope De Guaco S/Acucar 100ml 1ct X 50fr - Farma | G93: 30049099 | H93: ATIVO | I93: 50 | J93: ='LISTA PREÇO 2022-Vigen 01.02.22'!J93 -> 2.92 | L93: 2.86 | M93: =J93/(100%-$M$5) -> 3.5180723 | N93: =$M93*(100%-N$6) -> 2.9903614 | O93: =$M93*(100%-O$6) -> 3.0255422 | P93: =$M93*(100%-P$6) -> 3.0607229 | Q93: =$M93*(100%-Q$6) -> 3.0959036 | R93: =$M93*(100%-R$6) -> 3.1310843 | S93: =$M93*(100%-S$6) -> 3.1662651 | T93: =$M93*(100%-T$6) -> 3.2014458 | U93: =$M93*(100%-U$6) -> 3.2366265 | ... X93: =$M93*(100%-X$6) -> 3.5180723 | Y93: 0 | Z93: 0 | AA93: 0 | AC93: 29.57 | AD93: 23.59 | AE93: 31.64 | AF93: 27.26 | AG93: 36.41 | AH93: 29.16 | AI93: 38.86 | AJ93: 29.36 | AK93: 39.12 | AL93: 29.57 | AM93: 39.4 | AN93: 30.43 | AO93: 40.5 | AP93: 25.38 | AQ93: 35.09 | AR93: 25.54 | AS93: 35.31 | AT93: 25.69 | AU93: 35.52 | AV93: Negativa | AW93: Grupo 1
A94: Natulab | B94: Medicamentos | C94: 7898133131837 | D94: 24104 | E94: 15000112 | F94: Xarope De Guaco S/Acucar 150ml 1ct X 50fr - Farma | G94: 30049099 | H94: ATIVO | I94: 50 | J94: ='LISTA PREÇO 2022-Vigen 01.02.22'!J94 -> 4.93 | L94: 4.83 | M94: =J94/(100%-$M$5) -> 5.939759 | N94: =$M94*(100%-N$6) -> 5.0487952 | O94: =$M94*(100%-O$6) -> 5.1081928 | P94: =$M94*(100%-P$6) -> 5.1675904 | Q94: =$M94*(100%-Q$6) -> 5.226988 | R94: =$M94*(100%-R$6) -> 5.2863855 | S94: =$M94*(100%-S$6) -> 5.3457831 | T94: =$M94*(100%-T$6) -> 5.4051807 | U94: =$M94*(100%-U$6) -> 5.4645783 | ... X94: =$M94*(100%-X$6) -> 5.939759 | Y94: 4.69 | Z94: 10.038 | AA94: 0 | AC94: 33.46 | AD94: 26.7 | AE94: 35.81 | AF94: 30.85 | AG94: 41.2 | AH94: 32.99 | AI94: 43.97 | AJ94: 33.22 | AK94: 44.27 | AL94: 33.46 | AM94: 44.58 | AN94: 34.43 | AO94: 45.83 | AP94: 28.72 | AQ94: 39.7 | AR94: 28.9 | AS94: 39.95 | AT94: 29.07 | AU94: 40.19 | AV94: Negativa | AW94: Grupo 1
A95: Naturelife | B95: Alimentos | C95: 7899898601481 | D95: 21835 | E95: 15000257 | F95: CALCIOVITAL B12 SUS OR X 250ML | G95: 30045090 | H95: ATIVO | I95: 36 | J95: ='LISTA PREÇO 2022-Vigen 01.02.22'!J95 -> 5.2 | L95: 5.25 | M95: =J95/(100%-$M$5) -> 6.2650602 | N95: =$M95*(100%-N$6) -> 5.3253012 | O95: =$M95*(100%-O$6) -> 5.3879518 | P95: =$M95*(100%-P$6) -> 5.4506024 | Q95: =$M95*(100%-Q$6) -> 5.513253 | R95: =$M95*(100%-R$6) -> 5.5759036 | S95: =$M95*(100%-S$6) -> 5.6385542 | T95: =$M95*(100%-T$6) -> 5.7012048 | U95: =$M95*(100%-U$6) -> 5.7638554 | ... X95: =$M95*(100%-X$6) -> 6.2650602 | Y95: 0 | Z95: 0 | AA95: 0 | AC95: 25.42 | AD95: 20.42 | AE95: 27.58 | AF95: 23.5 | AG95: 31.64 | AH95: 25.07 | AI95: 33.7 | AJ95: 25.24 | AK95: 33.92 | AL95: 25.42 | AM95: 34.16 | AN95: 26.13 | AO95: 35.09 | AP95: 22.59 | AQ95: 31.23 | AR95: 22.72 | AS95: 31.41 | AT95: 22.86 | AU95: 31.6 | AV95: Neutra | AW95: NÃO SE APLICA - LIBERADOS
A96: Naturelife | B96: Alimentos | C96: 7899898601146 | D96: 208 | E96: 15000253 | F96: Calciovital D3 625mg Com Rev X 60 | G96: 21069030 | H96: ATIVO | I96: 50 | J96: ='LISTA PREÇO 2022-Vigen 01.02.22'!J96 -> 9.53 | L96: 9.35 | M96: =J96/(100%-$M$5) -> 11.481928 | N96: =$M96*(100%-N$6) -> 9.7596386 | O96: =$M96*(100%-O$6) -> 9.8744578 | P96: =$M96*(100%-P$6) -> 9.9892771 | Q96: =$M96*(100%-Q$6) -> 10.104096 | R96: =$M96*(100%-R$6) -> 10.218916 | S96: =$M96*(100%-S$6) -> 10.333735 | T96: =$M96*(100%-T$6) -> 10.448554 | U96: =$M96*(100%-U$6) -> 10.563373 | ... X96: =$M96*(100%-X$6) -> 11.481928 | Y96: 0 | Z96: 0 | AA96: 0 | AC96: 38.96 | AD96: 31.31 | AE96: 42.29 | AF96: 36.02 | AG96: 48.5 | AH96: 38.43 | AI96: 51.66 | AJ96: 38.69 | AK96: 52 | AL96: 38.96 | AM96: 52.36 | AN96: 40.05 | AO96: 53.79 | AP96: 34.62 | AQ96: 47.86 | AR96: 34.83 | AS96: 48.15 | AT96: 35.04 | AU96: 48.44 | AV96: Neutra | AW96: NÃO SE APLICA - LIBERADOS
A97: Naturelife | B97: Alimentos | C97: 7899898601061 | D97: 19794 | E97: 15000239 | F97: Calciovital D3 B12 Sol Or X 250ml | G97: 21069030 | H97: ATIVO | I97: 36 | J97: ='LISTA PREÇO 2022-Vigen 01.02.22'!J97 -> 5.29 | L97: 5.19 | M97: =J97/(100%-$M$5) -> 6.373494 | N97: =$M97*(100%-N$6) -> 5.4174699 | O97: =$M97*(100%-O$6) -> 5.4812048 | P97: =$M97*(100%-P$6) -> 5.5449398 | Q97: =$M97*(100%-Q$6) -> 5.6086747 | R97: =$M97*(100%-R$6) -> 5.6724096 | S97: =$M97*(100%-S$6) -> 5.7361446 | T97: =$M97*(100%-T$6) -> 5.7998795 | U97: =$M97*(100%-U$6) -> 5.8636145 | ... X97: =$M97*(100%-X$6) -> 6.373494 | Y97: 0 | Z97: 0 | AA97: 0 | AC97: 20.64 | AD97: 16.58 | AE97: 22.39 | AF97: 19.08 | AG97: 25.69 | AH97: 20.36 | AI97: 27.37 | AJ97: 20.5 | AK97: 27.55 | AL97: 20.64 | AM97: 27.74 | AN97: 21.22 | AO97: 28.5 | AP97: 18.34 | AQ97: 25.35 | AR97: 18.45 | AS97: 25.51 | AT97: 18.56 | AU97: 25.66 | AV97: Neutra | AW97: NÃO SE APLICA - LIBERADOS
A98: Naturelife | B98: Alimentos | C98: 7898557141337 | D98: 14033 | E98: 15000236 | F98: Calciovital Kids 250ml 24ct - Farma | G98: 21069030 | H98: ATIVO | I98: 24 | J98: ='LISTA PREÇO 2022-Vigen 01.02.22'!J98 -> 6.35 | L98: 6.23 | M98: =J98/(100%-$M$5) -> 7.6506024 | N98: =$M98*(100%-N$6) -> 6.503012 | O98: =$M98*(100%-O$6) -> 6.5795181 | P98: =$M98*(100%-P$6) -> 6.6560241 | Q98: =$M98*(100%-Q$6) -> 6.7325301 | R98: =$M98*(100%-R$6) -> 6.8090361 | S98: =$M98*(100%-S$6) -> 6.8855422 | T98: =$M98*(100%-T$6) -> 6.9620482 | U98: =$M98*(100%-U$6) -> 7.0385542 | ... X98: =$M98*(100%-X$6) -> 7.6506024 | Y98: 0 | Z98: 0 | AA98: 0 | AC98: 23.74 | AD98: 19.07 | AE98: 25.76 | AF98: 21.95 | AG98: 29.55 | AH98: 23.42 | AI98: 31.48 | AJ98: 23.58 | AK98: 31.69 | AL98: 23.74 | AM98: 31.91 | AN98: 24.4 | AO98: 32.77 | AP98: 21.09 | AQ98: 29.16 | AR98: 21.22 | AS98: 29.34 | AT98: 21.35 | AU98: 29.52 | AV98: Neutra | AW98: NÃO SE APLICA - LIBERADOS
A99: Naturelife | B99: Alimentos | C99: 7898557141115 | D99: 14275 | E99: 15000235 | F99: Deviter Solucao Oral Limao 20ml 200ct - Farma | G99: 21069030 | H99: ATIVO | I99: 200 | J99: ='LISTA PREÇO 2022-Vigen 01.02.22'!J99 -> 6.62 | L99: 6.49 | M99: =J99/(100%-$M$5) -> 7.9759036 | N99: =$M99*(100%-N$6) -> 6.7795181 | O99: =$M99*(100%-O$6) -> 6.8592771 | P99: =$M99*(100%-P$6) -> 6.9390361 | Q99: =$M99*(100%-Q$6) -> 7.0187952 | R99: =$M99*(100%-R$6) -> 7.0985542 | S99: =$M99*(100%-S$6) -> 7.1783133 | T99: =$M99*(100%-T$6) -> 7.2580723 | U99: =$M99*(100%-U$6) -> 7.3378313 | ... X99: =$M99*(100%-X$6) -> 7.9759036 | Y99: 0 | Z99: 9.703 | AA99: 0 | AC99: 31.53 | AD99: 25.33 | AE99: 34.22 | AF99: 29.15 | AG99: 39.25 | AH99: 31.1 | AI99: 41.81 | AJ99: 31.31 | AK99: 42.08 | AL99: 31.53 | AM99: 42.38 | AN99: 32.41 | AO99: 43.53 | AP99: 28.02 | AQ99: 38.74 | AR99: 28.19 | AS99: 38.97 | AT99: 28.36 | AU99: 39.21 | AV99: Neutra | AW99: NÃO SE APLICA - LIBERADOS
A100: Naturelife | B100: Alimentos | C100: 7899898601221 | D100: 20308 | E100: 15000247 | F100: Lactprev 10000 Cap Dura 500mg X 30 | G100: 21069030 | H100: ATIVO | I100: 24 | J100: ='LISTA PREÇO 2022-Vigen 01.02.22'!J100 -> 23.64 | L100: 21.19495 | M100: =J100/(100%-$M$5) -> 28.481928 | N100: =$M100*(100%-N$6) -> 24.209639 | O100: =$M100*(100%-O$6) -> 24.494458 | P100: =$M100*(100%-P$6) -> 24.779277 | Q100: =$M100*(100%-Q$6) -> 25.064096 | R100: =$M100*(100%-R$6) -> 25.348916 | S100: =$M100*(100%-S$6) -> 25.633735 | T100: =$M100*(100%-T$6) -> 25.918554 | U100: =$M100*(100%-U$6) -> 26.203373 | ... X100: =$M100*(100%-X$6) -> 28.481928 | Y100: 0 | Z100: 0 | AA100: 0 | AC100: 57.24 | AD100: 46 | AE100: 62.14 | AF100: 52.92 | AG100: 71.26 | AH100: 56.47 | AI100: 75.92 | AJ100: 56.85 | AK100: 76.41 | AL100: 57.24 | AM100: 76.93 | AN100: 58.84 | AO100: 79.02 | AP100: 50.86 | AQ100: 70.31 | AR100: 51.17 | AS100: 70.74 | AT100: 51.48 | AU100: 71.17 | AV100: Neutra | AW100: NÃO SE APLICA - LIBERADOS
A101: Naturelife | B101: Alimentos | C101: 7898557141054 | D101: 13802 | E101: 15000232 | F101: Lactulife Ameixa 120ml 50fr - Farma | G101: 21069030 | H101: ATIVO | I101: 50 | J101: ='LISTA PREÇO 2022-Vigen 01.02.22'!J101 -> 8.47 | L101: 8.31 | M101: =J101/(100%-$M$5) -> 10.204819 | N101: =$M101*(100%-N$6) -> 8.6740964 | O101: =$M101*(100%-O$6) -> 8.7761446 | P101: =$M101*(100%-P$6) -> 8.8781928 | Q101: =$M101*(100%-Q$6) -> 8.980241 | R101: =$M101*(100%-R$6) -> 9.0822892 | S101: =$M101*(100%-S$6) -> 9.1843373 | T101: =$M101*(100%-T$6) -> 9.2863855 | U101: =$M101*(100%-U$6) -> 9.3884337 | ... X101: =$M101*(100%-X$6) -> 10.204819 | Y101: 0 | Z101: 0 | AA101: 0 | AC101: 37.07 | AD101: 29.79 | AE101: 40.24 | AF101: 34.27 | AG101: 46.14 | AH101: 36.57 | AI101: 49.16 | AJ101: 36.82 | AK101: 49.49 | AL101: 37.07 | AM101: 49.82 | AN101: 38.11 | AO101: 51.18 | AP101: 32.94 | AQ101: 45.54 | AR101: 33.14 | AS101: 45.81 | AT101: 33.34 | AU101: 46.09 | AV101: Neutra | AW101: NÃO SE APLICA - LIBERADOS
A102: Naturelife | B102: Alimentos | C102: 7898557141061 | D102: 13806 | E102: 15000234 | F102: Lactulife Salada De Frutas 120ml 50fr - Farma | G102: 21069030 | H102: ATIVO | I102: 50 | J102: ='LISTA PREÇO 2022-Vigen 01.02.22'!J102 -> 8.47 | L102: 8.31 | M102: =J102/(100%-$M$5) -> 10.204819 | N102: =$M102*(100%-N$6) -> 8.6740964 | O102: =$M102*(100%-O$6) -> 8.7761446 | P102: =$M102*(100%-P$6) -> 8.8781928 | Q102: =$M102*(100%-Q$6) -> 8.980241 | R102: =$M102*(100%-R$6) -> 9.0822892 | S102: =$M102*(100%-S$6) -> 9.1843373 | T102: =$M102*(100%-T$6) -> 9.2863855 | U102: =$M102*(100%-U$6) -> 9.3884337 | ... X102: =$M102*(100%-X$6) -> 10.204819 | Y102: 0 | Z102: 0 | AA102: 0 | AC102: 36.04 | AD102: 28.96 | AE102: 39.12 | AF102: 33.32 | AG102: 44.86 | AH102: 35.55 | AI102: 47.79 | AJ102: 35.79 | AK102: 48.1 | AL102: 36.04 | AM102: 48.44 | AN102: 37.05 | AO102: 49.76 | AP102: 32.02 | AQ102: 44.27 | AR102: 32.22 | AS102: 44.54 | AT102: 32.41 | AU102: 44.81 | AV102: Neutra | AW102: NÃO SE APLICA - LIBERADOS
A103: Naturelife | B103: Alimentos | C103: 7898557147643 | D103: 17491 | E103: 15000228 | F103: Matherlly Gest 1000mg 30comx50ct - Farma | G103: 21069030 | H103: ATIVO | I103: 50 | J103: ='LISTA PREÇO 2022-Vigen 01.02.22'!J103 -> 11.66 | L103: 11.43 | M103: =J103/(100%-$M$5) -> 14.048193 | N103: =$M103*(100%-N$6) -> 11.940964 | O103: =$M103*(100%-O$6) -> 12.081446 | P103: =$M103*(100%-P$6) -> 12.221928 | Q103: =$M103*(100%-Q$6) -> 12.36241 | R103: =$M103*(100%-R$6) -> 12.502892 | S103: =$M103*(100%-S$6) -> 12.643373 | T103: =$M103*(100%-T$6) -> 12.783855 | U103: =$M103*(100%-U$6) -> 12.924337 | ... X103: =$M103*(100%-X$6) -> 14.048193 | Y103: 11.1 | Z103: 14.6363 | AA103: 0 | AC103: 50.47 | AD103: 40.55 | AE103: 54.78 | AF103: 46.66 | AG103: 62.83 | AH103: 49.79 | AI103: 66.93 | AJ103: 50.13 | AK103: 67.38 | AL103: 50.47 | AM103: 67.83 | AN103: 51.88 | AO103: 69.67 | AP103: 44.84 | AQ103: 61.99 | AR103: 45.12 | AS103: 62.38 | AT103: 45.39 | AU103: 62.75 | AV103: Neutra | AW103: NÃO SE APLICA - LIBERADOS
A104: Naturelife | B104: Alimentos | C104: 7898557147650 | D104: 17492 | E104: 15000229 | F104: Matherlly Lact 750mg Novo 30comx50ct - Farma | G104: 21069030 | H104: ATIVO | I104: 50 | J104: ='LISTA PREÇO 2022-Vigen 01.02.22'!J104 -> 11.66 | L104: 11.43 | M104: =J104/(100%-$M$5) -> 14.048193 | N104: =$M104*(100%-N$6) -> 11.940964 | O104: =$M104*(100%-O$6) -> 12.081446 | P104: =$M104*(100%-P$6) -> 12.221928 | Q104: =$M104*(100%-Q$6) -> 12.36241 | R104: =$M104*(100%-R$6) -> 12.502892 | S104: =$M104*(100%-S$6) -> 12.643373 | T104: =$M104*(100%-T$6) -> 12.783855 | U104: =$M104*(100%-U$6) -> 12.924337 | ... X104: =$M104*(100%-X$6) -> 14.048193 | Y104: 0 | Z104: 0 | AA104: 0 | AC104: 48.11 | AD104: 38.66 | AE104: 52.22 | AF104: 44.48 | AG104: 59.89 | AH104: 47.46 | AI104: 63.8 | AJ104: 47.78 | AK104: 64.22 | AL104: 48.11 | AM104: 64.66 | AN104: 49.45 | AO104: 66.41 | AP104: 42.75 | AQ104: 59.1 | AR104: 43.01 | AS104: 59.46 | AT104: 43.27 | AU104: 59.82 | AV104: Neutra | AW104: NÃO SE APLICA - LIBERADOS
... A106: Naturelife | B106: Alimentos | C106: 7899898601337 | D106: 19 | E106: 15000252 | F106: Nutrifort Sol Or X 240ml | G106: 21069030 | H106: ATIVO | I106: 24 | J106: ='LISTA PREÇO 2022-Vigen 01.02.22'!J106 -> 5.29 | L106: 5.19 | M106: =J106/(100%-$M$5) -> 6.373494 | N106: =$M106*(100%-N$6) -> 5.4174699 | O106: =$M106*(100%-O$6) -> 5.4812048 | P106: =$M106*(100%-P$6) -> 5.5449398 | Q106: =$M106*(100%-Q$6) -> 5.6086747 | R106: =$M106*(100%-R$6) -> 5.6724096 | S106: =$M106*(100%-S$6) -> 5.7361446 | T106: =$M106*(100%-T$6) -> 5.7998795 | U106: =$M106*(100%-U$6) -> 5.8636145 | ... X106: =$M106*(100%-X$6) -> 6.373494 | Y106: 0 | Z106: 0 | AA106: 0 | AC106: 15.53 | AD106: 12.48 | AE106: 16.86 | AF106: 14.36 | AG106: 19.33 | AH106: 15.32 | AI106: 20.59 | AJ106: 15.42 | AK106: 20.72 | AL106: 15.53 | AM106: 20.87 | AN106: 15.96 | AO106: 21.43 | AP106: 13.8 | AQ106: 19.08 | AR106: 13.88 | AS106: 19.19 | AT106: 13.97 | AU106: 19.31 | AV106: Neutra | AW106: NÃO SE APLICA - LIBERADOS
A107: Naturelife | B107: Alimentos | C107: 7899898601283 | D107: 20504 | E107: 15000251 | F107: Nutrivit Junior Sol Or X 120ml | G107: 21069030 | H107: ATIVO | I107: 50 | J107: ='LISTA PREÇO 2022-Vigen 01.02.22'!J107 -> 6.35 | M107: =J107/(100%-$M$5) -> 7.6506024 | N107: =$M107*(100%-N$6) -> 6.503012 | O107: =$M107*(100%-O$6) -> 6.5795181 | P107: =$M107*(100%-P$6) -> 6.6560241 | Q107: =$M107*(100%-Q$6) -> 6.7325301 | R107: =$M107*(100%-R$6) -> 6.8090361 | S107: =$M107*(100%-S$6) -> 6.8855422 | T107: =$M107*(100%-T$6) -> 6.9620482 | U107: =$M107*(100%-U$6) -> 7.0385542 | ... X107: =$M107*(100%-X$6) -> 7.6506024 | Y107: 0 | Z107: 0 | AA107: 0 | AC107: 27.85 | AD107: 22.38 | AE107: 30.23 | AF107: 25.75 | AG107: 34.67 | AH107: 27.47 | AI107: 36.93 | AJ107: 27.66 | AK107: 37.18 | AL107: 27.85 | AM107: 37.43 | AN107: 28.63 | AO107: 38.45 | AP107: 24.75 | AQ107: 34.22 | AR107: 24.9 | AS107: 34.42 | AT107: 25.05 | AU107: 34.63 | AV107: Neutra | AW107: NÃO SE APLICA - LIBERADOS
A108: Naturelife | B108: Alimentos | C108: 7899898601450 | D108: 20746 | E108: 15000254 | F108: Nutrivit Sol Or X 240ml | G108: 21069030 | H108: ATIVO | I108: 24 | J108: ='LISTA PREÇO 2022-Vigen 01.02.22'!J108 -> 5.29 | M108: =J108/(100%-$M$5) -> 6.373494 | N108: =$M108*(100%-N$6) -> 5.4174699 | O108: =$M108*(100%-O$6) -> 5.4812048 | P108: =$M108*(100%-P$6) -> 5.5449398 | Q108: =$M108*(100%-Q$6) -> 5.6086747 | R108: =$M108*(100%-R$6) -> 5.6724096 | S108: =$M108*(100%-S$6) -> 5.7361446 | T108: =$M108*(100%-T$6) -> 5.7998795 | U108: =$M108*(100%-U$6) -> 5.8636145 | ... X108: =$M108*(100%-X$6) -> 6.373494 | Y108: 0 | Z108: 0 | AA108: 0 | AC108: 21.66 | AD108: 17.4 | AE108: 23.5 | AF108: 20.02 | AG108: 26.95 | AH108: 21.37 | AI108: 28.73 | AJ108: 21.51 | AK108: 28.91 | AL108: 21.66 | AM108: 29.11 | AN108: 22.27 | AO108: 29.91 | AP108: 19.25 | AQ108: 26.61 | AR108: 19.36 | AS108: 26.76 | AT108: 19.48 | AU108: 26.93 | AV108: Neutra | AW108: NÃO SE APLICA - LIBERADOS
A109: Naturelife | B109: Alimentos | C109: 7899898600996 | D109: 19584 | E109: 15000231 | F109: Osteofix D3 K2 1700mg 3bl X 10com X 24ct - Farma | G109: 21069030 | H109: ATIVO | I109: 24 | J109: ='LISTA PREÇO 2022-Vigen 01.02.22'!J109 -> 28.43 | L109: 27.91871 | M109: =J109/(100%-$M$5) -> 34.253012 | N109: =$M109*(100%-N$6) -> 29.11506 | O109: =$M109*(100%-O$6) -> 29.45759 | P109: =$M109*(100%-P$6) -> 29.80012 | Q109: =$M109*(100%-Q$6) -> 30.142651 | R109: =$M109*(100%-R$6) -> 30.485181 | S109: =$M109*(100%-S$6) -> 30.827711 | T109: =$M109*(100%-T$6) -> 31.170241 | U109: =$M109*(100%-U$6) -> 31.512771 | ... X109: =$M109*(100%-X$6) -> 34.253012 | Y109: 0 | Z109: 0 | AA109: 0 | AC109: 133.45 | AD109: 107.24 | AE109: 144.87 | AF109: 123.39 | AG109: 166.15 | AH109: 131.66 | AI109: 177 | AJ109: 132.55 | AK109: 178.17 | AL109: 133.45 | AM109: 179.35 | AN109: 137.18 | AO109: 184.23 | AP109: 118.58 | AQ109: 163.93 | AR109: 119.29 | AS109: 164.91 | AT109: 120.02 | AU109: 165.92 | AV109: Neutra | AW109: NÃO SE APLICA - LIBERADOS
A110: Naturelife | B110: Alimentos | C110: 7899898600958 | D110: 19969 | E110: 15000241 | F110: Vitaz Az 630mg 60comx50ct - Farma | G110: 21069030 | H110: ATIVO | I110: 50 | J110: ='LISTA PREÇO 2022-Vigen 01.02.22'!J110 -> 9.44 | L110: 8.99 | M110: =J110/(100%-$M$5) -> 11.373494 | N110: =$M110*(100%-N$6) -> 9.6674699 | O110: =$M110*(100%-O$6) -> 9.7812048 | P110: =$M110*(100%-P$6) -> 9.8949398 | Q110: =$M110*(100%-Q$6) -> 10.008675 | R110: =$M110*(100%-R$6) -> 10.12241 | S110: =$M110*(100%-S$6) -> 10.236145 | T110: =$M110*(100%-T$6) -> 10.34988 | U110: =$M110*(100%-U$6) -> 10.463614 | ... X110: =$M110*(100%-X$6) -> 11.373494 | Y110: 0 | Z110: 0 | AA110: 0 | AC110: 35.53 | AD110: 28.55 | AE110: 38.57 | AF110: 32.85 | AG110: 44.23 | AH110: 35.05 | AI110: 47.12 | AJ110: 35.29 | AK110: 47.43 | AL110: 35.53 | AM110: 47.75 | AN110: 36.52 | AO110: 49.05 | AP110: 31.57 | AQ110: 43.64 | AR110: 31.76 | AS110: 43.91 | AT110: 31.96 | AU110: 44.18 | AV110: Neutra | AW110: NÃO SE APLICA - LIBERADOS
A111: Naturelife | B111: Alimentos | C111: 7899898601160 | D111: 19972 | E111: 15000244 | F111: Vitaz Cabelo Pele E Unhas 500mg 60capx50ct - Farma | G111: 21069030 | H111: ATIVO | I111: 50 | J111: ='LISTA PREÇO 2022-Vigen 01.02.22'!J111 -> 9.44 | L111: 8.99 | M111: =J111/(100%-$M$5) -> 11.373494 | N111: =$M111*(100%-N$6) -> 9.6674699 | O111: =$M111*(100%-O$6) -> 9.7812048 | P111: =$M111*(100%-P$6) -> 9.8949398 | Q111: =$M111*(100%-Q$6) -> 10.008675 | R111: =$M111*(100%-R$6) -> 10.12241 | S111: =$M111*(100%-S$6) -> 10.236145 | T111: =$M111*(100%-T$6) -> 10.34988 | U111: =$M111*(100%-U$6) -> 10.463614 | ... X111: =$M111*(100%-X$6) -> 11.373494 | Y111: 0 | Z111: 0 | AA111: 0 | AC111: 35.53 | AD111: 28.55 | AE111: 38.57 | AF111: 32.85 | AG111: 44.23 | AH111: 35.05 | AI111: 47.12 | AJ111: 35.29 | AK111: 47.43 | AL111: 35.53 | AM111: 47.75 | AN111: 36.52 | AO111: 49.05 | AP111: 31.57 | AQ111: 43.64 | AR111: 31.76 | AS111: 43.91 | AT111: 31.96 | AU111: 44.18 | AV111: Neutra | AW111: NÃO SE APLICA - LIBERADOS
A112: Naturelife | B112: Alimentos | C112: 7899898600972 | D112: 19970 | E112: 15000242 | F112: Vitaz Mulher 630mg 60comx50ct - Farma | G112: 21069030 | H112: ATIVO | I112: 50 | J112: ='LISTA PREÇO 2022-Vigen 01.02.22'!J112 -> 9.44 | L112: 8.99 | M112: =J112/(100%-$M$5) -> 11.373494 | N112: =$M112*(100%-N$6) -> 9.6674699 | O112: =$M112*(100%-O$6) -> 9.7812048 | P112: =$M112*(100%-P$6) -> 9.8949398 | Q112: =$M112*(100%-Q$6) -> 10.008675 | R112: =$M112*(100%-R$6) -> 10.12241 | S112: =$M112*(100%-S$6) -> 10.236145 | T112: =$M112*(100%-T$6) -> 10.34988 | U112: =$M112*(100%-U$6) -> 10.463614 | ... X112: =$M112*(100%-X$6) -> 11.373494 | Y112: 0 | Z112: 0 | AA112: 0 | AC112: 35.53 | AD112: 28.55 | AE112: 38.57 | AF112: 32.85 | AG112: 44.23 | AH112: 35.05 | AI112: 47.12 | AJ112: 35.29 | AK112: 47.43 | AL112: 35.53 | AM112: 47.75 | AN112: 36.52 | AO112: 49.05 | AP112: 31.57 | AQ112: 43.64 | AR112: 31.76 | AS112: 43.91 | AT112: 31.96 | AU112: 44.18 | AV112: Neutra | AW112: NÃO SE APLICA - LIBERADOS
A113: Naturelife | B113: Alimentos | C113: 7899898601207 | D113: 19974 | E113: 15000246 | F113: Vitaz Oleo De Peixe Ômega 3 Cap Mole X 120 | G113: 21069030 | H113: ATIVO | I113: 50 | J113: ='LISTA PREÇO 2022-Vigen 01.02.22'!J113 -> 15.73 | L113: 14.1 | M113: =J113/(100%-$M$5) -> 18.951807 | N113: =$M113*(100%-N$6) -> 16.109036 | O113: =$M113*(100%-O$6) -> 16.298554 | P113: =$M113*(100%-P$6) -> 16.488072 | Q113: =$M113*(100%-Q$6) -> 16.67759 | R113: =$M113*(100%-R$6) -> 16.867108 | S113: =$M113*(100%-S$6) -> 17.056627 | T113: =$M113*(100%-T$6) -> 17.246145 | U113: =$M113*(100%-U$6) -> 17.435663 | ... X113: =$M113*(100%-X$6) -> 18.951807 | Y113: 0 | Z113: 0 | AA113: 0 | AC113: 83.67 | AD113: 67.24 | AE113: 90.83 | AF113: 77.36 | AG113: 104.17 | AH113: 82.54 | AI113: 110.96 | AJ113: 83.1 | AK113: 111.7 | AL113: 83.67 | AM113: 112.45 | AN113: 86.01 | AO113: 115.51 | AP113: 74.34 | AQ113: 102.77 | AR113: 74.79 | AS113: 103.39 | AT113: 75.25 | AU113: 104.03 | AV113: Neutra | AW113: NÃO SE APLICA - LIBERADOS
A114: Naturelife | B114: Alimentos | C114: 7899898600989 | D114: 19971 | E114: 15000243 | F114: Vitaz Senior 630mg 60comx50ct - Farma | G114: 21069030 | H114: ATIVO | I114: 50 | J114: ='LISTA PREÇO 2022-Vigen 01.02.22'!J114 -> 9.44 | L114: 8.99 | M114: =J114/(100%-$M$5) -> 11.373494 | N114: =$M114*(100%-N$6) -> 9.6674699 | O114: =$M114*(100%-O$6) -> 9.7812048 | P114: =$M114*(100%-P$6) -> 9.8949398 | Q114: =$M114*(100%-Q$6) -> 10.008675 | R114: =$M114*(100%-R$6) -> 10.12241 | S114: =$M114*(100%-S$6) -> 10.236145 | T114: =$M114*(100%-T$6) -> 10.34988 | U114: =$M114*(100%-U$6) -> 10.463614 | ... X114: =$M114*(100%-X$6) -> 11.373494 | Y114: 0 | Z114: 0 | AA114: 0 | AC114: 35.53 | AD114: 28.55 | AE114: 38.57 | AF114: 32.85 | AG114: 44.23 | AH114: 35.05 | AI114: 47.12 | AJ114: 35.29 | AK114: 47.43 | AL114: 35.53 | AM114: 47.75 | AN114: 36.52 | AO114: 49.05 | AP114: 31.57 | AQ114: 43.64 | AR114: 31.76 | AS114: 43.91 | AT114: 31.96 | AU114: 44.18 | AV114: Neutra | AW114: NÃO SE APLICA - LIBERADOS
A115: Naturelife | B115: Alimentos | C115: 7899898601535 | D115: 22393 | E115: 15000259 | F115: Viter C Sol Or X 20ml | G115: 21069030 | H115: ATIVO | I115: 100 | J115: ='LISTA PREÇO 2022-Vigen 01.02.22'!J115 -> 1.6 | L115: 1.45 | M115: =J115/(100%-$M$5) -> 1.9277108 | N115: =$M115*(100%-N$6) -> 1.6385542 | O115: =$M115*(100%-O$6) -> 1.6578313 | P115: =$M115*(100%-P$6) -> 1.6771084 | Q115: =$M115*(100%-Q$6) -> 1.6963855 | R115: =$M115*(100%-R$6) -> 1.7156627 | S115: =$M115*(100%-S$6) -> 1.7349398 | T115: =$M115*(100%-T$6) -> 1.7542169 | U115: =$M115*(100%-U$6) -> 1.773494 | ... X115: =$M115*(100%-X$6) -> 1.9277108 | Y115: 0 | Z115: 0 | AA115: 0 | AC115: 12.2 | AD115: 9.8 | AE115: 13.23 | AF115: 11.28 | AG115: 15.19 | AH115: 12.03 | AI115: 16.17 | AJ115: 12.11 | AK115: 16.27 | AL115: 12.2 | AM115: 16.4 | AN115: 12.54 | AO115: 16.84 | AP115: 10.84 | AQ115: 14.99 | AR115: 10.91 | AS115: 15.08 | AT115: 10.97 | AU115: 15.17 | AV115: Neutra | AW115: NÃO SE APLICA - LIBERADOS
J116: ='LISTA PREÇO 2022-Vigen 01.02.22'!#REF! -> #REF! | M116: =J116/(100%-$M$5) -> #REF! | N116: =$M116*(100%-N$6) -> #REF! | O116: =$M116*(100%-O$6) -> #REF! | P116: =$M116*(100%-P$6) -> #REF! | Q116: =$M116*(100%-Q$6) -> #REF! | R116: =$M116*(100%-R$6) -> #REF! | S116: =$M116*(100%-S$6) -> #REF! | T116: =$M116*(100%-T$6) -> #REF! | U116: =$M116*(100%-U$6) -> #REF! | ... X116: =$M116*(100%-X$6) -> #REF! | Y116: 0 | Z116: 0 | AA116: 0
A117: Lançamentos | J117: ='LISTA PREÇO 2022-Vigen 01.02.22'!#REF! -> #REF! | M117: =J117/(100%-$M$5) -> #REF! | N117: =$M117*(100%-N$6) -> #REF! | O117: =$M117*(100%-O$6) -> #REF! | P117: =$M117*(100%-P$6) -> #REF! | Q117: =$M117*(100%-Q$6) -> #REF! | R117: =$M117*(100%-R$6) -> #REF! | S117: =$M117*(100%-S$6) -> #REF! | T117: =$M117*(100%-T$6) -> #REF! | U117: =$M117*(100%-U$6) -> #REF! | ... X117: =$M117*(100%-X$6) -> #REF! | Y117: 0 | Z117: 0 | AA117: 0
A118: Naturelife | B118: Alimentos | C118: 7899898601498 | D118: 22149 | E118: 15000258 | F118: DVITER COM REV 1000UI X 30 | G118: 21069030 | H118: ATIVO | I118: 50 | J118: ='LISTA PREÇO 2022-Vigen 01.02.22'!J176 -> 5.1 | L118: 0 | M118: =J118/(100%-$M$5) -> 6.1445783 | N118: =$M118*(100%-N$6) -> 5.2228916 | O118: =$M118*(100%-O$6) -> 5.2843373 | P118: =$M118*(100%-P$6) -> 5.3457831 | Q118: =$M118*(100%-Q$6) -> 5.4072289 | R118: =$M118*(100%-R$6) -> 5.4686747 | S118: =$M118*(100%-S$6) -> 5.5301205 | T118: =$M118*(100%-T$6) -> 5.5915663 | U118: =$M118*(100%-U$6) -> 5.653012 | ... X118: =$M118*(100%-X$6) -> 6.1445783 | Y118: 0 | Z118: 0 | AA118: 0 | AC118: 59 | AD118: 47.41 | AE118: 64.04 | AF118: 54.55 | AG118: 73.45 | AH118: 58.21 | AI118: 78.25 | AJ118: 58.6 | AK118: 78.77 | AL118: 59 | AM118: 79.29 | AN118: 60.65 | AO118: 81.45 | AP118: 52.42 | AQ118: 72.47 | AR118: 52.74 | AS118: 72.91 | AT118: 53.06 | AU118: 73.35 | AV118: Neutra | AW118: NÃO SE APLICA - LIBERADOS
A119: Naturelife | B119: Alimentos | C119: 7899898601467 | D119: 21226 | E119: 15000256 | F119: DVITER COM REV 2000UI X 30 | G119: 21069030 | H119: ATIVO | I119: 50 | J119: ='LISTA PREÇO 2022-Vigen 01.02.22'!J177 -> 5.54 | L119: 0 | M119: =J119/(100%-$M$5) -> 6.6746988 | N119: =$M119*(100%-N$6) -> 5.673494 | O119: =$M119*(100%-O$6) -> 5.740241 | P119: =$M119*(100%-P$6) -> 5.806988 | Q119: =$M119*(100%-Q$6) -> 5.8737349 | R119: =$M119*(100%-R$6) -> 5.9404819 | S119: =$M119*(100%-S$6) -> 6.0072289 | T119: =$M119*(100%-T$6) -> 6.0739759 | U119: =$M119*(100%-U$6) -> 6.1407229 | ... X119: =$M119*(100%-X$6) -> 6.6746988 | Y119: 0 | Z119: 0 | AA119: 0 | AC119: 76.75 | AD119: 61.67 | AE119: 83.31 | AF119: 70.96 | AG119: 95.55 | AH119: 75.72 | AI119: 101.8 | AJ119: 76.23 | AK119: 102.46 | AL119: 76.75 | AM119: 103.15 | AN119: 78.89 | AO119: 105.95 | AP119: 68.2 | AQ119: 94.28 | AR119: 68.61 | AS119: 94.85 | AT119: 69.03 | AU119: 95.43 | AV119: Neutra | AW119: NÃO SE APLICA - LIBERADOS
A120: Naturelife | B120: Alimentos | C120: 7899898601474 | D120: 21225 | E120: 15000255 | F120: DVITER SOL GOT 500UI X10ML | G120: 21069030 | H120: ATIVO | I120: 200 | J120: ='LISTA PREÇO 2022-Vigen 01.02.22'!J178 -> 7.12 | L120: 6.99 | M120: =J120/(100%-$M$5) -> 8.5783133 | N120: =$M120*(100%-N$6) -> 7.2915663 | O120: =$M120*(100%-O$6) -> 7.3773494 | P120: =$M120*(100%-P$6) -> 7.4631325 | Q120: =$M120*(100%-Q$6) -> 7.5489157 | R120: =$M120*(100%-R$6) -> 7.6346988 | S120: =$M120*(100%-S$6) -> 7.7204819 | T120: =$M120*(100%-T$6) -> 7.8062651 | U120: =$M120*(100%-U$6) -> 7.8920482 | ... X120: =$M120*(100%-X$6) -> 8.5783133 | Y120: 0 | Z120: 0 | AA120: 0 | AC120: 32.5 | AD120: 26.11 | AE120: 35.27 | AF120: 30.05 | AG120: 40.46 | AH120: 32.06 | AI120: 43.1 | AJ120: 32.28 | AK120: 43.39 | AL120: 32.5 | AM120: 43.68 | AN120: 33.41 | AO120: 44.87 | AP120: 28.88 | AQ120: 39.93 | AR120: 29.05 | AS120: 40.16 | AT120: 29.23 | AU120: 40.41 | AV120: Neutra | AW120: NÃO SE APLICA - LIBERADOS
A121: Natulab | B121: Medicamentos | C121: 7899470807850 | D121: 43211 | E121: 15000205 | F121: DVITERD3 CAP MOLE 5.000UI X 30 | G121: 30045050 | H121: LANÇTOS | I121: 50 | J121: ='LISTA PREÇO 2022-Vigen 01.02.22'!J179 -> 15.28 | L121: 15 | M121: =J121/(100%-$M$5) -> 18.409639 | N121: =$M121*(100%-N$6) -> 15.648193 | O121: =$M121*(100%-O$6) -> 15.832289 | P121: =$M121*(100%-P$6) -> 16.016386 | Q121: =$M121*(100%-Q$6) -> 16.200482 | R121: =$M121*(100%-R$6) -> 16.384578 | S121: =$M121*(100%-S$6) -> 16.568675 | T121: =$M121*(100%-T$6) -> 16.752771 | U121: =$M121*(100%-U$6) -> 16.936867 | ... X121: =$M121*(100%-X$6) -> 18.409639 | Y121: 0 | Z121: 0 | AA121: 0 | AC121: 55.89 | AD121: 44.6 | AE121: 59.82 | AF121: 51.54 | AG121: 68.84 | AH121: 55.11 | AI121: 73.45 | AJ121: 55.5 | AK121: 73.96 | AL121: 55.89 | AM121: 74.46 | AN121: 57.51 | AO121: 76.55 | AP121: 47.98 | AQ121: 66.33 | AR121: 48.27 | AS121: 66.73 | AT121: 48.56 | AU121: 67.13 | AV121: Negativa | AW121: Grupo 1
A122: Natulab | B122: Medicamentos | C122: 7899470807874 | D122: 43207 | E122: 15000202 | F122: DVITERD3 CAP MOLE 7.000UI X 08 | G122: 30045050 | H122: LANÇTOS | I122: 80 | J122: ='LISTA PREÇO 2022-Vigen 01.02.22'!J180 -> 5.81 | L122: 5.7 | M122: =J122/(100%-$M$5) -> 7 | N122: =$M122*(100%-N$6) -> 5.95 | O122: =$M122*(100%-O$6) -> 6.02 | P122: =$M122*(100%-P$6) -> 6.09 | Q122: =$M122*(100%-Q$6) -> 6.16 | R122: =$M122*(100%-R$6) -> 6.23 | S122: =$M122*(100%-S$6) -> 6.3 | T122: =$M122*(100%-T$6) -> 6.37 | U122: =$M122*(100%-U$6) -> 6.44 | ... X122: =$M122*(100%-X$6) -> 7 | Y122: 0 | Z122: 0 | AA122: 0 | AC122: 47.4 | AD122: 37.82 | AE122: 50.73 | AF122: 43.71 | AG122: 58.38 | AH122: 46.74 | AI122: 62.3 | AJ122: 47.06 | AK122: 62.71 | AL122: 47.4 | AM122: 63.15 | AN122: 48.77 | AO122: 64.91 | AP122: 40.69 | AQ122: 56.25 | AR122: 40.94 | AS122: 56.6 | AT122: 41.19 | AU122: 56.94 | AV122: Negativa | AW122: Grupo 1
A123: Natulab | B123: Medicamentos | C123: 7899470807553 | D123: 43208 | E123: 15000203 | F123: DVITERD3 CAP MOLE 10.000 X 04 | G123: 30045050 | H123: LANÇTOS | I123: 80 | J123: ='LISTA PREÇO 2022-Vigen 01.02.22'!J181 -> 5.3 | L123: 5.2 | M123: =J123/(100%-$M$5) -> 6.3855422 | N123: =$M123*(100%-N$6) -> 5.4277108 | O123: =$M123*(100%-O$6) -> 5.4915663 | P123: =$M123*(100%-P$6) -> 5.5554217 | Q123: =$M123*(100%-Q$6) -> 5.6192771 | R123: =$M123*(100%-R$6) -> 5.6831325 | S123: =$M123*(100%-S$6) -> 5.746988 | T123: =$M123*(100%-T$6) -> 5.8108434 | U123: =$M123*(100%-U$6) -> 5.8746988 | ... X123: =$M123*(100%-X$6) -> 6.3855422 | Y123: 0 | Z123: 0 | AA123: 0 | AC123: 41.204 | AD123: 32.88 | AE123: 44.1 | AF123: 37.99 | AG123: 50.74 | AH123: 40.63 | AI123: 54.15 | AJ123: 40.91 | AK123: 54.51 | AL123: 41.204 | AM123: 54.9 | AN123: 42.4 | AO123: 56.44 | AP123: 35.37 | AQ123: 48.9 | AR123: 35.59 | AS123: 49.2 | AT123: 35.8 | AU123: 49.49 | AV123: Negativa | AW123: Grupo 1
